Workbook

Sheet Compras 2026
A1: =SUBTOTAL(3,A3:A1095) -> 204 | D1: =SUBTOTAL(9,D3:D896) -> 1.7419035e+08 | I1: =SUBTOTAL(3,I3:I500) -> 118 | J1: =SUBTOTAL(3,J3:J500) -> 121 | N1: =SUBTOTAL(3,N3:N896) -> 82 | O1: =COUNTIF(O3:O301,"FINALIZADO") -> 82
A2: PROCESSO N° | B2: DESCRIÇÃO | C2: DATA DE CRIAÇÃO | D2: VALOR PREVISTO | E2: FONTE DE RECURSO | F2: MODALIDADE | G2: DATA DO PREGÃO | H2: CONTRATO ASSINADO | I2: EMPENHO ASSINADO | J2: EMPENHO E CONTRATO ENVIADO AO FORNECEDOR (DATA) | K2: PRAZO DE ENTREGA (DIAS) | L2: DATA PREV. DE ENTREGA | M2: COBRADO ENTREGA NO DIA | N2: MATERIAL ENTREGUE (DATA) | O2: SITUAÇÃO | P2: OBSERVAÇÃO
A3: 23.536.933-8 | B3: Dispensa de menor valor - Dispensa de contratação de prestação de serviço de Dosimetria, para atender a UETC Tarumã da Polícia Científica do Paraná | C3: 45715 | D3: 10560 | E3: CUSTEIO | F3: Dispensa de Licitação | H3: 45839 | I3: 45848 | J3: 45852 | K3: 30 | L3: =IF(ISBLANK(J3), "", SUM(J3, K3)) -> 45882 | N3: 45839 | O3: FINALIZADO
A4: 23.577.593-0 | B4: Contratação de Serviço de empresa especializada em lavagem de roupa hospitalar - Lavanderia | C4: 45714 | D4: 1778400 | E4: CUSTEIO | F4: Licitação | G4: 45875 | H4: 45932 | I4: 45951 | J4: 45951 | K4: 30 | L4: =IF(ISBLANK(J4), "", SUM(J4, K4)) -> 45981 | N4: 45981 | O4: FINALIZADO
A5: 23.432.467-5 | B5: [Verba Parlamentar Moro] Aquisição de Pipetador Automático para preparo de placas para a SGMF | C5: 45734 | D5: 531310 | E5: CUSTEIO | F5: Inexigibilidade | K5: 30 | L5: =IF(ISBLANK(J5), "", SUM(J5, K5)) | O5: ARQUIVADO
A6: 23.711.290-3 | B6: Dispensa de Licitação - Aquisição de Maleta de Perícia tipo 02, para atender as necessidades da Polícia Científica do Paraná, através do Convênio Federal No 936068/2022, No Processo: 08020002865202206 | C6: 45750 | D6: 106123 | E6: INVESTIMENTO | F6: Dispensa de Licitação | H6: 45903 | I6: 45922 | J6: 45923 | K6: 90 | L6: =IF(ISBLANK(J6), "", SUM(J6, K6)) -> 46013 | M6: 45992 | O6: TRAMITANDO
A7: 23.336.634-0 | B7: Contratação do serviço de ampliação da rede de gases especiais visando a instalação de novos equipamentos laboratoriais na UETC Curitiba - Tarumã | C7: 45674 | D7: 171111.52 | E7: CUSTEIO | F7: Licitação | H7: 45917 | I7: 45937 | J7: 45936 | K7: 15 | L7: =IF(ISBLANK(J7), "", SUM(J7, K7)) -> 45951 | N7: 45951 | O7: FINALIZADO
A8: 23.356.092-8 | B8: Aquisição de “Kits de Controle de Acesso”, para atender a demanda da Divisão de Custódia de Vestígios da Polícia Científica do Paraná | C8: 45678 | D8: 193026.4 | E8: INVESTIMENTO | F8: Licitação | K8: 30 | L8: =IF(ISBLANK(J8), "", SUM(J8, K8)) | O8: TRAMITANDO
A9: 23.708.709-7 | B9: Solicita abertura para aquisição de 60 Purificadores de água e refil de filtro, a fim de atender as demandas da Polícia Científica do Paraná. | C9: 45751 | D9: 85981.41 | E9: INVESTIMENTO | F9: Licitação | K9: 30 | L9: =IF(ISBLANK(J9), "", SUM(J9, K9)) | O9: TRAMITANDO
A10: 23.822.468-3 | B10: Contratação de empresa especializada na prestação de serviços de locação de veículos adaptados para transporte de cadáveres (COTRANS) - o protocolo que correu o processo licitatório, 22.469.724-4, foi arquivado na SEAP. | C10: 45763 | D10: 33480720 | E10: CUSTEIO | F10: Licitação | G10: 45702 | H10: 45820 | I10: 45868 | J10: 45821 | K10: 60 | L10: =IF(ISBLANK(J10), "", SUM(J10, K10)) -> 45881 | O10: TRAMITANDO
A11: 23.750.119-5 | B11: SEDCA Aquisição de uma Plataforma de Processamento Rápido de DNA | C11: 45747 | D11: 990000 | E11: INVESTIMENTO | F11: Inexigibilidade | H11: 45999 | I11: 46003 | J11: 46003 | K11: 30 | L11: =IF(ISBLANK(J11), "", SUM(J11, K11)) -> 46033 | O11: TRAMITANDO
A12: 23.391.860-1 | B12: SRP Coffee Break - Aquisição através do Registro de Preço do PE 494/2023, na modalidade PARTICIPANTE, de Serviço de Coffee Break para atender as necessidades da Unidade de Execução Técnico-Científica de Curitiba da Polícia Científica do Paraná. VALIDADE DA ATA 23/09/2025 | C12: 45686 | D12: 50000 | E12: CUSTEIO | F12: SRP Estadual | G12: 45946 | H12: 45733 | I12: 45748 | J12: 45756 | K12: 360 | L12: =IF(ISBLANK(J12), "", SUM(J12, K12)) -> 46116 | N12: 45751 | O12: FINALIZADO
A13: 23.384.464-0 | B13: AQUISIÇÃO DE SOLUÇÕES TAMPÃO E KCl, VIA PREGÃO ELETRÔNICO 851/2023 LOTES 01, 02 e 03, VALIDADE DA ATA: 19/02/2025, NA MODALIDADE PARTICIPANTE, PARA SUPRIR A DEMANDA DOS LABORATÓRIOS FORENSES DA POLÍCIA CIENTÍFICA DO PARANÁ. | C13: 45688 | D13: 233.25 | E13: CUSTEIO | F13: SRP Estadual | L13: =IF(ISBLANK(J13), "", SUM(J13, K13)) | O13: ARQUIVADO
A14: 23.427.285-3 | B14: SRP Máscara e Avental Descartável - Aquisição através do Registro de Preço do PE 706/2024, na modalidade PARTICIPANTE, de Máscara e Avental Descartável para atender as necessidades das unidades da Polícia Científica do Paraná. | C14: 45698 | D14: 17473 | E14: CUSTEIO | F14: SRP Estadual | G14: 46044 | I14: 45702 | J14: 45786 | K14: 30 | L14: =IF(ISBLANK(J14), "", SUM(J14, K14)) -> 45816 | M14: 45805 | N14: 45833 | O14: FINALIZADO
A15: 23.549.843-0 | B15: SRP Insumos de Laboratórios - Aquisição através do Registro de Preço do PE 163/2023, na modalidade PARTICIPANTE de Insumos de Laboratórios para atender as unidades da Polícia Científica do Paraná. VALIDADE DA ATA: 17/02/2026 | C15: 45712 | D15: 68276.4 | E15: CUSTEIO | F15: SRP Estadual | I15: 45806 | J15: 45812 | K15: 15 | L15: =IF(ISBLANK(J15), "", SUM(J15, K15)) -> 45827 | M15: 45910 | N15: 45915 | O15: FINALIZADO
A16: 23.539.216-0 | B16: Aquisição de Câmaras Frias pelo SRP no 1388/2024. 7 Unidades: 1 Seção Ambiental, 1 Telêmaco Borba, 3 Toledo, 1 Maringá e 1 Paranaguá | C16: 45735 | D16: 292600 | E16: INVESTIMENTO | F16: SRP Estadual | I16: 45800 | J16: 45792 | K16: 45 | L16: =IF(ISBLANK(J16), "", SUM(J16, K16)) -> 45837 | M16: 45862 | N16: 45867 | O16: FINALIZADO
A17: 23.726.102-0 | B17: SRP Papel Sulfite A4 - Aquisição através do Registro de Preço do PE 33/2024, na modalidade PARTICIPANTE, de Papel Sulfite A4 para atender as necessidades das unidades da Polícia Científica do Paraná. | C17: 45743 | D17: 19470 | E17: CUSTEIO | F17: SRP Estadual | I17: 45775 | J17: 45826 | K17: 30 | L17: =IF(ISBLANK(J17), "", SUM(J17, K17)) -> 45856 | N17: 45846 | O17: FINALIZADO
A18: 23.814.144-3 | B18: SRP Almoxarife - Contratação através do Registro de Preço do PE 1934/2024, na modalidade PARTICIPANTE, de Posto, Almoxarife, 40 horas semanais, De segunda a sexta para atender as necessidades do Almoxarifado Central da Polícia Científica do Paraná. | C18: 45762 | D18: 57317.76 | E18: CUSTEIO | F18: SRP Estadual | L18: =IF(ISBLANK(J18), "", SUM(J18, K18)) | O18: ARQUIVADO
A19: 23.852.416-4 | B19: SRP Água Mineral - Aquisição através do Registro de Preço do PE 1089/2024 na modalidade PARTICIPANTE, de Água Mineral para atender as necessidades das unidades da Polícia Científica do Paraná. VALIDADE DA ATA: 07/04/2026 | C19: 45763 | D19: 89853.91 | E19: CUSTEIO | F19: SRP Estadual | I19: 45840 | J19: 45852 | K19: 10 | L19: =IF(ISBLANK(J19), "", SUM(J19, K19)) -> 45862 | N19: 45862 | O19: FINALIZADO
A20: 23.759.626-9 | B20: Adesão em ATA DE REGISTRO DE PREÇO da PCP-SC, para aquisição de álcool metílico, álcool isopropílico e luminol. | C20: 45755 | D20: 2375 | E20: CUSTEIO | F20: SRP Estadual (Carona) | H20: 45852 | I20: 45883 | J20: 45852 | K20: 60 | L20: =IF(ISBLANK(J20), "", SUM(J20, K20)) -> 45912 | M20: 45890 | N20: 45887 | O20: FINALIZADO
A21: 23.529.878-3 | B21: Trata-se de abertura de dispensa de licitação para aquisição de embalagem simples. | C21: 45713 | D21: 53179.5 | E21: CUSTEIO | F21: Dispensa de Licitação | I21: 45777 | J21: 45784 | K21: 30 | L21: =IF(ISBLANK(J21), "", SUM(J21, K21)) -> 45814 | N21: 45799 | O21: FINALIZADO
A22: 23.550.851-6 | B22: dispensa eletrônica de licitação para aquisição de insumos para a realização de exames de identificação veicular, Em Aço Rápido; lixa, graxa, removedor de esmalte (acetona) estopa | C22: 45715 | D22: 51776 | E22: CUSTEIO | F22: Dispensa de Licitação | I22: 45792 | J22: 45796 | K22: 30 | L22: =IF(ISBLANK(J22), "", SUM(J22, K22)) -> 45826 | N22: 45824 | O22: FINALIZADO
A23: 23.590.694-5 | B23: dispensa eletrônica de processo licitatório, de Artigos de Higiene Pessoal - Sabonete Líquido | C23: 45722 | D23: 16271.44 | E23: CUSTEIO | F23: Dispensa de Licitação | I23: 45786 | J23: 45792 | K23: 30 | L23: =IF(ISBLANK(J23), "", SUM(J23, K23)) -> 45822 | N23: 45804 | O23: FINALIZADO
A24: 23.444.059-4 | B24: [Verba Parlamentar - Moro] - Aquisição de Insumos para o Analisador Genético 3500 | C24: 45692 | D24: 360551.24 | E24: CUSTEIO | F24: Inexigibilidade | L24: =IF(ISBLANK(J24), "", SUM(J24, K24)) | O24: ARQUIVADO
A25: 23.711.352-7 | B25: [Verba Parlamentar - Moro] - Aquisição Sequenciador com Sistema de Eletroforese capilar | C25: 45741 | D25: 1538000 | E25: CUSTEIO | F25: Inexigibilidade | K25: 90 | L25: =IF(ISBLANK(J25), "", SUM(J25, K25)) | O25: ARQUIVADO
A26: 23.678.445-2 | B26: [Emenda Parlamentar - Sérgio Moro] Aquisição de um moinho moedor de ossos | C26: 45734 | D26: 434305.84 | E26: CUSTEIO | F26: Inexigibilidade | K26: 90 | L26: =IF(ISBLANK(J26), "", SUM(J26, K26)) | O26: ARQUIVADO
A27: 23.503.010-1 | B27: SRP CAIXA VAZADA - AQUISIÇÃO ATRAVÉS DO REGISTRO DE PREÇO DO PE 979/2023, NA MODALIDADE PARTICIPANTE, DE CAIXA VAZADA, COR: AZUL, CAPACIDADE: 49 LITROS | C27: 45702 | D27: 6480 | E27: CUSTEIO | F27: SRP Estadual | G27: 46003 | I27: 45709 | J27: 45715 | K27: 30 | L27: =IF(ISBLANK(J27), "", SUM(J27, K27)) -> 45745 | N27: 45761 | O27: FINALIZADO
A28: 23.541.254-3 | B28: SRP Reagentes Químicos - Aquisição através do Registro de Preço do PE 975/2023, na modalidade PARTICIPANTE de Reagentes Químicos para atender as unidades da Polícia Científica do Paraná. VALIDADE DA ATA: 28/05/2025 | C28: 45712 | D28: 25816.46 | E28: CUSTEIO | F28: SRP Estadual | I28: 45721 | J28: 45733 | K28: 30 | L28: =IF(ISBLANK(J28), "", SUM(J28, K28)) -> 45763 | M28: 45861 | N28: 45910 | O28: FINALIZADO
A29: 23.581.473-0 | B29: SRP Bandeiras - Aquisição através do Registro de Preço do PE 449/2023, na modalidade PARTICIPANTE, de Bandeiras para atender as necessidades das unidades da Polícia Científica do Paraná. | C29: 45717 | D29: 4666 | E29: CUSTEIO | F29: SRP Estadual | G29: 46066 | I29: 45729 | J29: 45733 | K29: 30 | L29: =IF(ISBLANK(J29), "", SUM(J29, K29)) -> 45763 | N29: 45744 | O29: FINALIZADO
A30: 23.659.354-1 | B30: SRP Envelope, TIPO: Saco, COR: Branca - Aquisição através do Registro de Preço do PE 25/2023, na modalidade PARTICIPANTE, de Envelope, TIPO: Saco, COR: Branca para atender as necessidades das unidades da Polícia Científica do Paraná. | C30: 45733 | D30: 192 | E30: CUSTEIO | F30: SRP Estadual | G30: 46007 | I30: 45737 | J30: 45740 | K30: 30 | L30: =IF(ISBLANK(J30), "", SUM(J30, K30)) -> 45770 | N30: 45775 | O30: FINALIZADO
A31: 23.650.629-0 | B31: SRP Caneta Esferográfica - Aquisição através do Registro de Preço do PE 28/2023, na modalidade PARTICIPANTE, de Caneta Esferográfica para atender as necessidades das unidades da Polícia Científica do Paraná. | C31: 45729 | D31: 976.92 | E31: CUSTEIO | F31: SRP Estadual | I31: 45736 | J31: 45740 | K31: 30 | L31: =IF(ISBLANK(J31), "", SUM(J31, K31)) -> 45770 | N31: 45772 | O31: FINALIZADO
A32: 23.642.186-4 | B32: SRP Sabão em Pó, Limpa Vidros e Lustra Móveis - Aquisição através do Registro de Preço do PE 113/2024, na modalidade PARTICIPANTE, de Sabão em Pó, Limpa Vidros e Lustra Móveis | C32: 45728 | D32: 1631.75 | E32: CUSTEIO | F32: SRP Estadual | I32: 45740 | J32: 45748 | K32: 30 | L32: =IF(ISBLANK(J32), "", SUM(J32, K32)) -> 45778 | N32: 45803 | O32: FINALIZADO
A33: 23.574.455-4 | B33: SRP Materiais Diversos para Laboratório - Aquisição através do Registro de Preço do PE 747/2023, na modalidade PARTICIPANTE, de Materiais Diversos para Laboratório para atender as necessidades das unidades da Polícia Científica do Paraná. | C33: 45716 | D33: 11757.8 | E33: CUSTEIO | F33: SRP Estadual | I33: 45729 | J33: 45770 | K33: 30 | L33: =IF(ISBLANK(J33), "", SUM(J33, K33)) -> 45800 | M33: 45834 | N33: 45839 | O33: FINALIZADO
A34: 23.326.534-9 | B34: SRP CARONA - Adesão de Aquisição através do Registro de Preço do PE 185/2024, de aquisição de Seringa, Descartável, Estéril, 20ml (sem agulha | C34: 45673 | D34: 7000 | E34: CUSTEIO | F34: SRP Estadual (Carona) | G34: 46006 | I34: 45686 | J34: 45692 | K34: 30 | L34: =IF(ISBLANK(J34), "", SUM(J34, K34)) -> 45722 | N34: 45701 | O34: FINALIZADO
A35: 23.468.057-9 | B35: SRP Água Sanitária e Desodorizador de Ambiente - Aquisição através do Registro de Preço do PE 112/2024, na modalidade PARTICIPANTE, de Água Sanitária e Desodorizador de Ambiente para atender as necessidades das unidades da Polícia Científica do Paraná. VALIDADE DA ATA: 02/02/2026 | C35: 45698 | D35: 3078.15 | E35: CUSTEIO | F35: SRP Estadual | G35: 46055 | I35: 45702 | J35: 45722 | K35: 30 | L35: =IF(ISBLANK(J35), "", SUM(J35, K35)) -> 45752 | N35: 45730 | O35: FINALIZADO
A36: 23.518.554-7 | B36: SRP Material de Limpeza - Grupo I - Aquisição através do Registro de Preço do PE 1026/2023, na modalidade PARTICIPANTE de Material de Limpeza - Grupo I - Escova, Pá, desentupidor . VALIDADE DA ATA: 09/10/2025 | C36: 45705 | D36: 1301.91 | E36: CUSTEIO | F36: SRP Estadual | G36: 45939 | I36: 45707 | J36: 45723 | K36: 30 | L36: =IF(ISBLANK(J36), "", SUM(J36, K36)) -> 45753 | N36: 45737 | O36: FINALIZADO
A37: 23.443.596-5 | B37: SRP Caixa Arquivo - Aquisição através do Registro de Preço do PE 27/2023, na modalidade PARTICIPANTE, de Caixa Arquivo para atender as necessidades das unidades da Polícia Científica do Paraná. VALIDADE DA ATA: 27/02/2025 | C37: 45692 | D37: 2862 | E37: CUSTEIO | F37: SRP Estadual | G37: 45715 | I37: 45700 | J37: 45708 | K37: 30 | L37: =IF(ISBLANK(J37), "", SUM(J37, K37)) -> 45738 | N37: 45728 | O37: FINALIZADO
A38: 23.510.701-5 | B38: SRP Garrafa Térmica - Aquisição através do Registro de Preço do PE 366/2023, na modalidade PARTICIPANTE de Garrafa Térmica 1,8 Litros para atender as unidades da Polícia Científica do Paraná. VALIDADE DA ATA: 01/09/2025 | C38: 45705 | D38: 2847.5 | E38: CUSTEIO | F38: SRP Estadual | G38: 45901 | I38: 45716 | J38: 45722 | K38: 30 | L38: =IF(ISBLANK(J38), "", SUM(J38, K38)) -> 45752 | N38: 45737 | O38: FINALIZADO
A39: 23.460.149-0 | B39: SRP Luva Nitrílica - Aquisição através do Registro de Preço do PE 747/2023, na modalidade PARTICIPANTE, de Luva Nitrílica para atender as necessidades das unidades da Polícia Científica do Paraná. VALIDADE DA ATA: 29/04/2025 | C39: 45695 | D39: 99500.4 | E39: CUSTEIO | F39: SRP Estadual | G39: 45776 | I39: 45701 | J39: 45729 | K39: 30 | L39: =IF(ISBLANK(J39), "", SUM(J39, K39)) -> 45759 | N39: 45742 | O39: FINALIZADO
A40: 23.456.626-1 | B40: Solicitação de compra por dispensa de licitação de envelopes cartão. | C40: 45735 | D40: 2600 | E40: CUSTEIO | F40: Dispensa de Licitação | I40: 45818 | J40: 45824 | K40: 30 | L40: =IF(ISBLANK(J40), "", SUM(J40, K40)) -> 45854 | N40: 45847 | O40: FINALIZADO
A41: 21.027.878-8 | B41: Certame | PEI90968-23 | Análise docs complementares (30/01/25) | COLETES BALÍSTICOS VIA SRP - SESP | C41: 45687 | D41: 0 | E41: INVESTIMENTO | F41: SRP Estadual | L41: =IF(ISBLANK(J41), "", SUM(J41, K41)) | O41: TRAMITANDO
A42: 23.551.931-3 | B42: Processo de inexigibilidade para a aquisição de 200 (duzentas) inscrições para o congresso Interforensics | C42: 45727 | D42: 110000 | E42: CUSTEIO | F42: Inexigibilidade | H42: 45868 | I42: 45877 | J42: 45869 | K42: 30 | L42: =IF(ISBLANK(J42), "", SUM(J42, K42)) -> 45899 | N42: 45870 | O42: FINALIZADO
A43: 23.846.805-1 | B43: Solicitação para abertura de processo licitatório para manutenção preventiva e corretiva de dois Espectrômetros Raman da Seção de Química Forense da Polícia Científica do Paraná. | C43: 45763 | D43: 144046.09 | E43: CUSTEIO | F43: Licitação | L43: =IF(ISBLANK(J43), "", SUM(J43, K43)) | O43: ARQUIVADO
A44: 23.820.057-1 | B44: [Emenda Parlamentar Senador Sérgio Moro] Aquisição de Kits reagentes de extração de DNA forense automatizado BTA, validados e compatíveis com plataformas automatizadas Hamilton de extração de DNA, visando atender às demandas do Laboratório de Genética Molecular Forense da Polícia Científica do Paraná, através de inexigibilidade de licitação | C44: 45771 | D44: 113526 | E44: CUSTEIO | F44: Inexigibilidade | H44: 45917 | I44: 45938 | J44: 45938 | K44: 30 | L44: =IF(ISBLANK(J44), "", SUM(J44, K44)) -> 45968 | N44: 45968 | O44: FINALIZADO
A45: 23.484.170-0 | B45: SRP - Cordão personalizado e porta crachá - Aquisição através do Registro de Preço do PE 334/2023, na modalidade CARONA, de Cordão personalizado e porta crachá para atender as necessidades das unidades da Polícia Científica do Paraná. VALIDADE DA ATA 03/06/2025 | C45: 45701 | D45: 16234 | E45: CUSTEIO | F45: SRP Estadual (Carona) | I45: 45791 | J45: 45777 | K45: 30 | L45: =IF(ISBLANK(J45), "", SUM(J45, K45)) -> 45807 | N45: 45805 | O45: FINALIZADO
A46: 23.390.457-0 | B46: Cartão FTA para a Polícia Científica do Paraná. Certame| PE 90224-25 | Seleção de fornecedores 2. Prot. 24.213.141-0 - Homologação Parcial - 158 pacotes com 100 unidades (R$347.600,00) | C46: 45691 | D46: 838189.8 | E46: CUSTEIO | F46: Licitação | G46: 45826 | H46: 45922 | I46: 45937 | J46: 45938 | K46: 60 | L46: =IF(ISBLANK(J46), "", SUM(J46, K46)) -> 45998 | M46: 45987 | O46: TRAMITANDO
A47: 23.934.522-0 | B47: Dispensa eletrônica de Lâmina de Serra Sabre | C47: 45782 | D47: 7960 | E47: CUSTEIO | F47: Dispensa de Licitação | G47: 45819 | I47: 45861 | J47: 45862 | K47: 30 | L47: =IF(ISBLANK(J47), "", SUM(J47, K47)) -> 45892 | M47: 45904 | N47: 45905 | O47: FINALIZADO
A48: 23.951.184-8 | B48: SRP - Copo Descartável - Aquisição através do Registro de Preço do PE 1036/2024, na modalidade CARONA, de Copo Descartável para atender as necessidades das unidades da Polícia Científica do Paraná. VALIDADE DA ATA 05/11/2025 | C48: 45785 | D48: 11407 | E48: CUSTEIO | F48: SRP Estadual (Carona) | G48: 45966 | I48: 45826 | J48: 45832 | K48: 30 | L48: =IF(ISBLANK(J48), "", SUM(J48, K48)) -> 45862 | N48: 45835 | O48: FINALIZADO
A49: 23.824.217-7 | B49: Contrato de manutenção corretiva e preventiva do equipamento IDStarlet da marca HAMILTON, por meio da Ata de Registro de Preços no 04/2024/SENASP, da qual a Polícia Científica do Paraná é participante. | C49: 45758 | D49: 196096.08 | E49: CUSTEIO | F49: SRP Federal | L49: =IF(ISBLANK(J49), "", SUM(J49, K49)) | O49: ARQUIVADO
A50: 23.887.144-1 | B50: Solicita-se a aquisição de freezers científicos, por meio da ARP 15/2025 (SENASP). | C50: 45777 | D50: 835200 | E50: INVESTIMENTO | F50: SRP Federal | H50: 45883 | I50: 45902 | J50: 45902 | K50: 180 | L50: =IF(ISBLANK(J50), "", SUM(J50, K50)) -> 46082 | M50: 46050 | O50: TRAMITANDO
A51: 23.390.499-6 | B51: Aquisição via dispensa de processo licitatório na forma eletrônica de Água Sanitária para atende a demanda da Polícia Científica do Paraná. | C51: 45685 | D51: 4504 | E51: CUSTEIO | F51: Dispensa de Licitação | L51: =IF(ISBLANK(J51), "", SUM(J51, K51)) | O51: ARQUIVADO
A52: 23.484.056-8 | B52: Solicita a aquisição de letreiro para a fachada da UETC Curitiba Tarumã | C52: 45756 | D52: 9904.2 | E52: INVESTIMENTO | F52: Dispensa de Licitação | I52: 45869 | K52: 30 | L52: =IF(ISBLANK(J52), "", SUM(J52, K52)) | O52: TRAMITANDO
A53: 23.496.090-3 | B53: Aquisição, através de dispensa eletrônica de processo licitatório, de sabão em pó, a fim de suprir a demanda do órgão da Polícia Científica do Paraná. | C53: 45701 | D53: 11160 | E53: CUSTEIO | F53: Dispensa de Licitação | L53: =IF(ISBLANK(J53), "", SUM(J53, K53)) | O53: ARQUIVADO
A54: 23.364.790-0 | B54: Solicitação de compra de Leitores QRCode. PE90830/25 | C54: 45777 | D54: 152155.2 | E54: INVESTIMENTO | F54: Licitação | G54: 45888 | H54: 46003 | I54: 46008 | J54: 46008 | K54: 60 | L54: =IF(ISBLANK(J54), "", SUM(J54, K54)) -> 46068 | O54: TRAMITANDO
A55: 23.330.486-7 | B55: Solicitação de reabertura de processo licitatório para aquisição des STUBS para a Polícia Científica do Paraná. PE 150/2025 | C55: 45673 | D55: 98295.8 | E55: CUSTEIO | F55: Licitação | G55: 45926 | H55: 45993 | I55: 45996 | J55: 46000 | K55: 60 | L55: =IF(ISBLANK(J55), "", SUM(J55, K55)) -> 46060 | O55: TRAMITANDO
A56: 23.573.808-2 | B56: SRP Materiais Diversos para Laboratório - Aquisição através do Registro de Preço do PE 352/2023, na modalidade PARTICIPANTE, de Materiais Diversos para Laboratório para atender as necessidades das unidades da Polícia Científica do Paraná. | C56: 45715 | D56: 22453.8 | E56: CUSTEIO | F56: SRP Estadual | G56: 45866 | I56: 45757 | J56: 45762 | K56: 30 | L56: =IF(ISBLANK(J56), "", SUM(J56, K56)) -> 45792 | N56: 45838 | O56: FINALIZADO
A57: 22.075.189-9 | B57: Licitação - Abertura de procedimento Licitatório, visando a aquisição de Cofres para atender a demanda de todas as unidades da Polícia Científica do Paraná. | C57: 45440 | D57: 75039.4 | E57: INVESTIMENTO | F57: Licitação | G57: 45623 | H57: 45692 | I57: 45706 | J57: 45709 | K57: 45 | L57: =IF(ISBLANK(J57), "", SUM(J57, K57)) -> 45754 | N57: 45736 | O57: FINALIZADO
A58: 21.828.132-0 | B58: SOLICITAÇÃO PARA ABERTURA DE PROCESSO LICITATÓRIO PARA CONTRATAÇÃO DE EMPRESA ESPECIALIZADA NO FORNECIMENTO, CONFIGURAÇÃO E IMPLANTAÇÃO DE SISTEMA INFORMATIZADO DE AUTOMAÇÃO E GESTÃO DE LABORATÓRIOS (LIMS), ATRAVÉS DO CONVÊNIO No 919141/2021 - PLATAFORMA + BRASIL POR 12 MESES, PARA ATENDER A SEÇÃO DE GENÉTICA MOLECULAR FORENSE. | C58: 45357 | D58: 642413 | E58: INVESTIMENTO | F58: Licitação | G58: 45603 | H58: 45670 | I58: 45680 | J58: 45692 | K58: 60 | L58: =IF(ISBLANK(J58), "", SUM(J58, K58)) -> 45752 | N58: 45757 | O58: FINALIZADO
A59: 23.828.665-4 | B59: Contratação de serviço de manutenção corretiva do equipamento Hamilton EasyPunch STARlet (StarQ), por inexigibilidade de licitação, para atender a demanda da Seção de Genética Molecular Forense da Polícia Científica do Paraná. | C59: 45776 | D59: 147814.9 | E59: CUSTEIO | F59: Inexigibilidade | L59: =IF(ISBLANK(J59), "", SUM(J59, K59)) | O59: ARQUIVADO
A60: 23.912.341-4 | B60: AQUISIÇÃO DE AR CONDICIONADO PORTÁTIL ATRAVÉS DE ADESÃO À ATA DE REGISTRO DE PREÇOS 236/2024 - UNIVERSIDADE FEDERAL DO PARANÁ - UFPR, PARA ATENDER A DEMANDA DA POLÍCIA CIENTÍFICA DO PARANÁ | C60: 45777 | D60: 18161.65 | E60: INVESTIMENTO | F60: SRP Estadual (Carona) | L60: =IF(ISBLANK(J60), "", SUM(J60, K60)) | O60: ARQUIVADO
A61: 23.918.447-2 | B61: Solicitação de adesão ao item 42 da ata de registro de preços no 038/2023, UASG 153254, com vigência até 27/09/2025, para aquisição de ultrafreezers laboratoriais para atender a demanda da Seção de Genética Molecular Forense da Polícia Científica do Paraná | C61: 45783 | D61: 274500 | E61: INVESTIMENTO | F61: SRP Estadual (Carona) | I61: 45859 | J61: 45866 | K61: 60 | L61: =IF(ISBLANK(J61), "", SUM(J61, K61)) -> 45926 | M61: 45896 | N61: 45901 | O61: FINALIZADO
A62: 22.403.733-3 | B62: Dispensa de Licitação Eletrônica - Aquisição através de dispensa de licitação de aquisição de Pilhas AA e AAA recarregáveis para atendimento da demanda da Polícia Científica do Paraná. DISPENSA ELETRÔNICA | C62: 45516 | D62: 9301.95 | E62: CUSTEIO | F62: Dispensa de Licitação | I62: 45782 | J62: 45790 | K62: 30 | L62: =IF(ISBLANK(J62), "", SUM(J62, K62)) -> 45820 | N62: 45810 | O62: FINALIZADO
A63: 23.976.044-9 | B63: Dispensa de Licitação Eletrônica - Aquisição através de dispensa de licitação de aquisição de Agulha Hipodérmica 40 x 1,6 mm para atendimento da demanda da Polícia Científica do Paraná. DISPENSA ELETRÔNICA | C63: 45790 | D63: 8059.06 | E63: CUSTEIO | F63: Dispensa de Licitação | I63: 45848 | J63: 45852 | K63: 30 | L63: =IF(ISBLANK(J63), "", SUM(J63, K63)) -> 45882 | M63: 45924 | N63: 45937 | O63: FINALIZADO
A64: 23.970.694-0 | B64: Trata-se da aquisição de copos descartáveis para atendente a demanda da Policia Científica do Paraná. DISPENSA ELETRÔNICA | C64: 45789 | D64: 26808 | E64: CUSTEIO | F64: Dispensa de Licitação | L64: =IF(ISBLANK(J64), "", SUM(J64, K64)) | O64: ARQUIVADO
A65: 23.985.100-2 | B65: SRP Fragmentadora de Papel - Aquisição através do Registro de Preço do PE 595/2024, na modalidade PARTICIPANTE, de Fragmentadora de Papel para atender as necessidades das unidades da Polícia Científica do Paraná. VALIDADE DA ATA: 24/04/2026 | C65: 45791 | D65: 69200 | E65: INVESTIMENTO | F65: SRP Estadual | H65: 45856 | I65: 45876 | J65: 45860 | K65: 30 | L65: =IF(ISBLANK(J65), "", SUM(J65, K65)) -> 45890 | M65: 45881 | N65: 45884 | O65: FINALIZADO
A66: 23.985.963-1 | B66: SRP Limpador Multiuso - Aquisição através do Registro de Preço do PE 113/2024, na modalidade PARTICIPANTE, de Limpador Multiuso para atender as necessidades das unidades da Polícia Científica do Paraná. VALIDADE DA ATA: 06/03/2026 | C66: 45791 | D66: 963.9 | E66: CUSTEIO | F66: SRP Estadual | I66: 45812 | J66: 45817 | K66: 30 | L66: =IF(ISBLANK(J66), "", SUM(J66, K66)) -> 45847 | N66: 45832 | O66: FINALIZADO
A67: 23.994.158-3 | B67: SRP Papel Higiênico Rolão 10 cm x 300 m - Aquisição através do Registro de Preço do PE 1025/2023, na modalidade PARTICIPANTE, de Papel Higiênico Rolão 10 cm x 300 m para atender as necessidades das unidades da Polícia Científica do Paraná. VALIDADE DA ATA: 25/11/2026 | C67: 45792 | D67: 13750 | E67: CUSTEIO | F67: SRP Estadual | I67: 45807 | J67: 45817 | K67: 30 | L67: =IF(ISBLANK(J67), "", SUM(J67, K67)) -> 45847 | N67: 45853 | O67: FINALIZADO
A68: 23.901.224-8 | B68: Aquisição de Ferramenta Forense Avançada de Remoção de Senha e Extração de Dados de Dispositivos Móveis Portáteis | C68: 45775 | D68: 798231 | E68: INVESTIMENTO | F68: Inexigibilidade | H68: 45909 | I68: 45918 | J68: 45918 | K68: 90 | L68: =IF(ISBLANK(J68), "", SUM(J68, K68)) -> 46008 | N68: 45967 | O68: FINALIZADO
A69: 23.166.542-0 | B69: INSTRUÇÃO DE COMPRA - CADEIRAS DO AUDITÓRIO DA NOVA SEDE DA UETC-PG | C69: 45631 | D69: 121371.5 | E69: INVESTIMENTO | F69: Licitação | L69: =IF(ISBLANK(J69), "", SUM(J69, K69)) | O69: ARQUIVADO
A70: 23.695.715-2 | B70: AQUISIÇÃO DE COOKTOP E FRIGOBAR ATRAVÉS DE ADESÃO À ATA DE REGISTRO DE PREÇOS 243/2024 - UNIVERSIDADE FEDERAL DO PARANÁ - UFPR, PARA ATENDER A DEMANDA DA POLÍCIA CIENTÍFICA DO PARANÁ | C70: 45747 | D70: 7650 | E70: INVESTIMENTO | F70: SRP Estadual (Carona) | L70: =IF(ISBLANK(J70), "", SUM(J70, K70)) | O70: ARQUIVADO
A71: 23.841.550-0 | B71: Solicita adesão à ATA SRP no 0008/2025, UASG 155015, para aquisição de Proteinase K (item 21) para atender a demanda da Seção de Genética Molecular Forense da Polícia Científica do Paraná. | C71: 45762 | D71: 820 | E71: CUSTEIO | F71: SRP Federal (Carona) | L71: =IF(ISBLANK(J71), "", SUM(J71, K71)) | O71: ARQUIVADO
A72: 24.031.360-0 | B72: SRP Desktop e Monitores - Aquisição através do Registro de Preço do PE 1031/2023, na modalidade PARTICIPANTE, de Desktop e Monitores para atender as necessidades das unidades da Polícia Científica do Paraná. VALIDADE DA ATA: 14/04/2026 | C72: 45799 | D72: 150480 | E72: INVESTIMENTO | F72: SRP Estadual | H72: 45915 | I72: 45934 | J72: 45915 | K72: 120 | L72: =IF(ISBLANK(J72), "", SUM(J72, K72)) -> 46035 | M72: 46006 | O72: TRAMITANDO
A73: 24.040.265-3 | B73: SRP Licença Software Archicad Brazilian - Aquisição através do Registro de Preço do PE INEX 2/2024, na modalidade PARTICIPANTE, de Licença Software Archicad Brazilian para atender as necessidades das unidades da Polícia Científica do Paraná. VALIDADE DA ATA: 15/05/2026 | C73: 45800 | D73: 73530 | E73: CUSTEIO | F73: SRP Estadual | K73: 10 | L73: =IF(ISBLANK(J73), "", SUM(J73, K73)) | O73: ARQUIVADO
A74: 22.683.581-4 | B74: Aquisição de equipamentos de processamento e de armazenamento de vestígios digitais e de equipamentos de gerenciamento de rede através de Termo de Execução Descentralizada - TED no 001/2024 - Lottopar PE 698 2025 | Publicado (abertura 26/08/25) | C74: 45534 | D74: 6793984.2 | E74: INVESTIMENTO | F74: Licitação | G74: 45895 | H74: 45996 | I74: 46008 | J74: 46008 | K74: 120 | L74: =IF(ISBLANK(J74), "", SUM(J74, K74)) -> 46128 | O74: TRAMITANDO
A75: 24.071.567-8 | B75: SRP Lâmina e Corante Giemsa - Aquisição através do Registro de Preço do PE 2121/2024, na modalidade PARTICIPANTE, de Lâmina e Corante Giemsa para atender as necessidades das unidades da Polícia Científica do Paraná. VALIDADE DA ATA: 13/05/2026 | C75: 45806 | D75: 1325 | E75: CUSTEIO | F75: SRP Estadual | I75: 45835 | J75: 45840 | K75: 30 | L75: =IF(ISBLANK(J75), "", SUM(J75, K75)) -> 45870 | M75: 45923 | N75: 45852 | O75: FINALIZADO
A76: 22.774.761-7 | B76: Aquisição de Fuzil 5,56 por meio de adesão à Ata de Registro de Preços da Polícia Militar de Minas Gerais | C76: 45553 | D76: 40970 | E76: INVESTIMENTO | F76: SRP Estadual (Carona) | I76: 45775 | J76: 45784 | K76: 120 | L76: =IF(ISBLANK(J76), "", SUM(J76, K76)) -> 45904 | N76: 45925 | O76: FINALIZADO
A77: 24.016.119-2 | B77: INSTRUÇÃO INICIAL DE PROCESSO LICITATÓRIO VISANDO FUTURA E EVENTUAL AQUISIÇÃO E LOCAÇÃO DE VIATURAS | C77: 45797 | D77: 30802722 | E77: INVESTIMENTO | F77: SRP Estadual | L77: =IF(ISBLANK(J77), "", SUM(J77, K77)) | O77: TRAMITANDO
A78: 24.090.039-4 | B78: Monitores 24" Via SRP - Adesão - Defensoria Publica do Amapá | C78: 45445 | D78: 104850 | E78: INVESTIMENTO | F78: SRP Estadual (Carona) | H78: 45903 | I78: 45924 | J78: 45925 | K78: 30 | L78: =IF(ISBLANK(J78), "", SUM(J78, K78)) -> 45955 | M78: 45942 | N78: 45950 | O78: FINALIZADO
A79: 23.778.317-4 | B79: abertura de processo licitatório para aquisição de 08 unidades de Sistema de Espectrometria de Infravermelho com Transformada de Fourier e Reflexão Total Atenuada (FTIR-ATR) para a Seção de Química Forense. | C79: 45750 | D79: 4382364 | E79: INVESTIMENTO | F79: Licitação | H79: 46003 | I79: 46007 | J79: 46006 | K79: 120 | L79: =IF(ISBLANK(J79), "", SUM(J79, K79)) -> 46126 | O79: TRAMITANDO
A80: 22.415.334-1 | B80: aquisição de dois Espectrômetros de massa com plasma indutivamente acoplado (ICP-MS) | C80: 45477 | D80: 5922423.1 | E80: INVESTIMENTO | F80: Licitação | H80: 45902 | I80: 45922 | J80: 45923 | K80: 90 | L80: =IF(ISBLANK(J80), "", SUM(J80, K80)) -> 46013 | M80: 45992 | O80: TRAMITANDO
A81: 22.668.212-0 | B81: Aquisição de reagentes químicos por dispensa de licitação, para atender a demanda das Seções de Genética Molecular Forense, Química Forense e Toxicologia Forense da Polícia Científica do Paraná | C81: 45531 | D81: 29093 | E81: CUSTEIO | F81: Dispensa de Licitação | I81: 45810 | J81: 45810 | K81: 30 | L81: =IF(ISBLANK(J81), "", SUM(J81, K81)) -> 45840 | N81: 45840 | O81: FINALIZADO
A82: 22.415.499-2 | B82: Solicitação de abertura de processo de licitação para a aquisição de dois Sistemas de Cromatografia Líquida acoplada a Espectrômetro de Massas de alta resolução do tipo Quadrupolo e Tempo de Voo (LC-qTOF-MS). (Agro Forense) | C82: 45492 | D82: 7879099.7 | E82: INVESTIMENTO | F82: Licitação | G82: 45644 | H82: 45813 | I82: 45826 | J82: 45832 | K82: 90 | L82: =IF(ISBLANK(J82), "", SUM(J82, K82)) -> 45922 | N82: 45901 | O82: FINALIZADO
A83: 24.097.849-0 | B83: SRP de Drones - Aquisição através do Registro de Preço do PE 1327/2024, na modalidade PARTICIPANTE, de Drones para atender as necessidades da Unidade de Execução Técnico-Científica de Curitiba da Polícia Científica do Paraná. VALIDADE DA ATA 27/04/2026 | C83: 45811 | D83: 579575.06 | E83: INVESTIMENTO | F83: SRP Estadual | H83: 45896 | I83: 45840 | J83: 45895 | K83: 60 | L83: =IF(ISBLANK(J83), "", SUM(J83, K83)) -> 45955 | M83: 45943 | N83: 45964 | O83: FINALIZADO
A84: 22.385.321-8 | B84: Licitação para a aquisição de 03 Sistemas de cromatografia líquida acoplados a espectrometria de massas em tandem. LC-MS/MS | C84: 45484 | D84: 8432255.9 | E84: INVESTIMENTO | F84: Licitação | G84: 45596 | H84: 45716 | I84: 45735 | J84: 45736 | K84: 120 | L84: =IF(ISBLANK(J84), "", SUM(J84, K84)) -> 45856 | N84: 45853 | O84: FINALIZADO
A85: 23.656.828-8 | B85: SRP - Contratação através do Registro de Preço do PE 847/2024, de prestação de serviço de limpeza, postos 12x36 com insalubridade 40% para atender a unidade de Telemaco Borba da Polícia Científica do Paraná. VALIDADE DA ATA: 17/11/2025. | C85: 45730 | D85: 116360.88 | E85: CUSTEIO | F85: SRP Estadual | G85: 45621 | L85: =IF(ISBLANK(J85), "", SUM(J85, K85)) | O85: TRAMITANDO
A86: 23.766.345-4 | B86: adesão como carona em ATA DE REGISTRO DE PREÇO no 0050/2024/PCI da Polícia Científica de Santa Catarina, para aquisição de Fast Blue Salt e Tiocianato de Cobalto II, para atender a demanda da Seção de Química Forense. | C86: 45748 | D86: 9744.27 | E86: CUSTEIO | F86: SRP Estadual | H86: 45881 | I86: 45902 | J86: 45881 | K86: 60 | L86: =IF(ISBLANK(J86), "", SUM(J86, K86)) -> 45941 | M86: 45925 | N86: 45939 | O86: FINALIZADO
A87: 22.168.566-0 | B87: Licitação - Abertura de procedimento Licitatório, visando a aquisição de CÂMARAS MORTUÁRIAS para a nova unidade da Polícia Científica de Ponta Grossa. | C87: 45441 | D87: 1436816.3 | E87: INVESTIMENTO | F87: Licitação | I87: 45757 | J87: 45814 | K87: 60 | L87: =IF(ISBLANK(J87), "", SUM(J87, K87)) -> 45874 | M87: 45848 | N87: 45918 | O87: FINALIZADO
A88: 24.116.894-8 | B88: Solicitação de Adesão a ATA 011/2024 da SUPERINTENDÊNCIA REGIONAL DA POLÍCIA FEDERAL NO ESTADO DO AMAPÁ visando a aquisição de 40 unidades de Smart Tv 55 | C88: 45813 | D88: 83360 | E88: INVESTIMENTO | F88: SRP Federal (Carona) | H88: 45903 | I88: 45918 | J88: 45903 | K88: 30 | L88: =IF(ISBLANK(J88), "", SUM(J88, K88)) -> 45933 | M88: 45919 | N88: 45929 | O88: FINALIZADO
A89: 22.488.200-9 | B89: Aquisição de Equipamentos SGMF - Inexigibilidade StarletID, EasyPunch e QuantStudio. | C89: 45495 | D89: 4768676.8 | E89: INVESTIMENTO | F89: Inexigibilidade | H89: 45799 | I89: 45814 | J89: 45817 | K89: 30 | L89: =IF(ISBLANK(J89), "", SUM(J89, K89)) -> 45847 | N89: 45847 | O89: FINALIZADO
A90: 22.212.489-1 | B90: Prestação de serviço de manutenção, preventiva e corretiva, de câmaras mortuárias refrigeradas, para atender a demanda de 18 (dezoito) Unidades de Execução Técnico-Científicas (UETCs) da Polícia Científica do Paraná (PCP), pelo período de 12 (doze) meses | C90: 45435 | D90: 2192989.6 | E90: CUSTEIO | F90: Licitação | G90: 45714 | H90: 45819 | I90: 45849 | J90: 45852 | K90: 0 | L90: =IF(ISBLANK(J90), "", SUM(J90, K90)) -> 45852 | N90: 45852 | O90: FINALIZADO
A91: 22.124.897-0 | B91: Instrução de compra referente às mesas de necropsia da nova unidade da Polícia Científica de Ponta Grossa | C91: 45418 | D91: 697746 | E91: INVESTIMENTO | F91: Licitação | H91: 45729 | I91: 45737 | J91: 45740 | K91: 60 | L91: =IF(ISBLANK(J91), "", SUM(J91, K91)) -> 45800 | N91: 45820 | O91: FINALIZADO
A92: 22.443.126-0 | B92: AQUISIÇÃO DE SISTEMA DE CROMATOGRAFIA IÔNICA PARA ANÁLISE SIMULTÂNEA DE ÂNIONS E CÁTIONS COM DETECTORES POR CONDUTIVIDADE | C92: 45483 | D92: 1439800 | E92: INVESTIMENTO | F92: Licitação | G92: 46009 | H92: 45799 | I92: 45799 | J92: 45825 | K92: 90 | L92: =IF(ISBLANK(J92), "", SUM(J92, K92)) -> 45915 | M92: 45890 | O92: TRAMITANDO
A93: 24.162.789-6 | B93: Aquisição, através de procedimento licitatório de carrinho de instrumentação para atender a demanda das unidades que realizam exames de necropsia da Polícia Científica do Paraná | C93: 45821 | D93: 87471 | E93: INVESTIMENTO | F93: Licitação | L93: =IF(ISBLANK(J93), "", SUM(J93, K93)) | O93: TRAMITANDO
A94: 24.075.464-9 | B94: Aquisição de Tanques Balísticos - Adesão a Ata de Registro de Preços N° 0049/2024/PCI | C94: 45806 | D94: 255509.8 | E94: INVESTIMENTO | F94: SRP Estadual (Carona) | L94: =IF(ISBLANK(J94), "", SUM(J94, K94)) | O94: ARQUIVADO
A95: 24.172.889-7 | B95: protocolo de adesão à ata de lençol descartável | C95: 45824 | D95: 6784 | E95: CUSTEIO | F95: SRP Federal (Carona) | I95: 45901 | J95: 45910 | K95: 30 | L95: =IF(ISBLANK(J95), "", SUM(J95, K95)) -> 45940 | N95: 45916 | O95: FINALIZADO
A96: 24.195.717-9 | B96: SRP - Banco de Jardim - Aquisição através do Registro de Preço do PE 026/2025, na modalidade CARONA, de Banco de Jardim para atender as necessidades das unidades da Polícia Científica do Paraná. | C96: 45831 | D96: 2072 | E96: INVESTIMENTO | F96: SRP Estadual (Carona) | I96: 45961 | J96: 45966 | K96: 30 | L96: =IF(ISBLANK(J96), "", SUM(J96, K96)) -> 45996 | M96: 46009 | O96: TRAMITANDO
A97: 24.195.811-6 | B97: SRP MATERIAL DE COPA E COZINHA – GRUPO II - Aquisição através do Registro de Preço do PE 366/2023, na modalidade PARTICIPANTE, de MATERIAL DE COPA E COZINHA – GRUPO II para atender as necessidades das unidades da Polícia Científica do Paraná. VALIDADE DA ATA: 01/09/2025 | C97: 45834 | D97: 1050.05 | E97: CUSTEIO | F97: SRP Estadual | I97: 45840 | J97: 45842 | K97: 30 | L97: =IF(ISBLANK(J97), "", SUM(J97, K97)) -> 45872 | N97: 45859 | O97: FINALIZADO
A98: 23.885.636-1 | B98: processo de compra por inexigibilidade para aquisição de um Espectrômetro de Ressonância Magnética Nuclear (RMN) de bancada para atender a demanda da seção de química forense da Polícia Científica do Paraná | C98: 45831 | D98: 1952460.7 | E98: INVESTIMENTO | F98: Inexigibilidade | L98: =IF(ISBLANK(J98), "", SUM(J98, K98)) | O98: TRAMITANDO
A99: 24.197.585-1 | B99: SRP Detergente Laboratorial - Aquisição através do Registro de Preço do PE 107/2024, na modalidade CARONA, de Detergente Laboratorial para atender as necessidades das unidades da Polícia Científica do Paraná. VALIDADE DA ATA: 17/09/2025 | C99: 45831 | D99: 13311.15 | E99: CUSTEIO | F99: SRP Estadual (Carona) | I99: 45867 | J99: 45868 | K99: 30 | L99: =IF(ISBLANK(J99), "", SUM(J99, K99)) -> 45898 | M99: 45915 | N99: 45888 | O99: FINALIZADO
A100: 24.198.214-9 | B100: Aquisição de sacos plásticos para acondicionamento de resíduos hospitalares/infectantes, através de adesão à ata SRP no 2216/2024/SESA PR, vigência: 06/05/2026, para atender a demanda da Polícia Científica do Paraná. | C100: 45825 | D100: 18480 | E100: CUSTEIO | F100: SRP Estadual (Carona) | I100: 45895 | J100: 45896 | K100: 30 | L100: =IF(ISBLANK(J100), "", SUM(J100, K100)) -> 45926 | M100: 45924 | N100: 45929 | O100: FINALIZADO
...

Sheet Compras 2025
A1: =SUBTOTAL(3,A3:A1095) -> 204 | D1: =SUBTOTAL(9,D3:D1094) -> 1.7419035e+08 | I1: =SUBTOTAL(3,I3:I500) -> 110 | J1: =SUBTOTAL(3,J3:J500) -> 110 | N1: =SUBTOTAL(3,N3:N1094) -> 78 | O1: =COUNTIF(O3:O499,"FINALIZADO") -> 78
A2: PROCESSO N° | B2: DESCRIÇÃO | C2: DATA DE CRIAÇÃO | D2: VALOR PREVISTO | E2: FONTE DE RECURSO | F2: MODALIDADE | G2: DATA DO PREGÃO | H2: CONTRATO ASSINADO | I2: EMPENHO ASSINADO | J2: EMPENHO E CONTRATO ENVIADO AO FORNECEDOR (DATA) | K2: PRAZO DE ENTREGA (DIAS) | L2: DATA PREV. DE ENTREGA | M2: COBRADO ENTREGA NO DIA | N2: MATERIAL ENTREGUE (DATA) | O2: SITUAÇÃO | P2: OBSERVAÇÃO
A3: 23.536.933-8 | B3: Dispensa de menor valor - Dispensa de contratação de prestação de serviço de Dosimetria, para atender a UETC Tarumã da Polícia Científica do Paraná | C3: 45715 | D3: 10560 | E3: CUSTEIO | F3: Dispensa de Licitação | H3: 45839 | I3: 45848 | J3: 45852 | K3: 30 | L3: =IF(ISBLANK(J3), "", SUM(J3, K3)) -> 45882 | N3: 45839 | O3: FINALIZADO
A4: 23.577.593-0 | B4: Contratação de Serviço de empresa especializada em lavagem de roupa hospitalar - Lavanderia | C4: 45714 | D4: 1778400 | E4: CUSTEIO | F4: Licitação | G4: 45875 | H4: 45932 | I4: 45951 | J4: 45951 | K4: 30 | L4: =IF(ISBLANK(J4), "", SUM(J4, K4)) -> 45981 | N4: 45981 | O4: FINALIZADO
A5: 23.432.467-5 | B5: [Verba Parlamentar Moro] Aquisição de Pipetador Automático para preparo de placas para a SGMF | C5: 45734 | D5: 531310 | E5: CUSTEIO | F5: Inexigibilidade | K5: 30 | L5: =IF(ISBLANK(J5), "", SUM(J5, K5)) | O5: TRAMITANDO
A6: 23.711.290-3 | B6: Dispensa de Licitação - Aquisição de Maleta de Perícia tipo 02, para atender as necessidades da Polícia Científica do Paraná, através do Convênio Federal No 936068/2022, No Processo: 08020002865202206 | C6: 45750 | D6: 106123 | E6: INVESTIMENTO | F6: Dispensa de Licitação | H6: 45903 | I6: 45922 | J6: 45923 | K6: 90 | L6: =IF(ISBLANK(J6), "", SUM(J6, K6)) -> 46013 | M6: 45992 | O6: TRAMITANDO
A7: 23.336.634-0 | B7: Contratação do serviço de ampliação da rede de gases especiais visando a instalação de novos equipamentos laboratoriais na UETC Curitiba - Tarumã | C7: 45674 | D7: 171111.52 | E7: CUSTEIO | F7: Licitação | H7: 45917 | I7: 45937 | J7: 45936 | K7: 15 | L7: =IF(ISBLANK(J7), "", SUM(J7, K7)) -> 45951 | N7: 45951 | O7: FINALIZADO
A8: 23.356.092-8 | B8: Aquisição de “Kits de Controle de Acesso”, para atender a demanda da Divisão de Custódia de Vestígios da Polícia Científica do Paraná | C8: 45678 | D8: 193026.4 | E8: INVESTIMENTO | F8: Licitação | K8: 30 | L8: =IF(ISBLANK(J8), "", SUM(J8, K8)) | O8: TRAMITANDO
A9: 23.708.709-7 | B9: Solicita abertura para aquisição de 60 Purificadores de água e refil de filtro, a fim de atender as demandas da Polícia Científica do Paraná. | C9: 45751 | D9: 85981.41 | E9: INVESTIMENTO | F9: Licitação | K9: 30 | L9: =IF(ISBLANK(J9), "", SUM(J9, K9)) | O9: TRAMITANDO
A10: 23.822.468-3 | B10: Contratação de empresa especializada na prestação de serviços de locação de veículos adaptados para transporte de cadáveres (COTRANS) - o protocolo que correu o processo licitatório, 22.469.724-4, foi arquivado na SEAP. | C10: 45763 | D10: 33480720 | E10: CUSTEIO | F10: Licitação | G10: 45702 | H10: 45820 | I10: 45868 | J10: 45821 | K10: 60 | L10: =IF(ISBLANK(J10), "", SUM(J10, K10)) -> 45881 | O10: TRAMITANDO
A11: 23.750.119-5 | B11: SEDCA Aquisição de uma Plataforma de Processamento Rápido de DNA | C11: 45747 | D11: 990000 | E11: INVESTIMENTO | F11: Inexigibilidade | H11: 45999 | K11: 30 | L11: =IF(ISBLANK(J11), "", SUM(J11, K11)) | O11: TRAMITANDO | P11: 25/06/2025 - Enviado ao SESP/NFS/OR para emissão das informações financeiras
A12: 23.391.860-1 | B12: SRP Coffee Break - Aquisição através do Registro de Preço do PE 494/2023, na modalidade PARTICIPANTE, de Serviço de Coffee Break para atender as necessidades da Unidade de Execução Técnico-Científica de Curitiba da Polícia Científica do Paraná. VALIDADE DA ATA 23/09/2025 | C12: 45686 | D12: 50000 | E12: CUSTEIO | F12: SRP Estadual | G12: 45946 | H12: 45733 | I12: 45748 | J12: 45756 | K12: 360 | L12: =IF(ISBLANK(J12), "", SUM(J12, K12)) -> 46116 | N12: 45751 | O12: FINALIZADO
A13: 23.384.464-0 | B13: AQUISIÇÃO DE SOLUÇÕES TAMPÃO E KCl, VIA PREGÃO ELETRÔNICO 851/2023 LOTES 01, 02 e 03, VALIDADE DA ATA: 19/02/2025, NA MODALIDADE PARTICIPANTE, PARA SUPRIR A DEMANDA DOS LABORATÓRIOS FORENSES DA POLÍCIA CIENTÍFICA DO PARANÁ. | C13: 45688 | D13: 233.25 | E13: CUSTEIO | F13: SRP Estadual | L13: =IF(ISBLANK(J13), "", SUM(J13, K13)) | O13: ARQUIVADO
A14: 23.427.285-3 | B14: SRP Máscara e Avental Descartável - Aquisição através do Registro de Preço do PE 706/2024, na modalidade PARTICIPANTE, de Máscara e Avental Descartável para atender as necessidades das unidades da Polícia Científica do Paraná. | C14: 45698 | D14: 17473 | E14: CUSTEIO | F14: SRP Estadual | G14: 46044 | I14: 45702 | J14: 45786 | K14: 30 | L14: =IF(ISBLANK(J14), "", SUM(J14, K14)) -> 45816 | M14: 45805 | N14: 45833 | O14: FINALIZADO
A15: 23.549.843-0 | B15: SRP Insumos de Laboratórios - Aquisição através do Registro de Preço do PE 163/2023, na modalidade PARTICIPANTE de Insumos de Laboratórios para atender as unidades da Polícia Científica do Paraná. VALIDADE DA ATA: 17/02/2026 | C15: 45712 | D15: 68276.4 | E15: CUSTEIO | F15: SRP Estadual | I15: 45806 | J15: 45812 | K15: 15 | L15: =IF(ISBLANK(J15), "", SUM(J15, K15)) -> 45827 | M15: 45910 | N15: 45915 | O15: FINALIZADO
A16: 23.539.216-0 | B16: Aquisição de Câmaras Frias pelo SRP no 1388/2024. 7 Unidades: 1 Seção Ambiental, 1 Telêmaco Borba, 3 Toledo, 1 Maringá e 1 Paranaguá | C16: 45735 | D16: 292600 | E16: INVESTIMENTO | F16: SRP Estadual | I16: 45800 | J16: 45792 | K16: 45 | L16: =IF(ISBLANK(J16), "", SUM(J16, K16)) -> 45837 | M16: 45862 | N16: 45867 | O16: FINALIZADO | P16: 29/07/2025 - Ja entregue Telemaco Borba, Segundo Beatriz
A17: 23.726.102-0 | B17: SRP Papel Sulfite A4 - Aquisição através do Registro de Preço do PE 33/2024, na modalidade PARTICIPANTE, de Papel Sulfite A4 para atender as necessidades das unidades da Polícia Científica do Paraná. | C17: 45743 | D17: 19470 | E17: CUSTEIO | F17: SRP Estadual | I17: 45775 | J17: 45826 | K17: 30 | L17: =IF(ISBLANK(J17), "", SUM(J17, K17)) -> 45856 | N17: 45846 | O17: FINALIZADO
A18: 23.814.144-3 | B18: SRP Almoxarife - Contratação através do Registro de Preço do PE 1934/2024, na modalidade PARTICIPANTE, de Posto, Almoxarife, 40 horas semanais, De segunda a sexta para atender as necessidades do Almoxarifado Central da Polícia Científica do Paraná. | C18: 45762 | D18: 57317.76 | E18: CUSTEIO | F18: SRP Estadual | L18: =IF(ISBLANK(J18), "", SUM(J18, K18)) | O18: ARQUIVADO
A19: 23.852.416-4 | B19: SRP Água Mineral - Aquisição através do Registro de Preço do PE 1089/2024 na modalidade PARTICIPANTE, de Água Mineral para atender as necessidades das unidades da Polícia Científica do Paraná. VALIDADE DA ATA: 07/04/2026 | C19: 45763 | D19: 89853.91 | E19: CUSTEIO | F19: SRP Estadual | I19: 45840 | J19: 45852 | K19: 10 | L19: =IF(ISBLANK(J19), "", SUM(J19, K19)) -> 45862 | N19: 45862 | O19: FINALIZADO
A20: 23.759.626-9 | B20: Adesão em ATA DE REGISTRO DE PREÇO da PCP-SC, para aquisição de álcool metílico, álcool isopropílico e luminol. | C20: 45755 | D20: 2375 | E20: CUSTEIO | F20: SRP Estadual (Carona) | H20: 45852 | I20: 45883 | J20: 45852 | K20: 60 | L20: =IF(ISBLANK(J20), "", SUM(J20, K20)) -> 45912 | M20: 45890 | N20: 45887 | O20: FINALIZADO
A21: 23.529.878-3 | B21: Trata-se de abertura de dispensa de licitação para aquisição de embalagem simples. | C21: 45713 | D21: 53179.5 | E21: CUSTEIO | F21: Dispensa de Licitação | I21: 45777 | J21: 45784 | K21: 30 | L21: =IF(ISBLANK(J21), "", SUM(J21, K21)) -> 45814 | N21: 45799 | O21: FINALIZADO
A22: 23.550.851-6 | B22: dispensa eletrônica de licitação para aquisição de insumos para a realização de exames de identificação veicular, Em Aço Rápido; lixa, graxa, removedor de esmalte (acetona) estopa | C22: 45715 | D22: 51776 | E22: CUSTEIO | F22: Dispensa de Licitação | I22: 45792 | J22: 45796 | K22: 30 | L22: =IF(ISBLANK(J22), "", SUM(J22, K22)) -> 45826 | N22: 45824 | O22: FINALIZADO
A23: 23.590.694-5 | B23: dispensa eletrônica de processo licitatório, de Artigos de Higiene Pessoal - Sabonete Líquido | C23: 45722 | D23: 16271.44 | E23: CUSTEIO | F23: Dispensa de Licitação | I23: 45786 | J23: 45792 | K23: 30 | L23: =IF(ISBLANK(J23), "", SUM(J23, K23)) -> 45822 | N23: 45804 | O23: FINALIZADO
A24: 23.444.059-4 | B24: [Verba Parlamentar - Moro] - Aquisição de Insumos para o Analisador Genético 3500 | C24: 45692 | D24: 360551.24 | E24: CUSTEIO | F24: Inexigibilidade | L24: =IF(ISBLANK(J24), "", SUM(J24, K24)) | O24: TRAMITANDO
A25: 23.711.352-7 | B25: [Verba Parlamentar - Moro] - Aquisição Sequenciador com Sistema de Eletroforese capilar | C25: 45741 | D25: 1538000 | E25: CUSTEIO | F25: Inexigibilidade | K25: 90 | L25: =IF(ISBLANK(J25), "", SUM(J25, K25)) | O25: TRAMITANDO
A26: 23.678.445-2 | B26: [Emenda Parlamentar - Sérgio Moro] Aquisição de um moinho moedor de ossos | C26: 45734 | D26: 434305.84 | E26: CUSTEIO | F26: Inexigibilidade | K26: 90 | L26: =IF(ISBLANK(J26), "", SUM(J26, K26)) | O26: TRAMITANDO
A27: 23.503.010-1 | B27: SRP CAIXA VAZADA - AQUISIÇÃO ATRAVÉS DO REGISTRO DE PREÇO DO PE 979/2023, NA MODALIDADE PARTICIPANTE, DE CAIXA VAZADA, COR: AZUL, CAPACIDADE: 49 LITROS | C27: 45702 | D27: 6480 | E27: CUSTEIO | F27: SRP Estadual | G27: 46003 | I27: 45709 | J27: 45715 | K27: 30 | L27: =IF(ISBLANK(J27), "", SUM(J27, K27)) -> 45745 | N27: 45761 | O27: FINALIZADO
A28: 23.541.254-3 | B28: SRP Reagentes Químicos - Aquisição através do Registro de Preço do PE 975/2023, na modalidade PARTICIPANTE de Reagentes Químicos para atender as unidades da Polícia Científica do Paraná. VALIDADE DA ATA: 28/05/2025 | C28: 45712 | D28: 25816.46 | E28: CUSTEIO | F28: SRP Estadual | I28: 45721 | J28: 45733 | K28: 30 | L28: =IF(ISBLANK(J28), "", SUM(J28, K28)) -> 45763 | M28: 45861 | N28: 45910 | O28: FINALIZADO
A29: 23.581.473-0 | B29: SRP Bandeiras - Aquisição através do Registro de Preço do PE 449/2023, na modalidade PARTICIPANTE, de Bandeiras para atender as necessidades das unidades da Polícia Científica do Paraná. | C29: 45717 | D29: 4666 | E29: CUSTEIO | F29: SRP Estadual | G29: 46066 | I29: 45729 | J29: 45733 | K29: 30 | L29: =IF(ISBLANK(J29), "", SUM(J29, K29)) -> 45763 | N29: 45744 | O29: FINALIZADO
A30: 23.659.354-1 | B30: SRP Envelope, TIPO: Saco, COR: Branca - Aquisição através do Registro de Preço do PE 25/2023, na modalidade PARTICIPANTE, de Envelope, TIPO: Saco, COR: Branca para atender as necessidades das unidades da Polícia Científica do Paraná. | C30: 45733 | D30: 192 | E30: CUSTEIO | F30: SRP Estadual | G30: 46007 | I30: 45737 | J30: 45740 | K30: 30 | L30: =IF(ISBLANK(J30), "", SUM(J30, K30)) -> 45770 | N30: 45775 | O30: FINALIZADO
A31: 23.650.629-0 | B31: SRP Caneta Esferográfica - Aquisição através do Registro de Preço do PE 28/2023, na modalidade PARTICIPANTE, de Caneta Esferográfica para atender as necessidades das unidades da Polícia Científica do Paraná. | C31: 45729 | D31: 976.92 | E31: CUSTEIO | F31: SRP Estadual | I31: 45736 | J31: 45740 | K31: 30 | L31: =IF(ISBLANK(J31), "", SUM(J31, K31)) -> 45770 | N31: 45772 | O31: FINALIZADO
A32: 23.642.186-4 | B32: SRP Sabão em Pó, Limpa Vidros e Lustra Móveis - Aquisição através do Registro de Preço do PE 113/2024, na modalidade PARTICIPANTE, de Sabão em Pó, Limpa Vidros e Lustra Móveis | C32: 45728 | D32: 1631.75 | E32: CUSTEIO | F32: SRP Estadual | I32: 45740 | J32: 45748 | K32: 30 | L32: =IF(ISBLANK(J32), "", SUM(J32, K32)) -> 45778 | N32: 45803 | O32: FINALIZADO
A33: 23.574.455-4 | B33: SRP Materiais Diversos para Laboratório - Aquisição através do Registro de Preço do PE 747/2023, na modalidade PARTICIPANTE, de Materiais Diversos para Laboratório para atender as necessidades das unidades da Polícia Científica do Paraná. | C33: 45716 | D33: 11757.8 | E33: CUSTEIO | F33: SRP Estadual | I33: 45729 | J33: 45770 | K33: 30 | L33: =IF(ISBLANK(J33), "", SUM(J33, K33)) -> 45800 | M33: 45834 | N33: 45839 | O33: FINALIZADO
A34: 23.326.534-9 | B34: SRP CARONA - Adesão de Aquisição através do Registro de Preço do PE 185/2024, de aquisição de Seringa, Descartável, Estéril, 20ml (sem agulha | C34: 45673 | D34: 7000 | E34: CUSTEIO | F34: SRP Estadual (Carona) | G34: 46006 | I34: 45686 | J34: 45692 | K34: 30 | L34: =IF(ISBLANK(J34), "", SUM(J34, K34)) -> 45722 | N34: 45701 | O34: FINALIZADO
A35: 23.468.057-9 | B35: SRP Água Sanitária e Desodorizador de Ambiente - Aquisição através do Registro de Preço do PE 112/2024, na modalidade PARTICIPANTE, de Água Sanitária e Desodorizador de Ambiente para atender as necessidades das unidades da Polícia Científica do Paraná. VALIDADE DA ATA: 02/02/2026 | C35: 45698 | D35: 3078.15 | E35: CUSTEIO | F35: SRP Estadual | G35: 46055 | I35: 45702 | J35: 45722 | K35: 30 | L35: =IF(ISBLANK(J35), "", SUM(J35, K35)) -> 45752 | N35: 45730 | O35: FINALIZADO
A36: 23.518.554-7 | B36: SRP Material de Limpeza - Grupo I - Aquisição através do Registro de Preço do PE 1026/2023, na modalidade PARTICIPANTE de Material de Limpeza - Grupo I - Escova, Pá, desentupidor . VALIDADE DA ATA: 09/10/2025 | C36: 45705 | D36: 1301.91 | E36: CUSTEIO | F36: SRP Estadual | G36: 45939 | I36: 45707 | J36: 45723 | K36: 30 | L36: =IF(ISBLANK(J36), "", SUM(J36, K36)) -> 45753 | N36: 45737 | O36: FINALIZADO
A37: 23.443.596-5 | B37: SRP Caixa Arquivo - Aquisição através do Registro de Preço do PE 27/2023, na modalidade PARTICIPANTE, de Caixa Arquivo para atender as necessidades das unidades da Polícia Científica do Paraná. VALIDADE DA ATA: 27/02/2025 | C37: 45692 | D37: 2862 | E37: CUSTEIO | F37: SRP Estadual | G37: 45715 | I37: 45700 | J37: 45708 | K37: 30 | L37: =IF(ISBLANK(J37), "", SUM(J37, K37)) -> 45738 | N37: 45728 | O37: FINALIZADO
A38: 23.510.701-5 | B38: SRP Garrafa Térmica - Aquisição através do Registro de Preço do PE 366/2023, na modalidade PARTICIPANTE de Garrafa Térmica 1,8 Litros para atender as unidades da Polícia Científica do Paraná. VALIDADE DA ATA: 01/09/2025 | C38: 45705 | D38: 2847.5 | E38: CUSTEIO | F38: SRP Estadual | G38: 45901 | I38: 45716 | J38: 45722 | K38: 30 | L38: =IF(ISBLANK(J38), "", SUM(J38, K38)) -> 45752 | N38: 45737 | O38: FINALIZADO
A39: 23.460.149-0 | B39: SRP Luva Nitrílica - Aquisição através do Registro de Preço do PE 747/2023, na modalidade PARTICIPANTE, de Luva Nitrílica para atender as necessidades das unidades da Polícia Científica do Paraná. VALIDADE DA ATA: 29/04/2025 | C39: 45695 | D39: 99500.4 | E39: CUSTEIO | F39: SRP Estadual | G39: 45776 | I39: 45701 | J39: 45729 | K39: 30 | L39: =IF(ISBLANK(J39), "", SUM(J39, K39)) -> 45759 | N39: 45742 | O39: FINALIZADO
A40: 23.456.626-1 | B40: Solicitação de compra por dispensa de licitação de envelopes cartão. | C40: 45735 | D40: 2600 | E40: CUSTEIO | F40: Dispensa de Licitação | I40: 45818 | J40: 45824 | K40: 30 | L40: =IF(ISBLANK(J40), "", SUM(J40, K40)) -> 45854 | N40: 45847 | O40: FINALIZADO
A41: 21.027.878-8 | B41: Certame | PEI90968-23 | Análise docs complementares (30/01/25) | COLETES BALÍSTICOS VIA SRP - SESP | C41: 45687 | D41: 0 | E41: INVESTIMENTO | F41: SRP Estadual | L41: =IF(ISBLANK(J41), "", SUM(J41, K41)) | O41: TRAMITANDO
A42: 23.551.931-3 | B42: Processo de inexigibilidade para a aquisição de 200 (duzentas) inscrições para o congresso Interforensics | C42: 45727 | D42: 110000 | E42: CUSTEIO | F42: Inexigibilidade | H42: 45868 | I42: 45877 | J42: 45869 | K42: 30 | L42: =IF(ISBLANK(J42), "", SUM(J42, K42)) -> 45899 | N42: 45870 | O42: FINALIZADO
A43: 23.846.805-1 | B43: Solicitação para abertura de processo licitatório para manutenção preventiva e corretiva de dois Espectrômetros Raman da Seção de Química Forense da Polícia Científica do Paraná. | C43: 45763 | D43: 144046.09 | E43: CUSTEIO | F43: Licitação | L43: =IF(ISBLANK(J43), "", SUM(J43, K43)) | O43: TRAMITANDO
A44: 23.820.057-1 | B44: [Emenda Parlamentar Senador Sérgio Moro] Aquisição de Kits reagentes de extração de DNA forense automatizado BTA, validados e compatíveis com plataformas automatizadas Hamilton de extração de DNA, visando atender às demandas do Laboratório de Genética Molecular Forense da Polícia Científica do Paraná, através de inexigibilidade de licitação | C44: 45771 | D44: 113526 | E44: CUSTEIO | F44: Inexigibilidade | H44: 45917 | I44: 45938 | J44: 45938 | K44: 30 | L44: =IF(ISBLANK(J44), "", SUM(J44, K44)) -> 45968 | O44: TRAMITANDO
A45: 23.484.170-0 | B45: SRP - Cordão personalizado e porta crachá - Aquisição através do Registro de Preço do PE 334/2023, na modalidade CARONA, de Cordão personalizado e porta crachá para atender as necessidades das unidades da Polícia Científica do Paraná. VALIDADE DA ATA 03/06/2025 | C45: 45701 | D45: 16234 | E45: CUSTEIO | F45: SRP Estadual (Carona) | I45: 45791 | J45: 45777 | K45: 30 | L45: =IF(ISBLANK(J45), "", SUM(J45, K45)) -> 45807 | N45: 45805 | O45: FINALIZADO
A46: 23.390.457-0 | B46: Cartão FTA para a Polícia Científica do Paraná. Certame| PE 90224-25 | Seleção de fornecedores 2. Prot. 24.213.141-0 - Homologação Parcial - 158 pacotes com 100 unidades (R$347.600,00) | C46: 45691 | D46: 838189.8 | E46: CUSTEIO | F46: Licitação | G46: 45826 | H46: 45922 | I46: 45937 | J46: 45938 | K46: 60 | L46: =IF(ISBLANK(J46), "", SUM(J46, K46)) -> 45998 | M46: 45987 | O46: TRAMITANDO | P46: 2. Prot. 24.213.141-0 - Homologação Parcial - 158 pacotes com 100 unidades (R$347.600,00)
A47: 23.934.522-0 | B47: Dispensa eletrônica de Lâmina de Serra Sabre | C47: 45782 | D47: 7960 | E47: CUSTEIO | F47: Dispensa de Licitação | G47: 45819 | I47: 45861 | J47: 45862 | K47: 30 | L47: =IF(ISBLANK(J47), "", SUM(J47, K47)) -> 45892 | M47: 45904 | N47: 45905 | O47: FINALIZADO
A48: 23.951.184-8 | B48: SRP - Copo Descartável - Aquisição através do Registro de Preço do PE 1036/2024, na modalidade CARONA, de Copo Descartável para atender as necessidades das unidades da Polícia Científica do Paraná. VALIDADE DA ATA 05/11/2025 | C48: 45785 | D48: 11407 | E48: CUSTEIO | F48: SRP Estadual (Carona) | G48: 45966 | I48: 45826 | J48: 45832 | K48: 30 | L48: =IF(ISBLANK(J48), "", SUM(J48, K48)) -> 45862 | N48: 45835 | O48: FINALIZADO
A49: 23.824.217-7 | B49: Contrato de manutenção corretiva e preventiva do equipamento IDStarlet da marca HAMILTON, por meio da Ata de Registro de Preços no 04/2024/SENASP, da qual a Polícia Científica do Paraná é participante. | C49: 45758 | D49: 196096.08 | E49: CUSTEIO | F49: SRP Federal | L49: =IF(ISBLANK(J49), "", SUM(J49, K49)) | O49: ARQUIVADO
A50: 23.887.144-1 | B50: Solicita-se a aquisição de freezers científicos, por meio da ARP 15/2025 (SENASP). | C50: 45777 | D50: 835200 | E50: INVESTIMENTO | F50: SRP Federal | H50: 45883 | I50: 45902 | J50: 45902 | K50: 180 | L50: =IF(ISBLANK(J50), "", SUM(J50, K50)) -> 46082 | M50: 46050 | O50: TRAMITANDO
A51: 23.390.499-6 | B51: Aquisição via dispensa de processo licitatório na forma eletrônica de Água Sanitária para atende a demanda da Polícia Científica do Paraná. | C51: 45685 | D51: 4504 | E51: CUSTEIO | F51: Dispensa de Licitação | L51: =IF(ISBLANK(J51), "", SUM(J51, K51)) | O51: ARQUIVADO
A52: 23.484.056-8 | B52: Solicita a aquisição de letreiro para a fachada da UETC Curitiba Tarumã | C52: 45756 | D52: 9904.2 | E52: INVESTIMENTO | F52: Dispensa de Licitação | I52: 45869 | K52: 30 | L52: =IF(ISBLANK(J52), "", SUM(J52, K52)) | O52: TRAMITANDO | P52: Fornecedor desistiu do Serviço, será desomologado e solicitado o próximo colocado. 24.644.316-5 - Verifica eventual responsabilidade da empresa Visualiza Comunicação Visual (ENZO MIGUEL DIAS DA SILVA) adjudicatária sobre a recusa no prosseguimento da execução contratual.
A53: 23.496.090-3 | B53: Aquisição, através de dispensa eletrônica de processo licitatório, de sabão em pó, a fim de suprir a demanda do órgão da Polícia Científica do Paraná. | C53: 45701 | D53: 11160 | E53: CUSTEIO | F53: Dispensa de Licitação | L53: =IF(ISBLANK(J53), "", SUM(J53, K53)) | O53: ARQUIVADO
A54: 23.364.790-0 | B54: Solicitação de compra de Leitores QRCode. PE90830/25 | C54: 45777 | D54: 152155.2 | E54: INVESTIMENTO | F54: Licitação | G54: 45888 | L54: =IF(ISBLANK(J54), "", SUM(J54, K54)) | O54: TRAMITANDO
A55: 23.330.486-7 | B55: Solicitação de reabertura de processo licitatório para aquisição des STUBS para a Polícia Científica do Paraná. PE 150/2025 | C55: 45673 | D55: 98295.8 | E55: CUSTEIO | F55: Licitação | G55: 45926 | H55: 45993 | I55: 45996 | J55: 46000 | K55: 60 | L55: =IF(ISBLANK(J55), "", SUM(J55, K55)) -> 46060 | O55: TRAMITANDO
A56: 23.573.808-2 | B56: SRP Materiais Diversos para Laboratório - Aquisição através do Registro de Preço do PE 352/2023, na modalidade PARTICIPANTE, de Materiais Diversos para Laboratório para atender as necessidades das unidades da Polícia Científica do Paraná. | C56: 45715 | D56: 22453.8 | E56: CUSTEIO | F56: SRP Estadual | G56: 45866 | I56: 45757 | J56: 45762 | K56: 30 | L56: =IF(ISBLANK(J56), "", SUM(J56, K56)) -> 45792 | N56: 45838 | O56: FINALIZADO
A57: 22.075.189-9 | B57: Licitação - Abertura de procedimento Licitatório, visando a aquisição de Cofres para atender a demanda de todas as unidades da Polícia Científica do Paraná. | C57: 45440 | D57: 75039.4 | E57: INVESTIMENTO | F57: Licitação | G57: 45623 | H57: 45692 | I57: 45706 | J57: 45709 | K57: 45 | L57: =IF(ISBLANK(J57), "", SUM(J57, K57)) -> 45754 | N57: 45736 | O57: FINALIZADO
A58: 21.828.132-0 | B58: SOLICITAÇÃO PARA ABERTURA DE PROCESSO LICITATÓRIO PARA CONTRATAÇÃO DE EMPRESA ESPECIALIZADA NO FORNECIMENTO, CONFIGURAÇÃO E IMPLANTAÇÃO DE SISTEMA INFORMATIZADO DE AUTOMAÇÃO E GESTÃO DE LABORATÓRIOS (LIMS), ATRAVÉS DO CONVÊNIO No 919141/2021 - PLATAFORMA + BRASIL POR 12 MESES, PARA ATENDER A SEÇÃO DE GENÉTICA MOLECULAR FORENSE. | C58: 45357 | D58: 642413 | E58: INVESTIMENTO | F58: Licitação | G58: 45603 | H58: 45670 | I58: 45680 | J58: 45692 | K58: 60 | L58: =IF(ISBLANK(J58), "", SUM(J58, K58)) -> 45752 | N58: 45757 | O58: FINALIZADO
A59: 23.828.665-4 | B59: Contratação de serviço de manutenção corretiva do equipamento Hamilton EasyPunch STARlet (StarQ), por inexigibilidade de licitação, para atender a demanda da Seção de Genética Molecular Forense da Polícia Científica do Paraná. | C59: 45776 | D59: 147814.9 | E59: CUSTEIO | F59: Inexigibilidade | L59: =IF(ISBLANK(J59), "", SUM(J59, K59)) | O59: TRAMITANDO
A60: 23.912.341-4 | B60: AQUISIÇÃO DE AR CONDICIONADO PORTÁTIL ATRAVÉS DE ADESÃO À ATA DE REGISTRO DE PREÇOS 236/2024 - UNIVERSIDADE FEDERAL DO PARANÁ - UFPR, PARA ATENDER A DEMANDA DA POLÍCIA CIENTÍFICA DO PARANÁ | C60: 45777 | D60: 18161.65 | E60: INVESTIMENTO | F60: SRP Estadual (Carona) | L60: =IF(ISBLANK(J60), "", SUM(J60, K60)) | O60: ARQUIVADO | P60: Fornecedor declinou no fornecimento
A61: 23.918.447-2 | B61: Solicitação de adesão ao item 42 da ata de registro de preços no 038/2023, UASG 153254, com vigência até 27/09/2025, para aquisição de ultrafreezers laboratoriais para atender a demanda da Seção de Genética Molecular Forense da Polícia Científica do Paraná | C61: 45783 | D61: 274500 | E61: INVESTIMENTO | F61: SRP Estadual (Carona) | I61: 45859 | J61: 45866 | K61: 60 | L61: =IF(ISBLANK(J61), "", SUM(J61, K61)) -> 45926 | M61: 45896 | N61: 45901 | O61: FINALIZADO
A62: 22.403.733-3 | B62: Dispensa de Licitação Eletrônica - Aquisição através de dispensa de licitação de aquisição de Pilhas AA e AAA recarregáveis para atendimento da demanda da Polícia Científica do Paraná. DISPENSA ELETRÔNICA | C62: 45516 | D62: 9301.95 | E62: CUSTEIO | F62: Dispensa de Licitação | I62: 45782 | J62: 45790 | K62: 30 | L62: =IF(ISBLANK(J62), "", SUM(J62, K62)) -> 45820 | N62: 45810 | O62: FINALIZADO
A63: 23.976.044-9 | B63: Dispensa de Licitação Eletrônica - Aquisição através de dispensa de licitação de aquisição de Agulha Hipodérmica 40 x 1,6 mm para atendimento da demanda da Polícia Científica do Paraná. DISPENSA ELETRÔNICA | C63: 45790 | D63: 8059.06 | E63: CUSTEIO | F63: Dispensa de Licitação | I63: 45848 | J63: 45852 | K63: 30 | L63: =IF(ISBLANK(J63), "", SUM(J63, K63)) -> 45882 | M63: 45924 | N63: 45937 | O63: FINALIZADO
A64: 23.970.694-0 | B64: Trata-se da aquisição de copos descartáveis para atendente a demanda da Policia Científica do Paraná. DISPENSA ELETRÔNICA | C64: 45789 | D64: 26808 | E64: CUSTEIO | F64: Dispensa de Licitação | L64: =IF(ISBLANK(J64), "", SUM(J64, K64)) | O64: ARQUIVADO
A65: 23.985.100-2 | B65: SRP Fragmentadora de Papel - Aquisição através do Registro de Preço do PE 595/2024, na modalidade PARTICIPANTE, de Fragmentadora de Papel para atender as necessidades das unidades da Polícia Científica do Paraná. VALIDADE DA ATA: 24/04/2026 | C65: 45791 | D65: 69200 | E65: INVESTIMENTO | F65: SRP Estadual | H65: 45856 | I65: 45876 | J65: 45860 | K65: 30 | L65: =IF(ISBLANK(J65), "", SUM(J65, K65)) -> 45890 | M65: 45881 | N65: 45884 | O65: FINALIZADO
A66: 23.985.963-1 | B66: SRP Limpador Multiuso - Aquisição através do Registro de Preço do PE 113/2024, na modalidade PARTICIPANTE, de Limpador Multiuso para atender as necessidades das unidades da Polícia Científica do Paraná. VALIDADE DA ATA: 06/03/2026 | C66: 45791 | D66: 963.9 | E66: CUSTEIO | F66: SRP Estadual | I66: 45812 | J66: 45817 | K66: 30 | L66: =IF(ISBLANK(J66), "", SUM(J66, K66)) -> 45847 | N66: 45832 | O66: FINALIZADO
A67: 23.994.158-3 | B67: SRP Papel Higiênico Rolão 10 cm x 300 m - Aquisição através do Registro de Preço do PE 1025/2023, na modalidade PARTICIPANTE, de Papel Higiênico Rolão 10 cm x 300 m para atender as necessidades das unidades da Polícia Científica do Paraná. VALIDADE DA ATA: 25/11/2026 | C67: 45792 | D67: 13750 | E67: CUSTEIO | F67: SRP Estadual | I67: 45807 | J67: 45817 | K67: 30 | L67: =IF(ISBLANK(J67), "", SUM(J67, K67)) -> 45847 | N67: 45853 | O67: FINALIZADO
A68: 23.901.224-8 | B68: Aquisição de Ferramenta Forense Avançada de Remoção de Senha e Extração de Dados de Dispositivos Móveis Portáteis | C68: 45775 | D68: 798231 | E68: INVESTIMENTO | F68: Inexigibilidade | H68: 45909 | I68: 45918 | J68: 45918 | K68: 90 | L68: =IF(ISBLANK(J68), "", SUM(J68, K68)) -> 46008 | N68: 45967 | O68: FINALIZADO
A69: 23.166.542-0 | B69: INSTRUÇÃO DE COMPRA - CADEIRAS DO AUDITÓRIO DA NOVA SEDE DA UETC-PG | C69: 45631 | D69: 121371.5 | E69: INVESTIMENTO | F69: Licitação | L69: =IF(ISBLANK(J69), "", SUM(J69, K69)) | O69: ARQUIVADO
A70: 23.695.715-2 | B70: AQUISIÇÃO DE COOKTOP E FRIGOBAR ATRAVÉS DE ADESÃO À ATA DE REGISTRO DE PREÇOS 243/2024 - UNIVERSIDADE FEDERAL DO PARANÁ - UFPR, PARA ATENDER A DEMANDA DA POLÍCIA CIENTÍFICA DO PARANÁ | C70: 45747 | D70: 7650 | E70: INVESTIMENTO | F70: SRP Estadual (Carona) | L70: =IF(ISBLANK(J70), "", SUM(J70, K70)) | O70: TRAMITANDO
A71: 23.841.550-0 | B71: Solicita adesão à ATA SRP no 0008/2025, UASG 155015, para aquisição de Proteinase K (item 21) para atender a demanda da Seção de Genética Molecular Forense da Polícia Científica do Paraná. | C71: 45762 | D71: 820 | E71: CUSTEIO | F71: SRP Federal (Carona) | L71: =IF(ISBLANK(J71), "", SUM(J71, K71)) | O71: ARQUIVADO
A72: 24.031.360-0 | B72: SRP Desktop e Monitores - Aquisição através do Registro de Preço do PE 1031/2023, na modalidade PARTICIPANTE, de Desktop e Monitores para atender as necessidades das unidades da Polícia Científica do Paraná. VALIDADE DA ATA: 14/04/2026 | C72: 45799 | D72: 150480 | E72: INVESTIMENTO | F72: SRP Estadual | H72: 45915 | I72: 45934 | J72: 45915 | K72: 120 | L72: =IF(ISBLANK(J72), "", SUM(J72, K72)) -> 46035 | M72: 46006 | O72: TRAMITANDO
A73: 24.040.265-3 | B73: SRP Licença Software Archicad Brazilian - Aquisição através do Registro de Preço do PE INEX 2/2024, na modalidade PARTICIPANTE, de Licença Software Archicad Brazilian para atender as necessidades das unidades da Polícia Científica do Paraná. VALIDADE DA ATA: 15/05/2026 | C73: 45800 | D73: 73530 | E73: CUSTEIO | F73: SRP Estadual | K73: 10 | L73: =IF(ISBLANK(J73), "", SUM(J73, K73)) | O73: ARQUIVADO | P73: Processo arquivado para solicitar outro tipo de software com ATA disponível. Aberto o 24.761.161-4
A74: 22.683.581-4 | B74: Aquisição de equipamentos de processamento e de armazenamento de vestígios digitais e de equipamentos de gerenciamento de rede através de Termo de Execução Descentralizada - TED no 001/2024 - Lottopar PE 698 2025 | Publicado (abertura 26/08/25) | C74: 45534 | D74: 6793984.2 | E74: INVESTIMENTO | F74: Licitação | G74: 45895 | H74: 45996 | I74: 45999 | J74: 46000 | K74: 120 | L74: =IF(ISBLANK(J74), "", SUM(J74, K74)) -> 46120 | O74: TRAMITANDO
A75: 24.071.567-8 | B75: SRP Lâmina e Corante Giemsa - Aquisição através do Registro de Preço do PE 2121/2024, na modalidade PARTICIPANTE, de Lâmina e Corante Giemsa para atender as necessidades das unidades da Polícia Científica do Paraná. VALIDADE DA ATA: 13/05/2026 | C75: 45806 | D75: 1325 | E75: CUSTEIO | F75: SRP Estadual | I75: 45835 | J75: 45840 | K75: 30 | L75: =IF(ISBLANK(J75), "", SUM(J75, K75)) -> 45870 | M75: 45923 | N75: 45852 | O75: FINALIZADO
A76: 22.774.761-7 | B76: Aquisição de Fuzil 5,56 por meio de adesão à Ata de Registro de Preços da Polícia Militar de Minas Gerais | C76: 45553 | D76: 40970 | E76: INVESTIMENTO | F76: SRP Estadual (Carona) | I76: 45775 | J76: 45784 | K76: 120 | L76: =IF(ISBLANK(J76), "", SUM(J76, K76)) -> 45904 | N76: 45925 | O76: FINALIZADO
A77: 24.016.119-2 | B77: INSTRUÇÃO INICIAL DE PROCESSO LICITATÓRIO VISANDO FUTURA E EVENTUAL AQUISIÇÃO E LOCAÇÃO DE VIATURAS | C77: 45797 | D77: 30802722 | E77: INVESTIMENTO | F77: SRP Estadual | L77: =IF(ISBLANK(J77), "", SUM(J77, K77)) | O77: TRAMITANDO
A78: 24.090.039-4 | B78: Monitores 24" Via SRP - Adesão - Defensoria Publica do Amapá | C78: 45445 | D78: 104850 | E78: INVESTIMENTO | F78: SRP Estadual (Carona) | H78: 45903 | I78: 45924 | J78: 45925 | K78: 30 | L78: =IF(ISBLANK(J78), "", SUM(J78, K78)) -> 45955 | M78: 45942 | N78: 45950 | O78: FINALIZADO
A79: 23.778.317-4 | B79: abertura de processo licitatório para aquisição de 08 unidades de Sistema de Espectrometria de Infravermelho com Transformada de Fourier e Reflexão Total Atenuada (FTIR-ATR) para a Seção de Química Forense. | C79: 45750 | D79: 4382364 | E79: INVESTIMENTO | F79: Licitação | L79: =IF(ISBLANK(J79), "", SUM(J79, K79)) | O79: TRAMITANDO
A80: 22.415.334-1 | B80: aquisição de dois Espectrômetros de massa com plasma indutivamente acoplado (ICP-MS) | C80: 45477 | D80: 5922423.1 | E80: INVESTIMENTO | F80: Licitação | H80: 45902 | I80: 45922 | J80: 45923 | K80: 90 | L80: =IF(ISBLANK(J80), "", SUM(J80, K80)) -> 46013 | M80: 45992 | O80: TRAMITANDO
A81: 22.668.212-0 | B81: Aquisição de reagentes químicos por dispensa de licitação, para atender a demanda das Seções de Genética Molecular Forense, Química Forense e Toxicologia Forense da Polícia Científica do Paraná | C81: 45531 | D81: 29093 | E81: CUSTEIO | F81: Dispensa de Licitação | I81: 45810 | J81: 45810 | K81: 30 | L81: =IF(ISBLANK(J81), "", SUM(J81, K81)) -> 45840 | N81: 45840 | O81: FINALIZADO | P81: Entregue os materiais parcialmente, falta somente o LUMINOL
A82: 22.415.499-2 | B82: Solicitação de abertura de processo de licitação para a aquisição de dois Sistemas de Cromatografia Líquida acoplada a Espectrômetro de Massas de alta resolução do tipo Quadrupolo e Tempo de Voo (LC-qTOF-MS). (Agro Forense) | C82: 45492 | D82: 7879099.7 | E82: INVESTIMENTO | F82: Licitação | G82: 45644 | H82: 45813 | I82: 45826 | J82: 45832 | K82: 90 | L82: =IF(ISBLANK(J82), "", SUM(J82, K82)) -> 45922 | N82: 45901 | O82: FINALIZADO
A83: 24.097.849-0 | B83: SRP de Drones - Aquisição através do Registro de Preço do PE 1327/2024, na modalidade PARTICIPANTE, de Drones para atender as necessidades da Unidade de Execução Técnico-Científica de Curitiba da Polícia Científica do Paraná. VALIDADE DA ATA 27/04/2026 | C83: 45811 | D83: 579575.06 | E83: INVESTIMENTO | F83: SRP Estadual | H83: 45896 | I83: 45840 | J83: 45895 | K83: 60 | L83: =IF(ISBLANK(J83), "", SUM(J83, K83)) -> 45955 | M83: 45943 | N83: 45964 | O83: FINALIZADO | P83: Cobrado o Gestor Felipe Dias no dia 13/10/2025, Felipe informou que a empresa pediu prorrogação de mais 60 dias
A84: 22.385.321-8 | B84: Licitação para a aquisição de 03 Sistemas de cromatografia líquida acoplados a espectrometria de massas em tandem. LC-MS/MS | C84: 45484 | D84: 8432255.9 | E84: INVESTIMENTO | F84: Licitação | G84: 45596 | H84: 45716 | I84: 45735 | J84: 45736 | K84: 120 | L84: =IF(ISBLANK(J84), "", SUM(J84, K84)) -> 45856 | N84: 45853 | O84: FINALIZADO
A85: 23.656.828-8 | B85: SRP - Contratação através do Registro de Preço do PE 847/2024, de prestação de serviço de limpeza, postos 12x36 com insalubridade 40% para atender a unidade de Telemaco Borba da Polícia Científica do Paraná. VALIDADE DA ATA: 17/11/2025. | C85: 45730 | D85: 116360.88 | E85: CUSTEIO | F85: SRP Estadual | G85: 45621 | L85: =IF(ISBLANK(J85), "", SUM(J85, K85)) | O85: TRAMITANDO
A86: 23.766.345-4 | B86: adesão como carona em ATA DE REGISTRO DE PREÇO no 0050/2024/PCI da Polícia Científica de Santa Catarina, para aquisição de Fast Blue Salt e Tiocianato de Cobalto II, para atender a demanda da Seção de Química Forense. | C86: 45748 | D86: 9744.27 | E86: CUSTEIO | F86: SRP Estadual | H86: 45881 | I86: 45902 | J86: 45881 | K86: 60 | L86: =IF(ISBLANK(J86), "", SUM(J86, K86)) -> 45941 | M86: 45925 | N86: 45939 | O86: FINALIZADO
A87: 22.168.566-0 | B87: Licitação - Abertura de procedimento Licitatório, visando a aquisição de CÂMARAS MORTUÁRIAS para a nova unidade da Polícia Científica de Ponta Grossa. | C87: 45441 | D87: 1436816.3 | E87: INVESTIMENTO | F87: Licitação | I87: 45757 | J87: 45814 | K87: 60 | L87: =IF(ISBLANK(J87), "", SUM(J87, K87)) -> 45874 | M87: 45848 | N87: 45918 | O87: FINALIZADO
A88: 24.116.894-8 | B88: Solicitação de Adesão a ATA 011/2024 da SUPERINTENDÊNCIA REGIONAL DA POLÍCIA FEDERAL NO ESTADO DO AMAPÁ visando a aquisição de 40 unidades de Smart Tv 55 | C88: 45813 | D88: 83360 | E88: INVESTIMENTO | F88: SRP Federal (Carona) | H88: 45903 | I88: 45918 | J88: 45903 | K88: 30 | L88: =IF(ISBLANK(J88), "", SUM(J88, K88)) -> 45933 | M88: 45919 | N88: 45929 | O88: FINALIZADO
A89: 22.488.200-9 | B89: Aquisição de Equipamentos SGMF - Inexigibilidade StarletID, EasyPunch e QuantStudio. | C89: 45495 | D89: 4768676.8 | E89: INVESTIMENTO | F89: Inexigibilidade | H89: 45799 | I89: 45814 | J89: 45817 | K89: 30 | L89: =IF(ISBLANK(J89), "", SUM(J89, K89)) -> 45847 | N89: 45847 | O89: FINALIZADO
A90: 22.212.489-1 | B90: Prestação de serviço de manutenção, preventiva e corretiva, de câmaras mortuárias refrigeradas, para atender a demanda de 18 (dezoito) Unidades de Execução Técnico-Científicas (UETCs) da Polícia Científica do Paraná (PCP), pelo período de 12 (doze) meses | C90: 45435 | D90: 2192989.6 | E90: CUSTEIO | F90: Licitação | G90: 45714 | H90: 45819 | I90: 45849 | J90: 45852 | K90: 0 | L90: =IF(ISBLANK(J90), "", SUM(J90, K90)) -> 45852 | N90: 45852 | O90: FINALIZADO
A91: 22.124.897-0 | B91: Instrução de compra referente às mesas de necropsia da nova unidade da Polícia Científica de Ponta Grossa | C91: 45418 | D91: 697746 | E91: INVESTIMENTO | F91: Licitação | H91: 45729 | I91: 45737 | J91: 45740 | K91: 60 | L91: =IF(ISBLANK(J91), "", SUM(J91, K91)) -> 45800 | N91: 45820 | O91: FINALIZADO
A92: 22.443.126-0 | B92: AQUISIÇÃO DE SISTEMA DE CROMATOGRAFIA IÔNICA PARA ANÁLISE SIMULTÂNEA DE ÂNIONS E CÁTIONS COM DETECTORES POR CONDUTIVIDADE | C92: 45483 | D92: 1439800 | E92: INVESTIMENTO | F92: Licitação | G92: 46009 | H92: 45799 | I92: 45799 | J92: 45825 | K92: 90 | L92: =IF(ISBLANK(J92), "", SUM(J92, K92)) -> 45915 | M92: 45890 | O92: TRAMITANDO | P92: Empresa pediu prorrogação até dia 30/10/2025
A93: 24.162.789-6 | B93: Aquisição, através de procedimento licitatório de carrinho de instrumentação para atender a demanda das unidades que realizam exames de necropsia da Polícia Científica do Paraná | C93: 45821 | D93: 87471 | E93: INVESTIMENTO | F93: Licitação | L93: =IF(ISBLANK(J93), "", SUM(J93, K93)) | O93: TRAMITANDO
A94: 24.075.464-9 | B94: Aquisição de Tanques Balísticos - Adesão a Ata de Registro de Preços N° 0049/2024/PCI | C94: 45806 | D94: 255509.8 | E94: INVESTIMENTO | F94: SRP Estadual (Carona) | L94: =IF(ISBLANK(J94), "", SUM(J94, K94)) | O94: ARQUIVADO | P94: vencimento da ata de registro de preços e impossibilidade de aquisição
A95: 24.172.889-7 | B95: protocolo de adesão à ata de lençol descartável | C95: 45824 | D95: 6784 | E95: CUSTEIO | F95: SRP Federal (Carona) | I95: 45901 | J95: 45910 | K95: 30 | L95: =IF(ISBLANK(J95), "", SUM(J95, K95)) -> 45940 | N95: 45916 | O95: FINALIZADO
A96: 24.195.717-9 | B96: SRP - Banco de Jardim - Aquisição através do Registro de Preço do PE 026/2025, na modalidade CARONA, de Banco de Jardim para atender as necessidades das unidades da Polícia Científica do Paraná. | C96: 45831 | D96: 2072 | E96: INVESTIMENTO | F96: SRP Estadual (Carona) | I96: 45961 | J96: 45966 | K96: 30 | L96: =IF(ISBLANK(J96), "", SUM(J96, K96)) -> 45996 | O96: TRAMITANDO
A97: 24.195.811-6 | B97: SRP MATERIAL DE COPA E COZINHA – GRUPO II - Aquisição através do Registro de Preço do PE 366/2023, na modalidade PARTICIPANTE, de MATERIAL DE COPA E COZINHA – GRUPO II para atender as necessidades das unidades da Polícia Científica do Paraná. VALIDADE DA ATA: 01/09/2025 | C97: 45834 | D97: 1050.05 | E97: CUSTEIO | F97: SRP Estadual | I97: 45840 | J97: 45842 | K97: 30 | L97: =IF(ISBLANK(J97), "", SUM(J97, K97)) -> 45872 | N97: 45859 | O97: FINALIZADO
A98: 23.885.636-1 | B98: processo de compra por inexigibilidade para aquisição de um Espectrômetro de Ressonância Magnética Nuclear (RMN) de bancada para atender a demanda da seção de química forense da Polícia Científica do Paraná | C98: 45831 | D98: 1952460.7 | E98: INVESTIMENTO | F98: Inexigibilidade | L98: =IF(ISBLANK(J98), "", SUM(J98, K98)) | O98: TRAMITANDO
A99: 24.197.585-1 | B99: SRP Detergente Laboratorial - Aquisição através do Registro de Preço do PE 107/2024, na modalidade CARONA, de Detergente Laboratorial para atender as necessidades das unidades da Polícia Científica do Paraná. VALIDADE DA ATA: 17/09/2025 | C99: 45831 | D99: 13311.15 | E99: CUSTEIO | F99: SRP Estadual (Carona) | I99: 45867 | J99: 45868 | K99: 30 | L99: =IF(ISBLANK(J99), "", SUM(J99, K99)) -> 45898 | M99: 45915 | N99: 45888 | O99: FINALIZADO
A100: 24.198.214-9 | B100: Aquisição de sacos plásticos para acondicionamento de resíduos hospitalares/infectantes, através de adesão à ata SRP no 2216/2024/SESA PR, vigência: 06/05/2026, para atender a demanda da Polícia Científica do Paraná. | C100: 45825 | D100: 18480 | E100: CUSTEIO | F100: SRP Estadual (Carona) | I100: 45895 | J100: 45896 | K100: 30 | L100: =IF(ISBLANK(J100), "", SUM(J100, K100)) -> 45926 | M100: 45924 | N100: 45929 | O100: FINALIZADO
...

Sheet Compras 2024
A2: 164 | G2: R$ 109.146.876,16 | H2: 72 | I2: 69 | K2: 38 | N2: 13
A3: PROCESSO N° | B3: DESCRIÇÃO | C3: instrução | D3: UNIDADE PCP | E3: Unidade a ser atendida | F3: DATA DE CRIAÇÃO | G3: VALOR PREVISTO | H3: EMPENHO ASSINADO | I3: EMPENHO ENVIADO AO FORNECEDOR (DATA) | J3: Data Máxima de entrega | K3: MATERIAL ENTREGUE (DATA) | L3: VERBA | M3: MODALIDADE | N3: Convênio | O3: SITUAÇÃO | P3: GESTOR | Q3: FISCAL | R3: ONDE ESTÁ | S3: Desde Consulta | T3: Observações
A4: 21.104.002-5 | B4: PROGRAMA PARANÁ MAIS CIDADES - Aquisição de VTR por SRP | C4: Eduarda | D4: Grupo Auxiliar Administrativo | E4: UETC Maringa | F4: 45197 | G4: R$ 150.000,00 | L4: INVESTIMENTO | M4: REGISTRO DE PREÇO (ESTADUAL) | O4: TRAMITANDO | R4: SESP/APCP | S4: 45309 | T4: 05/12/2023 - Aguardando email de confirmação da Toyota 11/01/2023 - Considerando que não houve exito de nenhuma empresa para fornecer o veículo sedan, retorna-se ao divisional para ciência18/01/2024- Encaminhado ao PCP/DA/GAA/COMPRAS para providências
A5: 20.620.696-9 | B5: Convênio No 936068/2022 - aquisição de maletas para atendimento de local de crime (Meta 1 - etapas 1 e 2) Drone e maleta de ferramenta | C5: Eduarda | D5: CURITIBA | E5: TODAS | F5: 45093 | G5: R$ 381.353,30 | H5: 45475 | I5: 45484 | L5: INVESTIMENTO | M5: LICITAÇÃO | N5: 936.068/2022 | O5: TRAMITANDO | P5: Alexandre Guilherme de Lara | Q5: Roman Hector Abril | R5: PCP/ACF/DIR | S5: 45566 | T5: 23/08/2023 - , restitua-se os autos à PCP/DA/GAA/COMPRAS para ciência, análise e demais providências 04/10/2023 Encaminhado com adequações ao setor de licitações via Acessoria 16/11/2023 - Encontra-se no setor de licitações para abertura de procedimento licitatório 05/12/2023 - Encontra-se SESP/DG em fase de adjudicação/homologação17/05/2024- Encaminhado ao PCP/DA/GAOFS para inserção da nota de empenho11/07/2024- Encaminhado ao gestor para acompanhamento da entrega25/09/2024- Descumprimento contratual
A6: 21.585.332-2 | B6: SRP - Aquisição através do Registro de Preço do PE 25/2023, de Etiquetas Adesivas para atender a unidade da Polícia Científica do Paraná. | C6: Eduarda | D6: Grupo Auxiliar Administrativo | E6: TODAS | F6: 45308 | G6: R$ 3.595,26 | H6: 45328 | I6: 45337 | K6: 45364 | L6: CUSTEIO | M6: SRP Estadual | O6: FINALIZADO | P6: Não se aplica | Q6: Não se aplica | R6: SESP/DG/NFS | S6: 45488 | T6: 17/01/2024 - Encaminhado ao Chefe da Divisão para a análise a manifestação 16/02/2024 - Encaminhado para o setor de almoxarifado para aguardar entrega13/03/2024- Material recebido08/05/2024- Material recebido
A7: 21.585.336-5 | B7: SRP - Aquisição através do Registro de Preço do PE 1181/2022, de Material de Limpeza para atender a unidade da Polícia Científica do Paraná. | C7: Eduarda | D7: Grupo Auxiliar Administrativo | E7: TODAS | F7: 45308 | G7: R$ 727,96 | H7: 45327 | I7: 45337 | K7: 45355 | L7: CUSTEIO | M7: SRP Estadual | O7: FINALIZADO | P7: Não se aplica | Q7: Não se aplica | R7: SESP/DG/NFS | S7: 45488 | T7: 17/01/2024 - Encaminhado ao Chefe da Divisão para a análise a manifestação 16/02/2024 - Encaminhado para o setor de almoxarifado para aguardar entrega20/02/2024- Materiais recebidos
A8: 21.602.015-4 | B8: SRP - Contratação através do Registro de Preço do PE 146/2022, de prestação de serviço de locação de veículo para transporte de cadáver para atender as unidades da Polícia Científica do Paraná.VALIDADE DA ATA: 14/02/2024 | C8: Eduarda | D8: Grupo Auxiliar Administrativo | E8: TODAS | F8: 45310 | G8: R$ 504.048,00 | H8: 45384 | I8: 45385 | L8: CUSTEIO | M8: SRP Estadual | O8: ARQUIVADO | P8: Alessandro Burko Lopes | Q8: Philippe Alicio de Carvalho | R8: PCP/DA - PCP/DA/GAA/CONTRATOS | S8: 45586 | T8: 22/01/2024 - Encaminhado ao Chefe da Divisão para a análise a manifestação 19/02/2024 - Encaminhado ao SESP/APC para continuação da tramitação 15/03/2024- Encaminhado ao GAOFS para inserção de nota de empenho02/04/024- Nota de empenho inserida (ainda não foi assinada)03/04/2024- Contrato e Nota de Empenho encaminhados ao fornecedor
A9: 21.607.728-8 | B9: Dispensa de Licitação - Aquisição através de dispensa de licitação de aquisição de Tubo de Coleta Fluoretado e microtubo Eppendorf para atendimento da demanda da Polícia Científica do Paraná. DISPENSA ELETRÔNICA | C9: Eduarda | D9: Grupo Auxiliar Administrativo | E9: Laboratórios | F9: 45313 | G9: R$ 14.730,00 | H9: 45572 | I9: 45576 | J9: 45590 | K9: 45604 | L9: CUSTEIO | M9: DISPENSA ELETRÔNICA | O9: FINALIZADO | P9: Camilla Borges Gazolla | Q9: Josiane Brodzinski | R9: PCP/CWB/TAR/NECRO | S9: 45587 | T9: 30/01/2024 - Encaminhado ao Chefe do Financeiro para a atualização de informações orçamentárias 17/04/2024 - Encaminhado para SESP/APC para continuação da tramitação03/05/2024- Encaminhado ao NFS/OR para aprovação das informações orçamentárias 24/06/2024 - Encaminhado para SESP/COMPRAS para continuação da tramitação 07/08/2024 - Encaminhado para Chefe Divisional para ciência e encaminhamento a SESP/APC 12/09/2024 - Encaminhado para o GAOFS para emissão da Nota de Empenho
A10: 20.917.975-0 | B10: Solicita aquisição de um Sistema de Cromatografia Líquida acoplado a Espectrômetro de Massas Sequencial do tipo Triplo Quadrupolo (LC-MS/MS) para atender as necessidades da Seção de Toxicologia Forense | C10: Marcia | D10: Tarumã | E10: Laboratório de Toxicologia | F10: 45310 | G10: R$ 2.649.085,08 | L10: INVESTIMENTO | M10: LICITAÇÃO | O10: ARQUIVADO | P10: Carolina Schmeiske da Graça | Q10: Raquel de Oliveira Vilhena | R10: PCP/CWB/TAR/TOX | S10: 45415 | T10: 23/01/2024 - Encaminhado ao Chefe da Divisão para a análise a manifestação
A11: 21.555.888-6 | B11: Tem este o objetivo de solicitar a instauração de processo de licitação para aquisição de um Sistema de Cromatografia Gasosa Acoplado a Espectrômetro de Massas (GC/MS/MS), visando atender as necessidades de ampliação do escopo de análises analíticas realizadas pelos Laboratórios de Química Forense e Toxicologia Forense da Polícia Científica do Paraná | C11: Marcia | D11: Tarumã | E11: Laboratório de Toxicologia | F11: 45315 | G11: R$ 2.503.120,12 | L11: INVESTIMENTO | M11: LICITAÇÃO | O11: finalizado | P11: Carolina Schmeiske da Graça | Q11: Raquel de Oliveira Vilhena | R11: SESP - SESP/SL | S11: 45602 | T11: 25/01/2024 - Encaminhado ao Chefe da Divisão para a análise a manifestação08/04/2024- Encaminhado à origem para ciência e providências | U11: difícil | V11: Possibilidade de Empenho Baixa
A12: 20.575.782-1 | B12: Aquisição, através de procedimento licitatório, de duas unidades de Sistema de Espectrometria de Infravermelho com Transformada de Fourier (FTIR) para os Laboratórios de Química Forense da Polícia Científica do Paraná. | C12: Marcia | D12: Tarumã | E12: Laboratório de Química Forene | F12: 45315 | G12: R$ 900.215,75 | L12: INVESTIMENTO | M12: LICITAÇÃO | O12: TRAMITANDO | P12: Carolina Schmeiske da Graça | Q12: Raquel de Oliveira Vilhena | R12: SESP - SESP/DEST/SC | S12: 45602 | T12: 25/01/2024 - Encaminhado ao Chefe da Divisão para a análise a manifestação11/06/2024- Encaminhado à PGE para análise e deliberações 30/07/2024 - Com adequações restituído à APC para continuidade | U12: Licitado - Falta Homologar | V12: Empenho Condicional
A13: 21.599.749-9 | B13: Adesão à Ata de Registro de Preços - PE no 1883/2022, objetivando a aquisição de termômetros para suprir a demanda dos Laboratórios Forenses da Polícia Científica do Paraná.VALIDADE DA ATA: 27/05/2024 | C13: Amanda | D13: Grupo Auxiliar Administrativo | E13: Laboratórios Forenses | F13: 45310 | G13: R$ 5.034,00 | H13: 45392 | I13: 45411 | K13: 45441 | L13: CUSTEIO | M13: SRP Estadual | O13: FINALIZADO | P13: Jaqueline de Moura da Silva | Q13: Carolina Schmeiske da Graça | R13: SESP/DG/NFS | S13: 45498 | T13: 22/01/2024- Aguardando análise do Centro de Planejamento de Compras 01/03/2024- Aguardando autorização da carona04/04/2024- Encaminhado ao Chefe da Divisão para a análise a manifestação29/05/2024- Material entregue 04/06/2024- Encaminhado para liquidação e pagamento
A14: 21.634.362-0 | B14: Solicita a abertura de processo de licitação para aquisição de Café, com o intuito de atender à demanda de todas as Unidades da Polícia Científica do Paraná | C14: Raphael | D14: Grupo Auxiliar Administrativo | E14: TODAS | F14: 45317 | G14: R$ 141.057,00 | L14: CUSTEIO | M14: LICITAÇÃO | O14: ARQUIVADO | P14: Leonardo Morrissy Hostin | Q14: Mauricio Catitas de Sousa | R14: PCP/DA/GAA/COMPRAS | S14: 45582 | T14: 30/01/2024 - Encaminhado ao Chefe da Divisão para a análise a manifestação08/02/2024- Retorno devido à existência de Regitro de Preço vigente 21/03/2024- Encaminhado à PCP/DA/DIV informando o vencimento da ata09/04/2024 - Despacho do DG SESP informando que é para aguardar a liberação da ata de registro de preços. 13/09/2024 Com cancelamento dos lotes 1 e 2 do SRP, documentos e valores atualizados, enviado ao divisional, sugerindo encaminhamento ao financeiro para atualização e posterior envio ao setor de licitaçãoes17/10 - cONSIDERANDO A DIFICULDADE DO PROCESSO, ARQUIVADO (TEM QUE CONTRATAR LABORATORIO PARA ANALISAR AS AMOSTRAS) | U14: NÃO
A15: 21.592.164-6 | B15: Aquisição através de processo licitatório de papel toalha e papel higiênico para atender a demanda das unidades da Polícia Científica do Paraná. | C15: Raphael | D15: Grupo Auxiliar Administrativo | E15: TODAS | F15: 45313 | G15: R$ 109.513,75 | H15: sim | I15: 45544 | L15: CUSTEIO | M15: LICITAÇÃO | O15: TRAMITANDO | P15: Lucas de França Leviski | Q15: Mauricio Catitas de Sousa | R15: SESP/DG/NFS | S15: 45544 | T15: 22/01/2024- Encaminhado ao Chefe da Divisão para a análise e manifestação06/02/2024- Retorno devido à existência de Registro de Preço vigente 26/03/2024 - Com as negativas de participação às SRP e adequações dos documentos que se fizeram necessárias, enviado à PCP/DA/DIV para conhecimento, sugerindo encaminhamento à SESP 06/05/2024- Encaminhado ao PCP/DA/GAA/COMPRAS para providências09/09/2024- Encaminhado ao Almoxarifado para aguardar recebimento
A16: 21.588.711-1 | B16: Inexigibilidade- Manutenção Cromatógrafo gasoso | C16: Raphael | D16: PCP/CWB/TAR/TOX | E16: Seção de Toxicologia Forense | F16: 45308 | G16: R$ 98.797,40 | H16: 45463 | I16: 45468 | L16: CUSTEIO | M16: INEXIGIBILIDADE | O16: FINALIZADO | P16: Carolina Schmeiske da Graça | Q16: Dayse Fernanda de Souza | R16: PCP/CWB/TAR/TOX | S16: 45469 | T16: 30/01/2024 - Encaminhado ao Chefe da Divisão para a análise e manifestação 08/03/2024 - Encaminhado ao SESP/SC para continuação da tramitação03/04/2024- Encaminhado ao PCP/DA/GAA/COMPRAS para inclusão do ato de designação do agente de contratação20/06/2024- Nota de empenho assinada25/06/2024- Encaminhado para a gestora do contrato para acompanhamento da prestação do serviço
A17: 21.349.114-8 | B17: Dispensa de Licitação - Aquisição através de dispensa de licitação de aquisição de álcool e água oxigenada para atendimento da demanda da Polícia Científica do Paraná. DISPENSA ELETRÔNICA | C17: Raphael | D17: Grupo Auxiliar Administrativo | E17: TODAS | F17: 45250 | G17: R$ 16.715,60 | H17: 45516 | I17: 45520 | K17: 29/08/2024; 27/09/2024 | L17: CUSTEIO | M17: DISPENSA ELETRÔNICA | O17: FINALIZADO | P17: Regina de Paula Xavier Gomes | Q17: Anne Caroline Kambara Scholze | R17: PCP/DA/GAA/COMPRAS | S17: 45582 | T17: 30/01/2024 - Encaminhado ao Chefe do Financeiro para a atualização de informações orçamentárias21/02/2024 - Encaminhado ao SESP/AT via SESP/APC para continuação da tramitação21/05/2024- Encaminhado ao PCP/DA/GAA/COMPRAS para ciência e providências 13/06/2024 - Após disputa eletrônica enviado ao setor de compras/sesp29/07/2024- Encaminhado ao GAOFS para inserção de nota de empenho16/08/2024- Aguardando entrega29/08/2024- Material entregue 27/09/2024- Material entregue
A18: 20.651.072-2 | B18: Solicita a abertura de processo de licitação para aquisição de controle de acesso, com o intuito de atender à demanda da Unidade Tarumã | C18: Raphael | D18: PCP/DCV/DIV | E18: Tarumã | F18: 45099 | G18: R$ 587.051,94 | H18: 45665 | I18: 45686 | L18: INVESTIMENTO | M18: LICITAÇÃO | O18: TRAMITANDO | P18: Vinicius Gamarra Contieri | Q18: Camilla Borges Gazolla | R18: PCP/CWB/TAR/NECRO | S18: 45691 | T18: 26/01/2024 - Encaminhado ao Chefe da Divisão para a análise a manifestação 21/02/2024 - Encaminhado ao SESP/NFS via SESP/APC para continuação da tramitação 12/04/2024- Encaminhado à PGE/PRC para análise e deliberações 09/05/2024 - Encaminhado a unidade demandante para adequações 17/05/2024 - Encaminhado a SESP/APC para continuação da tramitação 03/02/2025 - Encaminhado ao Gestor do contrato para acompanhamento da execução das instalações | U18: Licitado e Homologado | V18: Empenho Imediato | X18: Dilação de prazo formalizada, os produtos deverão ser entregues ate dia 23/07/2025
A19: 20.402.562-2 | B19: FUNSUSP - AQUISIÇÃO, ATRAVÉS DE PROCEDIMENTO LICITATÓRIO, DE 20 POLTRONAS DE MASSAGEM | C19: Eduarda/Raphael | D19: CURITIBA | E19: TODAS | F19: 45049 | G19: R$ 287.230,60 | L19: INVESTIMENTO | M19: LICITAÇÃO | N19: FUNSUSP | O19: TRAMITANDO | P19: Vinicius Gamarra Contieri | Q19: Marceli dos Santos Gama | R19: PCP/DIR/DIRADM | S19: 45552 | T19: 22/05/2023 - Encaminhado ao PCP/DIV para análise e manifestação 20/06/2023 - Encaminhado a ao SESP/SL via Apoio Técnico da Polícia Científica para continuação da tramitação 11/07/2023 - Retorno para o GAA para providências 21/09/2023 - Encaminhado a ao SESP/SL via Apoio Técnico da Polícia Científica para continuação da tramitação 03/10/2023 - Enviado ao SESP/GOFS/FI para atualizações orçamentárias, sugerindo encaminhamento SESP/SL via SESP/APC 16/11/2023 - Retorno a PCP/DA/DIRADM tendo em vista que o protocolo chegou após a data limite para análise juridica.31/01/2024- Aguardando atualização de orçamento para envio ao SESP/APC 19/02/2024 - Encaminhado a SESP/NFS via SESP/APC para inclusão das informações orçamentarias e continuação da tramitação 01/04/2024 - Após nova atualização de valores, encaminhado à SESP/NFS via APC para inclusão de Inf. Orç, solicitando retorno para continuidade de instrução 09/05/2024 - Encaminhado a unidade demandante para adequações 11/07/2024 - Encaminhado para SESP/APC para continuação da tramitação | U19: não | V19: Sem Possibilidade de Empenho
A20: 21.582.699-6 | B20: Solicita a abertura de processo de licitação para aquisição de aparelhos de ar condicionado, com o intuito de atender à demanda da Polícia Científica do Paraná | C20: Raphael | D20: Grupo Auxiliar Administrativo | E20: TODAS | F20: 45307 | G20: R$ 448.316,80 | L20: INVESTIMENTO | M20: LICITAÇÃO | O20: TRAMITANDO | P20: Weverson Mendes de Lima | Q20: Augusto Pasqualini Neto | R20: SESP/SL | S20: 45574 | T20: 31/01/2024- Aguardando orçamentos para conclusão de cadastro em PCP/DA/GAA/COMPRAS07/06/2024- Encaminhado à Direção Administrativa para aprovação da despesa 04/10/2024-Com adequações encaminhado Setor de Licitações | U20: Licitando - PE90866/2024 - Talvez | V20: Indefinido
A21: 21.267.957-7 | B21: Manutenção nos microscópios comparadores balísticos Leica | C21: Raphael | D21: Grupo Auxiliar Administrativo | E21: Curitiba, Maringá, Londrina e Ponta Grossa | F21: 45231 | G21: R$ 168.750,00 | H21: 45454 | I21: 45456 | K21: 45569 | L21: INVESTIMENTO | M21: INEXIGIBILIDADE | O21: FINALIZADO | P21: Luiz Henrique da Silva Rotta | Q21: Luciano Gardano Elias Bucharles | R21: SESP/DG/NFS | S21: 45587 | T21: 30/01/2024 - Encaminhado ao Chefe do Financeiro para a atualização de informações orçamentárias09/04/2024- Encaminhado a PGE/AUT para análise e manifestação13/06/2024- Encaminhado para acompanhamento da entrega
A22: 20.634.920-4 | B22: Aquisição através de dispensa de licitação de cofres mecânicos relativo ao convênio federal 906.311/2020 para atendimento da Academia de Ciência Forense da Polícia Científica do Paraná. DISPENSA ELETRÔNICA | C22: Eduarda/Raphael | D22: ACF | E22: CURITIBA - ACADEMIA DE CIÊNCIAS FORENSES - ACF | F22: 45098 | G22: R$ 19.055,67 | L22: INVESTIMENTO | M22: DISPENSA ELETRÔNICA | N22: 906.311/2020 | O22: ARQUIVADO | P22: Ronald Silva Szafirski | Q22: Emílio Merino de Paz Júnior | R22: PCP/ACF/DIR | S22: 45355 | T22: 21/08/2023 - encaminhe-se à SESP/DG para apreciação e demais gestões 23/08/2023 - Encaminhado a SESP/DG para analise. 14/11/2023 - Encaminhado a SESP/COMPRAS via SESP/APC para continuação da tramitação 16/11/2023 - Encontra-se no setor de compras para analise do processo 05/12/2023 - Encontra-se SESP/DG em fase de autorizo19/01/2024 - Atualizado orçamento da empresa vencedora, encaminhado SESP/APC para continuidade
A23: 20.481.153-9 | B23: Solicitação de abertura de procedimento licitatório, visando a contratação de empresa especializada em prestação de serviços de locação de rastreadores veiculares, em substituição ao Protocolo 18.805.485-4, a fim de atender a demanda da Polícia Científica do Paraná. Apensado ao 21.828.937-1 | C23: Raphael | D23: CURITIBA | E23: TODAS | F23: 45062 | G23: R$ 164.160,00 | L23: CUSTEIO | M23: LICITAÇÃO | O23: Apensado | P23: Alessandro Burko Lopes | Q23: Philippe Alicio de Carvalho | R23: SESP/SL | S23: 45539 | T23: 31/05/2023 - Protocolo enviado DA/SEC para análise e manifestação 16/08/2023 - Enviado ao Apoio Técnico para continuidade de tramitação 16/11/2023 - Retorno a Origem tendo em vista que o protocolo chegou após a data limite para análise juridica. (Aguardar 2024)16/01/2024 - Com devidas adequações enviado PCP/DA/DIV06/02/2024 - Após adequações Prot devolvido ao Setor de Licitações.
A24: 21.672.986-2 | B24: SRP - Aquisição através do Registro de Preço do PE 26/2023, objetivando aquisição de material de Expediente - Grupo B para suprir a demanda da Polícia Científica do Paraná.VALIDADE DA ATA: 16/01/2025 | C24: Rodrigo Bianchini | D24: Grupo Auxiliar Administrativo | E24: TODAS | F24: 45324 | G24: R$ 4.059,60 | H24: 45362 | I24: 45392 | K24: 16/04/2024; 22/04/2024 | L24: CUSTEIO | M24: SRP Estadual | O24: FINALIZADO | P24: Rodrigo Taborda Ribas | Q24: Mauricio Catitas de Sousa | R24: PCP/DA/GAA/ALMOX | S24: 45454 | T24: 07/02/2024 - Encaminhado para o Chefe da Divisão Administrativa para análise e manifestação20/02/2024- Encaminhado ao GAOFS para informações orçamentárias e nota de reserva11/03/2024- Nota de empenho assinada 16/04/2024- Materiais recebidos22/04/2024- Materiais recebidos 07/05/2024- Encaminhado para liquidação e pagamento
A25: 21.680.216-0 | B25: SRP - Aquisição através do Registro de Preço do PE 28/2023, objetivando aquisição de material de Expediente - Grupo D para suprir a demanda da Polícia Científica do Paraná.VALIDADE DA ATA: 29/01/2025 | C25: Rodrigo Bianchini | D25: Grupo Auxiliar Administrativo | E25: TODAS | F25: 45327 | G25: R$ 1.817,48 | H25: 45377 | I25: 45393 | K25: 45407 | L25: CUSTEIO | M25: SRP Estadual | O25: FINALIZADO | P25: Rodrigo Taborda Ribas | Q25: Mauricio Catitas de Sousa | R25: SESP/DG/NFS | S25: 45498 | T25: 07/02/2024 - Encaminhado para o Chefe da Divisão Administrativa para análise e manifestação07/02/2024- Encaminhado ao GAOFS para informações orçamentárias e nota de reserva22/03/2024- Encaminhado para assinatura das notas de empenho25/04/2024- Materiais recebidos07/05/2024- Encaminhado para liquidação e pagamento
A26: 21.343.742-9 | B26: DISPENSA DE PROCEDIMENTO LICITATÓRIO POR INEXIGIBILIDADE PARA AQUISIÇÃO DE IMUNOENSAIOS CROMATOGRÁFICOS PARA A DETECÇÃO RÁPIDA DE HB PARA A IDENTIFICAÇÃO DE SANGUE E DE ANTÍGENO ESPECÍFICO DA PRÓSTATA (PSA) PARA A DENTIFICAÇÃO DE LÍQUIDO SEMINAL EM AMOSTRAS FORENSES, PARA ATENDER A DEMANDA DA SEÇÃO DE GENÉTICA MOLECULAR FORENSE DA POLÍCIA CIENTÍFICA DO PARANÁ. | C26: Eduarda/Raphael | D26: Genética | E26: Genética | F26: 45271 | G26: R$ 617.250,00 | H26: 45434 | I26: 45453 | K26: 45477 | L26: CUSTEIO | M26: INEXIGIBILIDADE | O26: FINALIZADO | P26: Jaqueline Andressa Machado Trentin Luz | Q26: Juliane Carlotto | R26: SESP/DG/NFS | S26: 45490 | T26: 16/01/2024 - Encaminhado para o Chefe da Divisão Administrativa para análise e manifestação06/02/2024 Após adequações restituído ao setor de Compras/SESP21/02/2024- Empenho emitido, encaminhado à SESP/DG para providências 15/03/2024 - Encaminhado a SESP/DEST/SC para continuação da tramitação30/04/2024- Contrato cadastrado no GMS; encaminhado ao GAOFS para providências 04/07/2024- Materiais entregues
A27: 21.555.831-2 | B27: Tem este o objetivo de solicitar a instauração de processo de licitação para aquisição de um Sistema de Cromatografia Líquida Acoplado a Espectrômetro de Massas de Alta Resolução (quadrupolo e tempo de voo - LC-qTOF), visando atender as necessidades de ampliação do escopo de análises analíticas realizadas pelos Laboratórios de Química Forense e Toxicologia Forense da Polícia Científica do Paraná. QUímica AGRO Forense | C27: Marcia | D27: Química | E27: Química | F27: 45330 | G27: R$ 3.694.713,38 | L27: INVESTIMENTO | M27: LICITAÇÃO | O27: ARQUIVADO | P27: Carolina Schmeiske da Graça | Q27: Raquel de Oliveira Vilhena | R27: PCP/CWB/TAR/QUIM | S27: 45491 | T27: 08/02/2024 - Abertura do processo licitatório03/05/2024- Encaminhado à SESP/DEST para providências
A28: 21.556.083-0 | B28: Solicita abertura de processo licitatório para aquisição de freezers e refrigeradores científicos, a fim de atender as demandas dos Laboratórios de Toxicologia Forense, Química Forense, Genética Forense e Central de Custódia da Polícia Científica do Paraná. | C28: Marcia | D28: Tarumã | E28: Toxicologia | F28: 45330 | G28: R$ 116.916,00 | L28: INVESTIMENTO | M28: LICITAÇÃO | O28: TRAMITANDO | P28: Carolina Schmeiske da Graça | Q28: Anna Carolina de Moraes Braga | R28: PCP/CWB/TAR/TOX | S28: 45467 | T28: 08/02/2024 - Abertura do processo licitatório 16/02/2024 - Encaminhado ao Divisional para análise e manifestação 26/03/2024 - Encaminhado a origem para adequação 04/06/2024- Encaminhado à SESP/SL para ciência e providências 21/06/2024- Encaminhado à origem para adequações | U28: Não - Enviado em 06/2024 para adequar e não retornou mais | V28: Indefinido
A29: 21.556.070-8 | B29: Tem este o objetivo de solicitar a instauração de processo de licitação para aquisição de um Sistema de Cromatografia iônica, visando atender as necessidades do Laboratórios de Química Forense e Toxicologia Forense da Polícia Científica do Paraná. Química Agro Forense | C29: Marcia | D29: Tarumã | E29: Química | F29: 45330 | G29: R$ 1.155.560,80 | L29: INVESTIMENTO | M29: LICITAÇÃO | O29: ARQUIVADO | P29: Carolina Schmeiske da Graça | Q29: Raquel de Oliveira Vilhena | R29: PCP/CWB/TAR/QUIM | S29: 45491 | T29: 08/02/2024 - Abertura do processo licitatório03/05/2024- Encaminhado à SESP/DEST para providências
A30: 21.706.486-4 | B30: Adesão à Ata de Registro de Preços - PE no 1142/2022, na modalidade carona, objetivando a aquisição de papel higiênico para suprir a demanda da Polícia Científica do Paraná. VALIDADE DA ATA: 01/04/2024 | C30: Amanda | D30: Grupo Auxiliar Administrativo | E30: Todos | F30: 45338 | G30: R$ 26.250,00 | L30: CUSTEIO | M30: SRP Estadual | O30: ARQUIVADO | P30: Leonardo Morrissy Hostin | Q30: Mauricio Catitas de Sousa | R30: PCP/DA/GAA/COMPRAS | S30: 45377 | T30: 20/02/2024- Encaminhado ao GAOFS para informação orçamentária e nota de reserva04/03/2024- Aguardando autorização da carona21/03/2024 - Não oha saldo para carona conforme informação do DECON
A31: 21.722.777-1 | B31: Dispensa de processo licitatório por inexigibilidade para aquisição de insumos para a Plataforma de Sequenciamento Massivo Paralelo (de nova geração) Ion Genestudio S5 e Ion Chef HID para atender a demanda da Seção de Genética Molecular Forense da Polícia Científica do Paraná. | C31: Marcia | D31: Tarumã | E31: Genética | F31: 45338 | G31: R$ 1.954.863,96 | L31: CUSTEIO | M31: INEXIGIBILIDADE | O31: APENSADO | P31: Luciellen D'avilla Giacomel Kobachuck | Q31: Pedro Henrqiue Canezin | R31: PCP/CWB/TAR/GENET | S31: 45544 | T31: 20/02/2024 - Encaminhado para o Chefe da Divisão Administrativa para análise e manifestaçãoEste protocolo está apensado ao 21.760.337-4
A32: 21.556.005-8 | B32: Tem este o objetivo de solicitar a instauração de processo de licitação para aquisição de um Sistema de Espectometria de Massas com plasma indutivamente acoplado (ICP/MS/MS), visando atender as necessidades de ampliação do escopo de análises analíticas realizadas pelos Laboratórios de Química Forense e Toxicologia Forense da Polícia Científica do Paraná. Química Agro Forense | C32: Marcia | D32: Tarumã | E32: Laboratórios de Química Forense e Toxicologia Forense | F32: 45314 | G32: R$ 2.539.153,47 | L32: INVESTIMENTO | M32: LICITAÇÃO | O32: ARQUIVADO | P32: Raquel de Oliveira Vilhena | Q32: Carolina Schmeiske da Graça | R32: PCP/CWB/TAR/QUIM | S32: 45491 | T32: 21/02/2024 - Encaminhado para o Chefe da Divisão Administrativa para análise e manifestação03/05/2024- Encaminhado à SESP/DEST para ciência e providências
A33: 21.631.509-0 | B33: SRP Cadeiras Giratórias - Aquisição através do Registro de Preço do PE 1415/2022, de Cadeiras Giratórias para atender a demanda das unidades da Polícia Científica do Paraná.VALIDADE DA ATA: 15/10/2024 | C33: Amanda | D33: Grupo Auxiliar Administrativo | E33: Tarumã | F33: 45322 | G33: R$ 13.621,21 | H33: 45509 | I33: 45510 | K33: 02/09/2024; 18/09/2024 | L33: INVESTIMENTO | M33: SRP Estadual | O33: FINALIZADO | P33: Adriano Saldanha Carneiro | Q33: Edgar Mallmann | R33: SESP/DG/NFS | S33: 45559 | T33: 19/02/2024 - Encaminhado a SESP/COMPRAS para continuação da tramitação 13/03/2024 - Encaminhado a SESP/DEST/SC para continuação da tramitação, bem como, elaboração da minuta de contrato30/04/2024- Retorno do processo à PCP/DA/GAA/COMPRAS para inserção de documentos 24/05/2024 - Encaminhado a AT/SESP via SESP/APC para continuação da tramitação 09/07/2024- Encaminhado ao GAOFS para inserção de nota de empenho08/08/2024- Aguardando entrega02/09/2024- Material entregue (FK)18/09/2024- Material entregue (EKOMB)
A34: 20.719.484-0 | B34: Licitação para aquisição de kits de Sistema de Vigilância - Circuito Fechado de TV (CFTV), sem instalação, para as sedes do Interior da Polícia Científica do Paraná | C34: Raphael | D34: Computação Forense | E34: Todas | F34: 45173 | G34: R$ 347.269,76 | L34: INVESTIMENTO | M34: LICITAÇÃO | O34: TRAMITANDO | P34: Leonardo de Ataide Jedneralski | Q34: Marcio Lopes Villanova e Silva | R34: PCP/DA/GAOFS | S34: 45692 | T34: 06/11/2023 - Retorno ao setor de compras PCP para adequações 16/11/2023 - Com as devidas alterações, restituído SESP/SL via SESP/APC 05/12/2023 - Encontra - se na assessoriaTécnica desta SESP para análise da redação de minuta do edital. 06/12/2023 - DEVOLVIDO A ORIGEM ENVIO FORA DO PRAZO - PCP/DIR/NI22/02/2024- Anexada a minuta padronizada da PGE, remetemos o procedimento à Assessoria Técnica Jurídica para providências cabíveis09/04/2024- Encaminhado ao PCP/DA/GAA/COMPRAS para ciência e providências 26/09/2024 - Com novas atualizações encaminhado ao setor financeiro para atualizações de informações orçamentárias. 04/02/2025 - Encaminhado para o PCP/DA/GAOFS para emissão da nota de empenho | U34: TALVEZ - CERTAME | PE 994/23 | PUBLICADO (abertura em 11/11/24) | V34: Indefinido
A35: 21.739.658-1 | B35: Aquisição de café por meio da Ata de Registro de Preços - PE no 1786/2022, para suprir a demanda da Polícia Científica do Paraná. | C35: Amanda | D35: Grupo Auxiliar Administrativo | E35: TODAS | F35: 45341 | G35: R$ 75.600,00 | H35: 45425 | L35: CUSTEIO | M35: SRP Estadual | O35: TRAMITANDO | P35: Leonardo Morrissy Hostin | Q35: Mauricio Catitas de Sousa | R35: PCP/DA/GAA/COMPRAS | S35: 45582
A36: 21.728.149-0 | B36: Contratação direta por dispensa de licitação para aquisição de rolos de papel alumínio com 7,5 m de comprimento e 30 cm de largura para atender a demanda das Seções de Química Forense e Toxicologia Forense, da Polícia Científica do Paraná. | C36: Eduarda | D36: Grupo Auxiliar Administrativo | E36: Seção de Química e Toxicologia Forense | F36: 45341 | G36: R$ 510,94 | H36: 45425 | I36: 45433 | K36: 45439 | L36: CUSTEIO | M36: DISPENSA DE LICITAÇÃO | O36: FINALIZADO | P36: Ricardo Maia | Q36: Paula Eidt Fornari | R36: SESP/DG/NFS | S36: 45498 | T36: 28/02/2024 - Encaminhado a PCP/DIV para análise e manifestação 12/03/2024 - Encaminhado ao SESP/COMPRAS para continuação da tramitação por menor valor 04/04/2024 - Encaminhado ao SESP/COMPRAS para continuação da tramitação29/04/2024- Encaminhado para assinatura da Nota de Empenho21/05/2024- Empenho e O.C encaminhados ao fornecedor- Aguardando entrega03/06/2024- Encaminhado para liquidação e pagamento
A37: 21.399.689-4 | B37: Dispensa de Licitação, na modalidade Eletrônica, para aquisição de Caixa de Arquivo Morto em atendimento da demanda da Polícia Científica do Paraná. DISPENSA ELETRÔNICA | C37: Eduarda | D37: Grupo Auxiliar Administrativo | E37: Todas | F37: 45259 | G37: R$ 11.504,00 | H37: 45567 | I37: 45512 | K37: 45552 | L37: CUSTEIO | M37: DISPENSA ELETRÔNICA | O37: FINALIZADO | P37: Beatriz Rossi Canuto de Menezes Rodrigues | Q37: Mauricio Catitas de Souza | R37: SESP/DG/NFS | S37: 45575 | T37: 06/12/2023 - ENCAMINHADO EM 04/12 PARA NFS/OR para assinatura das informações orçamentárias 13/12/2023 - Encaminhado ao PCP/DA/DIV para ciência e posterior envio até o dia 02/01/2024 22/01/2024 - Encaminhado ao PCP/DA/GAOFS para continuação da tramitação 23/02/2024 - Encaminhado ao SESP/COMPRAS para continuação da tramitação18/03/2024- Encaminhado à Assessoria Técnica da SESP solicitando autorizção do ordenador de despesas 26/06/2024 - Encaminhado para SESP/COMPRAS para continuação da tramitação 08/08/2024- Aguardando entrega17/09/2024- Material entregue
A38: 21.307.642-6 | B38: Dispensa de procedimento licitatório por inexigibilidade para aquisição de insumos para a Plataforma Automatizada Hamilton Starlet e para os Analisadores Genéticos 3500 conforme instrumento de convênio Federal firmado sob o no 905.779/2020 para atender a demanda da Seção de Genética Molecular Forense da Polícia Científica do Paraná. | C38: Marcia | D38: Tarumã | E38: Seção de Genética Forense | F38: 45247 | G38: R$ 371.418,26 | H38: 45434 | I38: 45436 | K38: 45450 | L38: CUSTEIO | M38: INEXIGIBILIDADE | N38: 905.779/2020 | O38: FINALIZADO | P38: Jaqueline Andressa Machado Trentin Luz | Q38: Pedro Henrique Canezin | R38: PCP/CWB/TAR/GENET | S38: 45502 | T38: 20/11/2023 - Encaminhado a PCP/DIV para análise e manifestação 05/12/2023 - Devolvido ao setor sugerindo a remessa dos autos à origem para impulsionamento do protocolado a partir do dia 02 de janeiro de 2024 06/12/2023 - DEVOLVIDO À ORIGEM - PCP/CWB/TAR/QUIM 02/01/2024 - Encaminhado a AT/SESP via SESP/APC para a continuação da tramitação 19/01/2024 - Encanhado a SESP/APC para a continuação da tramitação 26/02/2024 - Encanhado a SESP/APC para a continuação da tramitação01/04/2024- Encaminhado para emissão da CALV09/05/2024- Contrato assinado07/06/2024- Parte dos materiais entregue
A39: 21.775.959-5 | B39: SRP - Contratação de dois postos de arquivista por meio de adesão à Ata de Registro de Preços - PE n 2168/2022, para suprir a demanda da Polícia Científica do Paraná. VALIDADE DA ATA: 15/07/2024 | C39: Eduarda | D39: Grupo Auxiliar Administrativo | F39: 45366 | G39: R$ 219.573,60 | L39: CUSTEIO | M39: SRP Estadual | O39: ARQUIVADO | P39: Fabiola Schutzenberger Machado | Q39: Vinicius Gamarra Contieri | R39: PCP/DA/GAA/COMPRAS | S39: 45588 | T39: 06/03/2024- Carona autorizada; aguardando instrução 15/03/2024 - Encaminhado a PCP/DA/DIV para análise e manifestação18/03/2024- Encaminhado ao GAOFS para informações orçamentárias e nota de reserva 09/05/2024 - Encaminhado para SESP/COMPRAS para análise e continuação da tramitação 17/05/2024 - Encaminhado para SESP/DEST/SC 06/06/2024 - Encaminhado para AT/SESP via SESP/APC para continuação da tramitação 14/08/2024 - Encaminhado para Divisional para ciência
A40: 21.556.068-6 | B40: Processo de compra de microscópios comparadores para a Seção de Balística de Curitiba - Inexigibilidade de Licitação | C40: Eduarda | D40: Visconde | E40: Seção de Balística Forense | F40: 45338 | G40: R$ 3.510.000,00 | L40: INVESTIMENTO | M40: INEXIGIBILIDADE | O40: ARQUIVADO | P40: Gisele Rodrigues dos Santos Oliveira | Q40: Carlos Silveira de Barros | R40: PCP/CWB/VISC/BALI | S40: 45474 | T40: 28/02/2024 - Encaminhado a PCP/DIV para análise e manifestação
A41: 21.718.196-8 | B41: Contratação direta por dispensa de processo licitatório para aquisição de papel de filtro qualitativo de e caixas de fibra de papelão para armazenamento de amostras, para atender a demanda das Seções de Química Forense e Toxicologia Forense da Polícia Científica do Paraná. | C41: Eduarda | D41: Tarumã | E41: Seção de Quimica e Toxicologia Forense | F41: 45343 | G41: R$ 5.674,98 | L41: CUSTEIO | M41: DISPENSA DE LICITAÇÃO | O41: ARQUIVADO | R41: PCP/CWB/TAR/QUIM | S41: 45362 | T41: 28/02/2024 - Retornado a origem para adequação
A42: 21.790.813-2 | B42: SRP - Aquisição através do Registro de Preço do PE 53/2023, de Detergente e Desodorizador para atender a unidade da Polícia Científica do Paraná. VALIDADE DA ATA: 27/06/2024 | C42: Rodrigo Bianchini | D42: Grupo Auxiliar Administrativo | E42: Todas | F42: 45350 | G42: R$ 2.789,25 | H42: 45363 | I42: 45392 | K42: 45398 | L42: CUSTEIO | M42: SRP Estadual | O42: FINALIZADO | P42: Rodrigo Taborda Ribas | Q42: Mauricio Catitas de Sousa | R42: SESP/DG/NFS | S42: 45489 | T42: 28/02/2024 - Encaminhado a PCP/DIV para análise e manifestação08/03/2024- Encaminhado ao NFS/OR para assinatura das informações orçamentárias11/03/2024- Empenho assinado 16/04/2024- Materiais recebidos07/05/2024- Encaminhado para liquidação e pagamento
A43: 20.195.722-2 | B43: Aquisição de Equipamentos de gerenciamento de rede para grandes volumes de dados com instalação, por licitação - Convênio Federal no 936068/2022 | C43: Eduarda | D43: CURITIBA | E43: SESSÃO DE COMPUTAÇÃO FORENSE | F43: 45007 | G43: R$ 260.576,58 | H43: 45546 | I43: 45551 | L43: INVESTIMENTO | M43: LICITAÇÃO | O43: TRAMITANDO | P43: Henrique Galperin | Q43: Fabio Luiz Correia da Rocha | R43: PCP/CWB/VISC/COMP | S43: 45582 | T43: 17/04/2023 - Encaminhado à Divisão Administrativa para análise e demais providências 31/07/2023 - Devolvido à origem para adequações 30/08/2023 - Encaminhado ao setor de compras após adequações necessarias 04/09/2023 - Devolvido a origem para adequação TR 16/11/2023 - Análise da Tecnologia de Comunicação quanto ao objeto pretendido ser, ou não, caracterizado como TIC 05/12/2023 - Encontra-se SESP/AT/ASS 16/01/2024 - Encaminhado a SESP/APC para continuação da tramitação 28/02/2024 - Devolvido a origem para adequações 04/03/2024 - Encaminhado a SESP/APC para continuação da tramitação16/05/2024- Encaminhado para emissão de Nota de Reserva16/09/2024- Aguardando entrega
A44: 21.790.967-8 | B44: SRP - Aquisição através do Registro de Preço do PE 54/2023, de Sabão em Pó, Sabão em Barra e Pedra Sanitária para atender a unidade da Polícia Científica do Paraná. | C44: Rodrigo Bianchini | D44: Grupo Auxiliar Administrativo | E44: Todas | F44: 45350 | G44: R$ 1.299,65 | H44: 45371 | I44: 45392 | K44: 12/04/2024; 18/04/2024 | L44: CUSTEIO | M44: SRP Estadual | O44: ARQUIVADO | P44: Rodrigo Taborda Ribas | Q44: Mauricio Catitas de Sousa | R44: SESP/DG/NFS | S44: 45499 | T44: 29/02/2024 - Encaminhado a PCP/DIV para análise e manifestação 21/03/2024- Empenho assinado12/04/2024- Materiais recebidos18/04/2024- Materiais recebidos07/05/2024- Encaminhado para liquidação e pagamento
A45: 21.791.908-8 | B45: SOLICITAÇÃO PARA AQUISIÇÃO DE PAPEL KRAFT, VIA PREGÃO ELETRÔNICO 26/2023/DECON - LOTE 29 - NA MODALIDADE ADESÃO/CARONA, VALIDADE DA ATA 16/01/2025, ENTREGA ÚNICA, PARA SUPRIR A DEMANDA DOS LABORATÓRIOS FORENSES DA POLÍCIA CIENTÍFICA DO PARANÁ - UNIDADE TARUMÃ - CURITIBA.VALIDADE DA ATA:16/01/2025 | C45: Amanda | D45: Grupo Auxiliar Administrativo | E45: Tarumã | F45: 45345 | G45: R$ 2.040,00 | H45: 45384 | I45: 45411 | K45: 45441 | L45: CUSTEIO | M45: SRP Estadual | O45: FINALIZADO | R45: SESP/DG/NFS | S45: 45488 | T45: 15/03/2024- Encaminhado ao GAOFS para informações orçamentárias e nota de reserva04/04/2024- Nota de Empenho assinada29/05/2024- Material recebido04/06/2024- Encaminhado para liquidação e pagamento
A46: 21.731.579-4 | B46: Abertura de processo licitatório, visando a contratação de empresa especializada em prestação de serviços de consultoria e acreditação do Laboratório de Genética Molecular Forense da Polícia Científica do Paraná, na norma ABNT NBR ISO 17025:2017, conforme instrumento de convênio firmado n.o 919141/2021. | C46: Marcia | D46: Tarumã | E46: Seção Genética Forense | F46: 45349 | G46: R$ 170.890,60 | L46: CUSTEIO | M46: LICITAÇÃO | O46: TRAMITANDO | P46: Paula Eidt Fornari | Q46: Claudia Marina Schellin Becker | R46: SESP - SESP/DG | S46: 45603 | T46: 04/03/2024 - Encaminhado a PCP/DA/DIV para análise e manifestação20/05/2024- Encaminhado para a unidade demandante para adequações 30/07/2024 - Com adequações restituido a SESP APC para adequações 18/10/2024 - Encaminhado ao SESP/NFS via SESP/APC para continuação da tramitação | U46: NÃO | V46: Sem Possibilidade de Empenho
A47: 21.635.875-9 | B47: SOLICITAÇÃO PARA AQUISIÇÃO DE ARMÁRIO ALTO EM MDF, VIA PREGÃO ELETRÔNICO 1415/2022/DECON - LOTES 09 E 10, NA MODALIDADE PARTICIPANTE, VALIDADE DA ATA 09/05/2024, ENTREGA ÚNICA, PARA SUPRIR A DEMANDA DA POLÍCIA CIENTÍFICA DO PARANÁ - UNIDADE TARUMÃ. VALIDADE DA ATA: 09/05/2024 | C47: Marcia | D47: Tarumã | E47: Seção de Química Forense | F47: 45317 | G47: R$ 11.594,00 | H47: 45337 | I47: 45351 | K47: 45372 | L47: INVESTIMENTO | M47: SRP Estadual | O47: FINALIZADO | P47: Carolina Schmeiske da Graça | Q47: Raquel de Oliveira Vilhena | R47: SESP/DG/NFS | S47: 45488 | T47: 29/02/2024- Encaminhado ao setor de origem para aguardar entrega dos materiais16/02/2024- Notas de empenho assinadas03/04/2024- Encaminhado ao SESP/DA/GAOFS para continuidade
A48: 21.810.072-4 | B48: SRP - Aquisição através do Registro de Preço do PE 27/2023, objetivando aquisição de material de Expediente - Grupo C para suprir a demanda da Polícia Científica do Paraná. VALIDADE DA ATA: 27/02/2025 | C48: Rodrigo Bianchini | D48: Grupo Auxiliar Administrativo | E48: Todas | F48: 45355 | G48: R$ 4.013,82 | H48: 45369 | I48: 45392 | K48: 45407 | L48: CUSTEIO | M48: SRP Estadual | O48: FINALIZADO | R48: SESP/DG/NFS | S48: 45498 | T48: 05/03/2024 - Encaminhado a PCP/DA/DIV para análise e manifestação25/04/2024- Materiais recebidos 07/05/2024- Encaminhado para liquidação e pagamento
A49: 21.726.417-0 | B49: Solicitação de compra de lacres tipo pino para uso nas embalagens reutilizáveis. DISPENSA ELETRÔNICA | C49: RAPHAEL | D49: Grupo Auxiliar Administrativo | E49: Todas | F49: 45337 | G49: R$ 39.000,00 | H49: 45506 | I49: 45509 | L49: CUSTEIO | M49: DISPENSA ELETRÔNICA | O49: TRAMITANDO | P49: Rodrigo Rocha Freire da Silva | Q49: Edgar Mallmann | R49: PCP/CWB/VISC/BALI | S49: 45565 | T49: 21/03/2024- Encaminhado a PCP/DA/DIV para análise e manifestação03/04/2024- Encaminhado ao NFS/OR para assinatura das informações orçamentárias e nota de reserva 12/07/2024 - Encaminhado para SESP/SC para continuação da tramitação 05/08/2024- Aguardando entrega
A50: 21.133.292-1 | B50: Solicitação de compra de caixas plásticas para as Centrais de Custódia de Vestígios. | C50: Eduarda | D50: Custodia | E50: Todas | F50: 45226 | G50: R$ 108.991,00 | H50: 45489 | I50: 45492 | K50: 45506 | L50: CUSTEIO | M50: LICITAÇÃO | O50: FINALIZADO | P50: Mariane Moreira Poletto | Q50: Wellerson Jeremias Colombari | R50: SESP/DG/NFS | S50: 45518 | T50: 01/11/2023 - Encaminhado ao Chefe da Divisão Administrativa para análise e aprovação 01/11/2023 - Encaminhado ao GAOFS para informação orçamentaria 07/11/2023 - Encaminhado ao SESP/DG para analise via apoio técnico 09/11/2023 - Encaminhado ao SESP/DEST para analise 13/11/2023 - Encaminhado ao SESP/SL para providencias 24/11/2023 - Encaminhado com adequações SESP/SL via SESP/APC. 05/12/2023 - SESP/DEST para continuidade 06/12/2023 - DEVOLVIDO A ORIGEM DEVIDO A ENVIO FORA DE PRAZO- PCP/DCV/DIV 08/01/2023 - Encaminhado a AT/SESP via SESP/APC para continuação da tramitação 23/02/2024 - Encaminhado a AT/SESP para continuação da tramitação 04/03/2024 - Encaminhado a SESP/APC para continuação da tramitação19/07/2024- Encaminhado ao Almoxarifado para acompanhamento da entrega02/08/2024- Material entregue
A51: 20.087.803-5 | B51: Aquisição de Ferramenta Forense de duplicação de HDs, SSDs e dispositivos USB, por Inexigibilidade de Licitação - Convênio Federal no 936068/2022 | C51: Eduarda | D51: CURITIBA | E51: CURITIBA | F51: 44994 | G51: R$ 113.826,00 | H51: 45561 | I51: 45572 | L51: INVESTIMENTO | M51: INEXIGIBILIDADE | O51: TRAMITANDO | P51: Henrique Galperin | Q51: Fabio Luiz Correia da Rocha | R51: PCP/CWB/VISC/COMP | S51: 45572 | T51: 24/03/2023- Encaminhado a DA/DIV para ações caso requer 30/08/2023 - Encaminhado para adequações 05/10/2023 - Encaminhado a SESP/COMPRAS via SESP/APC para continuação da tramitação 16/11/2023 - Análise da Tecnologia de Comunicação quanto ao objeto pretendido ser, ou não, caracterizado como TIC 05/12/2023 - Encontra-se SESP/AT/ASS 07/12/2023 - DEVOLVIDO A ORIGEM DEVIDO A ENVIO FORA DE PRAZO- PCP/CWB/VISC/COMP 14/03/2024 - Encaminhado ao Setor de Contratos da SESP para continuação da tramitação, bem como, a elaboração da minuta de contrato 03/04/2024 - Encaminhado a SESP/APC para continuação da tramitação20/09/2024- Encaminhado para inserção de nota de empenho
A52: 20.600.933-0 | B52: Abertura de Procedimento Licitatório visando aquisição de Luvas e mangotes para atendimento da demanda de todas as unidades da Polícia Científica. | C52: Raphael | D52: TODAS | E52: TODAS | F52: 45124 | G52: R$ 80.180,10 | H52: 45364 | I52: 45366 | K52: 23/05/2024 Apenas Mangotes | L52: CUSTEIO | M52: LICITAÇÃO | O52: FINALIZADO | P52: Raul Messias Lessa | Q52: Francisco da Silva Martins | R52: SESP/DG/NFS | S52: 45498 | T52: 28/08/2023 - o setor de Compras para atendimento à Aanalise constante às fls. 110 à 123 - 30/08/2023 - Encontra-se no compras para adequação 05/09/2023 - Adequado, enviado para SESP/APC sugerindo envio SESP/SL 20/09/2023 - Adequado, enviado para SESP/APC sugerindo envio SESP/SL. 16/11/2023 - Desde o dia 03/10 no setor de licitações , em fase de adjudicação 05/12/2023 - SESP/DG fase de Adjudicação e homologação 03/01/2024 - Encaminha-se ao chefe do gaofs para emissão de empenho 21/02/2024- Encaminhado ao Contratos/SESP15/03/2024- Encaminhado ao Almoxarifado para aguardo da entrega dos materiais23/05/2024- Mangotes recebidos
A53: 21.893.710-1 | B53: SRP - Aquisição através do Registro de Preço do PE 29/2023, objetivando aquisição de material de Expediente - Grupo E para suprir a demanda da Polícia Científica do Paraná. VALIDADE DA ATA: 14/03/2025 | C53: Rodrigo Bianchini | D53: Grupo Auxiliar Administrativo | E53: Todas | F53: 45370 | G53: R$ 6.054,35 | H53: 45399 | I53: 45415 | K53: 45422 | L53: CUSTEIO | M53: SRP Estadual | O53: FINALIZADO | R53: SESP/DG/NFS | S53: 45498 | T53: 20/03/2024 - Encaminhado a PCP/DIV para análise e manifestação08/04//2024- Notas de empenho assinadas06/05/2024- Aguardando entrega dos materiais 10/05/2024- Materiais recebidos
A54: 20.249.968-6 | B54: FUNSUSP - Aquisição, através de procedimento licitatório, de uma unidade de Sistema de Cromatografia Líquida Acoplado a Espectrômetro de Massas Sequencial (LC-MS/MS) | C54: Eduarda | D54: CURITIBA | E54: Tarumã | F54: 45033 | G54: R$ 1.991.866,39 | L54: INVESTIMENTO | M54: LICITAÇÃO | N54: FUNSUSP | O54: ARQUIVADO | P54: Isabella Ferreira Melo | Q54: Carolina Schmeiske da Graça | R54: PCP/CWB/TAR/QUIM | S54: 45516 | T54: 20/04/20223 - Encaminhado para DIV para análise e manifestação 26/06/2023- No GAA para adequações a nova Lei. 29/06/2023 Documentos atualizados, encaminhado à SESP/APC para continuidade. 03/07/2023 - encaminhado ao SESP/SL para providencias 09/08/2023 - Encaminhado a SESP/SL via SESP/APC para continuação da tramitação 16/11/2023: Análise de indisponibilidade de recursos do FUNSUSP para custear a despesa em tela 21/03/2024 - Encaminhado a origem para adequação do mesmo 03/05/2024 - Encaminhado a SESP/APC para continuação da tramitação 11/06/2024-Encaminhado à unidade demandante para adequações
A55: 21.906.273-7 | B55: Abertura de Procedimento Licitatório visando aquisição de macas e carros pantográficos para atendimento da demanda de todas as unidades da Polícia Científica. | C55: Raphael | D55: Todas | E55: Todas | F55: 45006 | G55: R$ 1.575.825,77 | H55: 45544 | I55: 45546 | K55: 45575 | L55: INVESTIMENTO | M55: LICITAÇÃO | O55: TRAMITAÇÃO INICIAL | P55: RAFAELA ROSSI MARQUES | Q55: VINICIUS GAMARRA | R55: PCP/DA/GAOFS | S55: 45588 | T55: 22/03/2024 - Encaminhado para DIV para análise e manifestação10/05/2024- Encaminhado à PCP/DA/GAA/COMPRAS para ciência e providências 27/05/2024 - Reenviado ao setor de licitações, via APC após adequações sugeridas pela PGE 13/06/2024 - Com nova atualização sugerida pelo setor de licitações restituido a SESP/SL04/09/2024- Encaminhado para inserção de nota de empenho
A56: 21.788.217-6 | B56: Solicita manutenção corretiva, com substituição do detector DTGS, em espectrofotômetro da marca Bruker, modelo Alpha II, utilizado na UETC de Londrina. | C56: Eduarda | D56: Londrina | E56: Londrina | F56: 45351 | G56: R$ 26.000,00 | H56: 45561 | I56: 45572 | L56: CUSTEIO | M56: INEXIGIBILIDADE | O56: TRAMITAÇÃO | P56: Mauricio Nakao Yorinori | Q56: Camila Castro Teixeira | R56: SESP - SESP/DG | S56: 45603 | T56: 25/03/2024 - Aguardando a empresa atualizar o cadastro no GMS 02/04/2024 - Encaminhado para DIV para análise e manifestação 06/05/2024 - Encaminhado a SESP/APC para análise da pertinência de realização de Contrato16/05/2024- Encaminhado ao NFS/OR para assinatura das informações orçamentárias 19/07/2024 - Encaminhado SESP/SC para continuação da tramitação 25/09/2024 - Encaminhado SESP/SC para continuação da tramitação | U56: SIM | V56: Indefinido
A57: 20.667.709-0 | B57: AQUISIÇÃO DA PLATAFORMA AUTOMATIZADA DEDICADA À EXTRAÇÃO AUTOMATIZADA DIFERENCIAL - HAMILTON AUTOLYS SAE ID COMPLETE COM INSUMOS | C57: Raphael | D57: UETC Tarumã | E57: Genética Forense | F57: 45117 | G57: R$ 2.926.971,76 | H57: 45264 | I57: 45469 | K57: 45747 | L57: INVESTIMENTO | M57: INEXIGIBILIDADE | O57: Finalizado em 31/3/25 | P57: Leonardo Arduino Marano | Q57: Anna Carolina de Moraes Braga | R57: PCP/CWB/TAR/GENET | S57: 45474 | T57: 09/08/2023 - Encaminhe-se à SESP/DEST para conhecimento edemais providências 16/11/2023 - Encontra-se no Centro de Acompanhamento de Projetos e Captação de Recursos para análise 05/12/2023 - Encontra-se PCP/DA - PCP/DA/GAOFS 25/03/2024 - Aguardando PCA 05/04/2024 - Encaminhado para SESP/COMPRAS para continuação da tramitação 19/04/2024 - Encaminhado para SESP/DEST/SC para continuação da tramitação, bem como, elaboração da minuta 06/05/2024 - Encaminhado a SESP/APC para continuação da tramitação 26/06/2024- Encaminhado para acompanhamento da entrega
A58: 21.837.256-2 | B58: Contratação direta por dispensa de processo licitatório para aquisição de papel de filtro qualitativo de e caixas de fibra de papelão para armazenamento de amostras, para atender a demanda das Seções de Química Forense e Toxicologia Forense da Polícia Científica do Paraná. DISPENSA ELETRÔNICA | C58: Eduarda | D58: UETC Tarumã | E58: Seção de Química Forense | F58: 45366 | G58: R$ 4.122,00 | H58: 45400 | I58: 45517 | L58: CUSTEIO | M58: DISPENSA ELETRÔNICA | O58: TRAMITANDO | P58: Dayse Fernanda de Souza | Q58: Amanda Cristina de Jesus Cunha | R58: PCP/CWB/TAR/TOXIC | S58: 45518 | T58: 01/04/2024 - Encaminhado para DIV para análise e manifestação05/04/2024- Nota de empenho inserida 17/05/2024 - Encaminhado ao SESP/COMPRAS para continuação da tramitação 05/06/2024- Encaminhado para abertura da disputa 02/07/2024 - Encaminhado para SESP/COMPRAS para continuação da tramitação 11/07/2024 - Encaminhado para PCP/DA/GAOFS para inclusão das notas reservas 09/08/2024 - Encaminhado para SESP/APC para continuação da tramitação 14/08/2024 - Encaminhado a origem para aguardar a entrega dos itens
A59: 21.872.103-6 | B59: Aquisição de reagentes químicos via pregão eletrônico 47/2023 Lotes 11, 42, 43, 58, 64, 74 65, 71, 15, 27, 34, 81, 83, validade da Ata: 04/07/2024, na modalidade PARTICIPANTE, para suprir a demanda dos Laboratórios da Polícia Científica do Paraná, Unidade Tarumã, no valor de R$ 9.113,80 (nove mil cento e oitenta e três reais e oitenta centavos), ENTREGA UNICA. VALIDADE DA ATA: 04/07/2024 | C59: Amanda | D59: Grupo Auxiliar Administrativo | E59: UETC Tarumã | F59: 45365 | G59: R$ 9.113,80 | H59: 45392 | I59: 45415 | K59: 45432 | L59: CUSTEIO | M59: SRP Estadual | O59: FINALIZADO | R59: SESP/DG/NFS | S59: 45498 | T59: 03/04/2024 - Encaminhado para DIV para análise e manifestação10/04/2024- Notas de empenho assinadas03/05/2024- Aguardando entrega dos materiais20/05/2024- Materiais entregues05/06/2024- Encaminhado para liquidação e pagamento
A60: 21.828.937-1 | B60: (PROTOCOLO NOVO)Abertura de procedimento licitatório, visando a contratação de empresa especializada na prestação de serviços continuados de rastreamento, monitoramento e telemetria de veículos via satélite por GPS/GSM/GPRS (sem locação de mão de obra), visando atender a demanda de todas as unidades da Polícia Científica do Paraná. Rastreador rastreadores | C60: Raphael | D60: Grupo Auxiliar Administrativo | E60: Todas | F60: 45357 | G60: R$ 220.164,84 | L60: CUSTEIO | M60: LICITAÇÃO | O60: TRAMITANDO | P60: Alessandro Burko Lopes | Q60: Philippe Alicio de Carvalho | R60: PCP/DA - PCP/DA/GAOFS | S60: 45603 | T60: 01/04/2024 - Encaminhado para DIV para análise e manifestação17/04/2024- Encaminhado à PCP/DA/GAOFS para emissão de informações orçamentárias 12/07/2024 - Encaminhado para SESP/APC para continuação da tramitação | U60: SIM | V60: Indefinido
A61: 21.951.986-9 | B61: Aquisição de Sulfato de Zinco Heptahidratado, via pregão eletrônico 47/2023 da SESA - lote 46, na modalidade adesão/carona, validade da ata 04/07/2024, para suprir a demanda do Laboratório de Toxicologia Forense da Polícia Científica do Paraná. VALIDADE DA ATA: 04/07/2024 | C61: Tycianne/ Amanda | D61: UETC Tarumã | E61: Todas | F61: 45385 | G61: R$ 200,00 | H61: 45426 | I61: 45429 | K61: 45450 | L61: CUSTEIO | M61: SRP Estadual | O61: FINALIZADO | R61: SESP/DG/NFS | S61: 45498 | T61: 09/04/2024- Carona autorizada pela SESA18/04/2024- Encaminhado ao GAOFS para informações orçamentárias e nota de reserva02/05/2024- Encaminhado à NFS/OR para assinatura das informações orçamentárias17/05/2024- Empenho e O.C encaminhados ao fornecedor; Aguadando entrega10/06/2024- Encaminhado para liquidação e pagamento
A62: 21.980.038-0 | B62: SRP Mobiliários - Aquisição através do Registro de Preço do PE 1727/2022, na modalidade CARONA, de mobiliários para atender as necessidades das unidades da Polícia Científica do ParanáVALIDADE DA ATA: 28/08/2024 | C62: Eduarda | D62: Grupo Auxiliar Administrativo | E62: Todas | F62: 45387 | G62: R$ 491.107,87 | H62: 45489 | I62: 45503 | L62: INVESTIMENTO | M62: SRP Estadual | N62: Ponta Grossa | O62: FINALIZADO | P62: Edson da Silva Napoleão | Q62: Kelly Cristina Cancela | R62: PCP/DA/GAA/PATR | S62: 45506 | T62: 05/04/2024 - Encaminhado para DIV para análise e manifestação 22/04/2024 - Encaminhado para DIV para análise e manifestação09/05/2024- Encaminhado à SESP/NFS para inclusão do IDO, DAD e QDD 15/05/2024 - Encaminhado a SESP/APC para continuação da tramitação 11/06/2024 - Encaminhado para SESP/DEST/SC para continuação da tramitação 24/06/2024 - Encaminhado para AT/SESP via SESP/APC para continuação da tramitação 30/07/2024- Aguardando entrega
A63: 21.760.337-4 | B63: cópia do protocolo nr. 21.722.777-1 - dispensa de processo licitatório por inexigibilidade para aquisição de insumos para a plataforma de sequenciamento massivo paralelo (de nova geração) ion genestudio s5 e ion chef hid para atender a demanda da seção - termo de cooperação técnica sejuf x sesp - projeto fim da dúvida - protocolo inicial 16.881.163-2 | C63: Eduarda | D63: PCP/DIR/DIRADM | E63: Genética Forense | F63: 45386 | G63: R$ 1.954.863,96 | H63: 45540 | I63: 45541 | K63: 45566 | L63: CUSTEIO | M63: INEXIGIBILIDADE | O63: FINALIZADO | P63: Luciellen D'avilla Giacomel Kobachuck | Q63: Pedro Henrqiue Canezin | R63: PCP/CWB/TAR/GENET | S63: 45544 | T63: 09/04/2024 Encaminhado para SESP/COMPRAS para continuação da tramitação 17/04/2024 - Encaminhado para SESP/APC para continuação da tramitação16/08/2024- Encaminhado para inserção de nota de empenho
A64: 21.975.012-9 | B64: Aquisição, através de dispensa de licitação, de açúcar refinado 1kG. DISPENSA ELETRÔNICA | C64: Raphael | D64: Grupo Auxiliar Administrativo | E64: Todas | F64: 45386 | G64: R$ 13.851,00 | H64: SIM | I64: SIM | K64: 45962 | L64: CUSTEIO | M64: DISPENSA ELETRÔNICA | O64: FINALIZADO | P64: LUCIANA DE ANDRADE LIMA PENCAL | Q64: MAURICIO CATITAS DE SOUSA | R64: PCP/DA/GAOFS | S64: 45588 | T64: 09/04/2024 - Encaminhado para DIV para análise e manifestação
A65: 22.000.622-0 | B65: Dispensa Eletrônica - Aquisição, através de dispensa eletrônica de insumos para impressora de Crachá, em atendimento as necessidades da demanda da Polícia Científica do Paraná. DISPENSA ELETRÔNICA | C65: Eduarda | D65: Grupo Auxiliar Administrativo | E65: Seção de Recursos Humanos | F65: 45392 | G65: R$ 12.724,37 | H65: 45575 | I65: 45579 | L65: CUSTEIO | M65: DISPENSA ELETRÔNICA | O65: TRAMITANDO | P65: Mariane Moreira Poletto | Q65: Manoel Luiz Vieira | R65: PCP/DA/GARH | S65: 45579 | T65: 16/04/2024- Encaminhado ao GAOFS para emissão da CALV, informações orçamentárias e nota de reserva 14/05/2024 - Encaminhado ao SESP/NFS via SESP/APC 14/06/2024 - Encaminhado a PCP/GAOFS para inclusão da Nota reserva 08/08/2024 - Encaminha ao SESP/COMPRAS para continuação da tramitação
A66: 21.642.557-0 | B66: Solicitação de compra de Geladeiras Automotivas Portáteis por licitação. | C66: Beatriz Rossi Canuto de Menezes Rodrigues | D66: Todas | E66: Todas | F66: 45397 | G66: R$ 113.955,01 | L66: INVESTIMENTO | M66: LICITAÇÃO | O66: TRAMITANDO | P66: Leonete Ghellere | Q66: Edson Jovimiano de Lima | R66: SESP/SL | S66: 45565 | T66: 19/04/2024- Encaminhado ao setor de compras para instrução 09/07/2024 - Encaminhado ao Centro de Licitações via SESP/APC 04/09/2024 - Com adequações, encaminhado ao GOFS para atualizações financeiras , sugerindo encaminhamento ao setor de licitações/SESP | U66: TALVEZ - EM PROCESSO LICITATORIO | V66: Indefinido
A67: 21.980.848-8 | B67: Solicita aquisição de SSDs NVMe e memórias RAM através do convênio federal 904902-2020 | C67: Eduarda | D67: Visconde de Guarapuava | E67: Seção de Computação Forense | F67: 45399 | G67: R$ 140.559,80 | L67: INVESTIMENTO | M67: LICITAÇÃO | O67: TRAMITANDO | P67: Cristiano de Mello Murbach | Q67: Fabio Ogassawara | R67: SESP/SL | S67: 45583 | T67: 22/04/2024 - Encaminhado para PCP/DA/DIV para análise e manifestação 21/06/2024- Encaminhado para a origem para adequações 11/07/2024 - Encaminhado para SESP/NSF via SESP/APC para atualização das informações orçamentárias 17/09/2024 - Restituído PCP/CWB/VISC/COMP para adequações | U67: TALVEZ - Certame | PE 90981-24 | Abertura (em 25/11/2024) | V67: Indefinido
A68: 22.035.907-7 | B68: Licitação - Aquisição através de procedimento licitatório, de maletas de exames periciais em local de crime do tipo 2, em atendimento a Seção de Localística da Polícia Científica do Paraná, conforme convênio Federal No 936068/2022 | C68: Eduarda | D68: Grupo Auxiliar Administrativo | E68: Campo Mourão, Curitiba, Londrina, Maringá, Umuarama | F68: 45404 | G68: R$ 126.300,00 | L68: INVESTIMENTO | M68: LICITAÇÃO | O68: TRAMITANDO | P68: Alexandre Guilherme de Lara | Q68: Roman Hector Abril | R68: SESP/SL | S68: 45574 | T68: 23/04/2024 - Encaminhado para PCP/DA/DIV para análise e manifestação 13/05/2024 - Encaminhado via SESP/APC para continuação da tramitação 12/07/2024 - Encaminhado para Centro de Licitações via SESP/APC para continuação da tramitação 23/09/2024 - Encaminhado para Centro de Licitações via SESP/APC para continuação da tramitação | U68: TALVEZ - CERTAME | PE90924-24 | PUBLICADO (ABERTURA 07/11) | MALETAS LOCAL CRIME CONV.FED no 936068/2022. | V68: Indefinido
A69: 22.072.433-6 | B69: Descumprimento da Empresa LEVEL FARMACÊUTICA LTDA do Contrato n0027/2024, GMS n0562/2024, referente a entrega de Luvas e Mangote Plástico em atendimento as necessidades da Polícia Científica do Paraná | C69: Eduarda | D69: Grupo Auxiliar Administrativo | E69: Grupo Auxiliar Administrativo | F69: 45407 | G69: R$ 0,00 | L69: N/A | M69: N/A | O69: TRAMITANDO | R69: CGE/CCOR | S69: 45588 | T69: 25/04/2024 - Encaminhado a DIV para gestões do processo | U69: Não se aplica | V69: Indefinido
A70: 22.086.646-7 | B70: SRP - Aquisição através do Registro de Preço do PE 467/2023, objetivando aquisição de Copo Descartável para suprir a demanda da Polícia Científica do Paraná. VALIDADE DA ATA: 08/04/2025 | C70: Rodrigo Bianchini | D70: Grupo Auxiliar Administrativo | E70: Todas | F70: 45408 | G70: R$ 9.901,23 | H70: 45432 | I70: 45446 | K70: 45448 | L70: CUSTEIO | M70: SRP Estadual | O70: FINALIZADO | R70: SESP/DG/NFS | S70: 45498 | T70: 29/04/2024 - Encaminhado a PCP/DIV para análise e manifestação20/05/2024- Notas de Empenho assinadas 05/05/2024- Materiais entregues10/06/2024- Encaminhado para liquidação e pagamento
A71: 22.093.650-3 | B71: SRP - Aquisição através do Registro de Preço do PE 1086/2022, objetivando aquisição de Máscara e Avental para suprir a demanda da Polícia Científica do Paraná. VALIDADE DA ATA: 10/05/2024 | C71: Rodrigo Bianchini | D71: Grupo Auxiliar Administrativo | E71: Todas | F71: 45411 | G71: R$ 10.608,75 | H71: 45422 | L71: CUSTEIO | M71: SRP Estadual | O71: ARQUIVADO | R71: PCP/DA/GAA/COMPRAS | S71: 45432 | T71: 30/04/2024 - Encaminhado a PCP/DIV para análise e manifestação 02/05/2024- Encaminhado ao GAOFS para providencias10/05/2024- Notas de Empenho assinadas***Protocolo arquivado devido as empresas não aceitarem ter recebido posteriormente
A72: 22.144.943-6 | B72: SRP - Aquisição através do Registro de Preço do PE 1355/2022, objetivando aquisição de Licença de Software AutoCAD e Adobe Creative Cloud (CC) para suprir a demanda da Polícia Científica do Paraná. VALIDADE DA ATA: 05/07/2024 | C72: Rodrigo Bianchini/ Amanda | D72: Grupo Auxiliar Administrativo | E72: Curitiba | F72: 45421 | G72: R$ 157.948,09 | H72: 45502 | I72: 45505 | K72: 45482 | L72: INVESTIMENTO | M72: SRP Estadual | O72: FINALIZADO | R72: PCP/DA/GAA/COMPRAS | S72: 45567 | T72: 10/05/2024 - Encaminhado a PCP/DIV para análise e manifestação21/06/2024- Encaminhado à SESP/DEST/SC para providências 09/07/2024- Encaminhado ao GAOFS para inserção de nota de empenho09/07/2024- Material entregue
A73: 22.101.782-0 | B73: EMERGENCIAL LUVAS - Compra emergencial para aquisição de Luvas de Látex e Luvas Nitrílicas. | C73: Raphael | D73: Grupo Auxiliar Administrativo | E73: Todas | F73: 45412 | G73: R$ 44.828,00 | L73: CUSTEIO | M73: DISPENSA DE LICITAÇÃO | O73: ARQUIVADO | P73: Vinicius Gamarra Contieri | Q73: Maurício Catitas de Sousa, | R73: PCP/DA/GAA/COMPRAS | S73: 45511 | T73: 10/05/2024 - Encaminhado a PCP/DIV para análise e encaminhamento à casa civil para autorização de processo emergencial20/06/2024- Encaminhado à SESP/APC para continuidade na tramitação
A74: 22.098.366-8 | B74: Solicita a instauração de processo de licitação para aquisição de duas unidades de Sistema de Cromatografia Líquida Acoplado a Espectrômetro de Massas Sequencial (LC-MS/MS) tipo Triplo Quadrupolo, visando atender as necessidades da Seção de Toxicologia Forense da Polícia Científica do Paraná. | C74: Jefté Teixeira da Silva | D74: CURITIBA | E74: Seção de Toxicologia Forense | F74: 45411 | G74: R$ 5.298.170,16 | L74: INVESTIMENTO | M74: LICITAÇÃO | O74: ARQUIVADO | P74: Carolina Schmeiske da Graça | Q74: Alessandra Rodrigues de Araújo | R74: PCP/CWB/TAR/QUIM | S74: 45516 | T74: 20/05/2024- Encaminhado à SESP/DEST para ciência e providências 11/07/2024 - tRAMITA O PROTOCOLO 22.385.321-8 que instrui a compra de 3 equipamentos semelhantes ao deste processo
A75: 22.200.885-9 | B75: Abertura de dispensa de licitação, visando a aquisição de Papel Sulfite A4, a fim de atender a demanda do Órgão da Polícia Científica do Paraná. | C75: Raphael | D75: Grupo Auxiliar Administrativo | E75: Todas | F75: 45403 | G75: R$ 40.320,00 | L75: CUSTEIO | M75: DISPENSA ELETRÔNICA | O75: ARQUIVADO | P75: Rodrigo Taborda Ribas | Q75: Maurício Catitas de Sousa, | R75: PCP/DA/GAA/COMPRAS | S75: 45504 | T75: 23/05/2024 - Encaminhado a PCP/DIV para análise e manifestação
A76: 22.221.397-5 | B76: Aquisição, através de dispensa de licitação, de Algodão, Esparadrapo e Fio para Costura de Couro, nas quantidades e exigências estabelecidas neste instrumento, visando atender a Polícia Científica do Paraná. | C76: Raphael | D76: Grupo Auxiliar Administrativo | E76: Todas | F76: 45436 | G76: R$ 5.204,53 | H76: 45533 | I76: 45539 | K76: 45553 | L76: CUSTEIO | M76: DISPENSA ELETRÔNICA | O76: FINALIZADO | P76: Rafaela Rossi Marques | Q76: Vinicius Gamarra Contieri | R76: SESP/DG/NFS | S76: 45555 | T76: 10/06/2024- Encaminhado ao GAOFS para informação orçamentária 05/07/2024 Encaminhado a SESP/COMPRAS para a continuação da tramitação 07/08/2024 - Com o processo de dispensa eletrônica finalizado, enviado ao setor SESP/COMP para adjudicação/homologação.18/09/2024- Material entregue
A77: 22.124.897-0 | B77: Instrução de compra referente às mesas de necropsia da nova unidade da Polícia Científica de Ponta Grossa | C77: Raphael | D77: Grupo Auxiliar Administrativo | E77: UETC Ponta Grossa | F77: 45418 | G77: R$ 697.746,00 | L77: INVESTIMENTO | M77: LICITAÇÃO | N77: Ponta Grossa | O77: TRAMITAÇÃO INICIAL | P77: Edson da Silva Napoleão | Q77: Izabelle Engels | R77: SESP/SL | S77: 45532 | T77: 27/05/2024 - Encaminhado a PCP/DIV para análise e manifestação 07/08/2024 - Após adequações exigidas pela PGE , encaminhado a SESP/NFS/OR via SESP/APC 21/08/2024 - Com adequações encaminhado ao setor de licitações via SESP/APC | U77: talvez - Certame | PE90681-24 | ANÁLISE PROPOSTA (06/10/24) | Mesas de necropsia - PCP | V77: Indefinido
A78: 22.232.865-9 | B78: Aquisição, através de dispensa de licitação, de Swab de Algodão e Haste Plástica, nas quantidades e exigências estabelecidas neste instrumento, visando atender a Polícia Científica do Paraná. | C78: Rodrigo Bianchini / Raphael | D78: Grupo Auxiliar Administrativo | E78: Todas | F78: 45440 | G78: R$ 8.260,40 | L78: CUSTEIO | M78: DISPENSA ELETRÔNICA | O78: TRAMITAÇÃO INICIAL | P78: Vinicius Gamarra Contieri | Q78: Camilla Borges Gazolla | R78: PCP/DA - PCP/DA/GAA/CONTRATOS | S78: 45596 | T78: 10/06/2024- Encaminhado ao GAOFS para informação orçamentária 09/10/2024- Finalizada a etapa de disputa eletrônica encaminhado ao setor de compras para adjudicação e Homologação | U78: SIM | V78: Indefinido
A79: 22.241.998-0 | B79: SRP - Contratação através do Registro de Preço do PE 428/2023, de aquisição de Luvas Nitrílicas e Latex para atender as unidades da Polícia Científica do Paraná. VALIDADE DA ATA: 20/03/2025 | C79: Rodrigo Bianchini | D79: Grupo Auxiliar Administrativo | E79: Todas | F79: 45441 | G79: R$ 74.694,00 | H79: 45467 | I79: 45469 | K79: 45491 | L79: CUSTEIO | M79: SRP Estadual | O79: FINALIZADO | P79: Vinicius Gamarra Contieri | Q79: Mauricio Catitas de Souza | R79: SESP/DG/NFS | S79: 45587 | T79: 03/06/2024 - Encaminhado a PCP/DIV para análise e manifestação26/06/2024- Encaminhado ao almoxarifado para acompanhamento da entrega18/07/2024- Material entregue
A80: 22.242.905-6 | B80: SRP - Contratação através do Registro de Preço do PE 116/2024, de Prestação de Serviços de Locação de Equipamento de Reprografia para atender as unidades da Polícia Científica do Paraná. VALIDADE DA ATA: 19/05/2025 | C80: Rodrigo Bianchini | D80: Grupo Auxiliar Administrativo | E80: Todas | F80: 45441 | G80: R$ 5.826,68 | H80: 45509 | I80: 45516 | L80: CUSTEIO | M80: SRP Estadual | O80: ARQUIVADO | R80: PCP/DA/GAA/CONTRATOS | S80: 45516
A81: 21.828.132-0 | B81: SOLICITAÇÃO PARA ABERTURA DE PROCESSO LICITATÓRIO PARA CONTRATAÇÃO DE EMPRESA ESPECIALIZADA NO FORNECIMENTO, CONFIGURAÇÃO E IMPLANTAÇÃO DE SISTEMA INFORMATIZADO DE AUTOMAÇÃO E GESTÃO DE LABORATÓRIOS (LIMS), ATRAVÉS DO CONVÊNIO No 919141/2021 - PLATAFORMA + BRASIL POR 12 MESES, PARA ATENDER A SEÇÃO DE GENÉTICA MOLECULAR FORENSE. | C81: Marcia | D81: CURITIBA | E81: SEÇÃO DE GENÉTICA MOLECULAR FORENSE | F81: 45357 | G81: R$ 642.413,00 | K81: 45757 | L81: CUSTEIO | M81: LICITAÇÃO | O81: TRAMITANDO | P81: Pedro Henrique Canezin | Q81: Marianna Maia Taulois do Rosário | R81: PGE - PGE/PRC | S81: 45596 | U81: Provavelmente não | V81: Indefinido
A82: 20.054.891-4 | B82: Aquisição através de licitação de 02 Sistemas de Purificação de Água Ultrapura | C82: Eduarda | D82: CURITIBA | E82: TARUMÃ - LABORATÓRIOS FORENSES | F82: 44974 | G82: R$ 359.233,96 | H82: 45435 | I82: 45440 | L82: INVESTIMENTO | M82: LICITAÇÃO | O82: TRAMITANDO - Licitação em 24/11/2023 | P82: Carolina Schmeiske da Graça | Q82: Isabella Ferreira Melo | R82: PCP/CWB/TAR/TOX | S82: 45448 | T82: 17/02/2023 - Instrução processual Setor de Compras 03/05/2023 - Encaminhado ao SESP/APC para continuação da tramitação 22/05/2023 - Encaminhado ao SESP/APC para continuação da tramitação 02/08/2023 - Encaminhado ao SESP/APC para continuação da tramitação 30/08/2023 - PCP/GAA/COMPRAS para adequações. 21/09/2023 - Encaminhado ao SESP/APC para continuação da tramitação 11/10/2023 - Devolvido ao setor jurídico via APC 05/12/2023 - No setor de licitações em fase de documentação 07/03/2024- Nota de reserva assinada 11/04/2024- Encaminhado a PCP/DA/GAA/CONTRATOS para apreciação23/05/2024- Empenho assinado e aprovado
A83: 22.075.189-9 | B83: Licitação - Abertura de procedimento Licitatório, visando a aquisição de Cofres para atender a demanda de todas as unidades da Polícia Científica do Paraná. | C83: Eduarda | D83: CURITIBA | E83: TODAS | F83: 45448 | G83: R$ 75.039,40 | L83: INVESTIMENTO | M83: LICITAÇÃO | O83: TRAMITAÇÃO INICIAL | P83: Edilson Massao Miaqui | Q83: Simone Silva de Queiroz | R83: SESP/SC | S83: 45691 | T83: 21/06/2024 - Encaminhado para PCP/DA/DIV para análise e manifestação 16/07/2024- Encaminhado à origem para adequações 29/07/2024 - Encaminhado a SESP/SL via SESP/APC para continuação da tramitação 24/09/2024 - Encaminhado à origem para adequações 16/10/2024 - Encaminhado a SESP/SL via SESP/APC para continuação da tramitação 03/02/2025 - Encaminhado para SESP/SC com o contrato assinado pela parte da empresa, encaminhado para demais providências | U83: talvez - Certame | PE91024-24 | Publicado (Abertura 27/11/2024)| Cofres - PCP | (P.7) Aquisição de Cofres para atender a demanda de todas as unidades da Polícia Científica do Paraná. | V83: Indefinido
A84: 21.813.909-4 | B84: Dispensa de Licitação de Contratação de Prestação de Serviço de Dosimetria para atendimento das necessidades da unidade do Tarumã | C84: Eduarda | D84: CURITIBA | E84: TARUMÃ | F84: 45418 | G84: R$ 6.296,40 | L84: CUSTEIO | M84: DISPENSA ELETRÔNICA | O84: TRAMITAÇÃO INICIAL | P84: Vinicius Gamarra Contieri | Q84: Camilla Borges Gazolla | R84: PCP/DA/GAA/COMPRAS | S84: 45546 | T84: 11/06/2024 - Encaminhado para DIV para análise e manifestação 27/06/2024 - Encaminhado para SESP/COMPRAS para continuação da tramitação 29/07/2024 - Encaminhado para DIV para ciência e gestões 16/08/2024 - Encaminhado para SESP/APC para continuação da tramitação 06/09/2024 - Encaminhado para o Divisional sugerindo encaminhamento a SESP/APC para gestões | U84: talvez - Em instrução dispensa não eletronica | V84: Indefinido
A85: 21.912.291-8 | B85: Solicitação de aquisição de lacres plásticos para identificação de cadáveres. DISPENSA ELETRÔNICA | C85: Eduarda | D85: CURITIBA | E85: TODAS | F85: 45449 | G85: R$ 13.440,00 | L85: CUSTEIO | M85: DISPENSA ELETRÔNICA | O85: ARQUIVADO | P85: Roman Hector Abril | Q85: Camilla Borges Gazolla | R85: PCP/DCV/DIV | S85: 45506 | T85: 20/06/2024 - Encaminhado para PCP/DA/DIV para análise e manifestação 15/07/2024 - Encaminhamos ao SESP/NFS via SESP/APC para continuação da tramitação
A86: 22.216.342-0 | B86: Agua Mineral Telemaco Borba | C86: Eduarda | D86: TELÊMACO BORBA | E86: UETC TELÊMACO BORBA | F86: 45435 | G86: R$ 2.772,00 | H86: sim | I86: 45878 | K86: sim | L86: CUSTEIO | M86: SRP Estadual | O86: FINALIZADO | P86: Não se aplica | Q86: Não se aplica | R86: PCP/TB/CHEFIA | S86: 45516 | T86: 11/07/2024 - Encaminhado para PCP/DA/DIV para análise e manifestação 31/07/2024 - Encaminhado para PCP/DA/GAOFS para emissão do empenho 02/08/2024 - Encaminhado para SESP/APC para continuação da tramitação
A87: 21.847.127-7 | B87: Solicitação de aquisição de etiquetas e ribbons para os laboratórios de Curitiba. | C87: Raphael | D87: CURITIBA | E87: TARUMÃ | F87: 45362 | G87: R$ 16.106,27 | H87: 45573 | I87: 45575 | L87: CUSTEIO | M87: DISPENSA ELETRÔNICA | O87: TRAMITANDO | P87: Carolina Schmeiske da Graça | Q87: Raquel de Oliveira Vilhena | R87: PCP/CWB/TAR/TOX | S87: 45581
A88: 22.257.594-0 | B88: SOLICITAÇÃO PARA AQUISIÇÃO DE GASES ESPECIAIS (AR SINTÉTICO E GÁS HÉLIO), VIA PREGÃO ELETRÔNICO 15/2023/UNILA - LOTES 01 E 04, RESPECTIVAMENTE - NA MODALIDADE ADESÃO/CARONA, VALIDADE DA ATA 07/11/2024, ENTREGA ÚNICA, PARA SUPRIR A DEMANDA DOS LABORATÓRIOS FORENSES DA POLÍCIA CIENTÍFICA DO PARANÁ - UNIDADE TARUMÃ - CURITIBA. | C88: Amanda | D88: CURITIBA | E88: TARUMÃ | F88: 45447 | G88: R$ 20.595,00 | H88: 45492 | I88: 45496 | L88: CUSTEIO | M88: SRP Estadual | O88: TRAMITANDO | P88: Carolina Schmeiske da Graça | Q88: Raquel de Oliveira Vilhena | R88: PCP/CWB/TAR/TOX | S88: 45554 | T88: 23/07/2024- Aguardando entrega
A89: 22.140.865-9 | B89: Aquisição através de dispensa de licitação do serviço de CALIBRAÇÃO DOS EQUIPAMENTOS DO LIM. | C89: Eduarda | D89: CURITIBA | E89: ACADEMIA FORENSE | F89: 45432 | G89: R$ 7.072,04 | L89: SOBRESTADO | M89: DISPENSA ELETRÔNICA | O89: TRAMITAÇÃO | P89: Emilio Merino de Paz Junior | Q89: Alexandre Guilherme de Lara | R89: PCP/ACF/DIR | S89: 45456 | T89: 13/06/2024 - Devolvido a pedido da unidade. Sobrestado la | U89: não | V89: Sem Possibilidade de Empenho
A90: 22.295.731-1 | B90: Licitação - Abertura de procedimento Licitatório, visando a aquisição de um Microscópio Eletrônico de Varredura para o Laboratório de Inovação e Metrologia (LIM). | C90: Eduarda | D90: CURITIBA | E90: ACADEMIA FORENSE | F90: 45454 | G90: R$ 2.255.586,19 | H90: 45975 | I90: 45978 | J90: 46157 | L90: INVESTIMENTO | M90: LICITAÇÃO | O90: TRAMITAÇÃO | P90: Emilio Merino de Paz Junior | Q90: Alexandre Guilherme de Lara | R90: SESP - SESP/SL | S90: 45602 | T90: 20/06/2024 - Encaminhado PCP/DA/DIV para analise e manifestação | U90: Talvez - No setor de licitação | V90: Indefinido
A91: 22.291.999-1 | B91: INSTRUÇÃO DE COMPRA REFERENTE ÀS CADEIRAS GINECOLÓGICAS ELETRICAS - NOVA UETC PONTA GROSSA | C91: Eduarda | D91: PONTA GROSSA | E91: UETC PONTA GROSSA | F91: 45454 | G91: R$ 42.054,58 | L91: INVESTIMENTO | M91: DISPENSA ELETRÔNICA | O91: TRAMITAÇÃO | P91: Edson da Silva Napoleão | Q91: Izabelle Engels | R91: PCP/DA/GAA/CONTRATOS | S91: 45601 | T91: 02/07/2024 - Encaminhado PCP/DA/DIV para analise e manifestação 03/09/2024 - Encaminhado para SESP/COMPRAS para continuação da tramitação 10/10/2024 - Encaminhado para SESP/COMPRAS para continuação da tramitação 17/10/2024 - Encaminhado para SESP/CONTRATOS para continuação da tramitação | U91: sim | V91: Indefinido
A92: 21.728.751-0 | B92: AQUISIÇÃO, ATRAVÉS DE INEXIGIBILIDADE DE LICITAÇÃO, DE ESPECTRÔMETRO DE FLUORESCÊNCIA DE RAIOS X (XRF) PORTÁTIL S1 TITAN (BRUKER), A FIM DE ATENDER A DEMANDA DA SEÇÃO DE CRIMES AMBIENTAIS DA POLÍCIA CIENTÍFICA DO PARANÁ | C92: Angela Andreassa | D92: CURITIBA | E92: Seção de Crimes Ambientais | F92: 45475 | G92: R$ 465.430,04 | H92: 45586 | L92: INVESTIMENTO | M92: INEXIGIBILIDADE | O92: TRAMITAÇÃO | P92: Angela Andreassa | Q92: Denise Maria Gineste | R92: SESP/NFS/LIQSEM | S92: 45587 | T92: 19/07/2024 - Encaminhado PCP/DIR/DIRADM para analise e manifestação 06/09/2024 - Encaminhado a origem para adequações 11/09/2024 - Encaminhado para o SESP/CONTRATOS via SESP/APC para continuação da tramitação 12/09/2024 - Após a certificação solicitada, encaminhe-se ao SESP/CONTRATOS para continuação da tramitação.
A93: 22.168.566-0 | B93: Licitação - Abertura de procedimento Licitatório, visando a aquisição de CÂMARAS MORTUÁRIAS para a nova unidade da Polícia Científica de Ponta Grossa. | C93: Kelly Cristina Cancela | D93: PONTA GROSSA | E93: UETC PONTA GROSSA | F93: 45441 | G93: R$ 1.436.816,34 | L93: INVESTIMENTO | M93: LICITAÇÃO | O93: TRAMITAÇÃO | P93: Edson da Silva Napoleão | Q93: Izabelle Engels | R93: PGE - PGE/PRC | S93: 45597 | T93: 30/09/2024 - Com adequações encaminhado ao financeiro para informações, sugerindo encaminhamento ao setor de compras SESP | U93: dificilmente - em analise na PGE da minuta do edital | V93: Indefinido
A94: 22.447.757-0 | B94: Licitação, Abertura de procedimento Licitatório, visando a aquisição de STUBS, FITAS DE CARBONO E EMBALAGENS para coleta de resíduos de disparo de arma de fogo, a fim de atender a demanda da Polícia Científica do Paraná. | C94: Rodrigo Bianchini | D94: Grupo Auxiliar Administrativo | E94: TODAS | F94: 45484 | G94: R$ 66.201,50 | L94: CUSTEIO | M94: LICITAÇÃO | O94: TRAMITAÇÃO | P94: Beatriz Rossi Canuto de Menezes Rodrigues | Q94: Alexandre Guilherme de Lara | R94: SESP/SL | S94: 45566 | T94: 16/07/2024 - Encaminhado para análise e manifestação | U94: talvez - Certame | PE91285/2024 | Publicado (06/11/2024) | V94: Indefinido
A95: 22.385.321-8 | B95: Licitação para a aquisição de 03 Sistemas de cromatografia líquida acoplados a espectrometria de massas em tandem. LC-MS/MS | C95: Carolina Schmeiske da Graça | D95: CURITIBA | E95: TARUMÃ | F95: 45484 | G95: R$ 8.432.255,91 | L95: INVESTIMENTO | M95: LICITAÇÃO | O95: TRAMITAÇÃO | P95: Raquel de Oliveira Vilhena | Q95: Jefté Teixeira da Silva | R95: SESP/SL | S95: 45568 | T95: 16/07/2024 - Encaminhado para análise e manifestação 17/09/2024 - Devolvido a origem para adequações sugeridas pela PGE | U95: provavelmente - Certame | PE91153-24 | HABILITAÇÃO (ATÉ 12/11/2024) | CROMATÓGRAFO LC MS/MS - PCP | V95: Indefinido
A96: 22.414.628-0 | B96: FUNSUSP - Aquisição de Equipamentos de processamento e de armazenamento de vestígios digitais via ATA de Registro de Preços 999/2023 (validade 23/06/2025) | C96: Amanda | D96: Grupo Auxiliar Administrativo | E96: Seção de Computação Forense | F96: 45477 | G96: R$ 1.193.620,00 | H96: 45554 | I96: 45560 | K96: 45576 | L96: INVESTIMENTO | M96: SRP Estadual | O96: TRAMITAÇÃO | P96: Henrique Galperin | Q96: Cristiano de Mello Murbach | R96: PCP/DA/GAA/PATR | S96: 45583 | T96: 19/09/2024- Empenho assinado25/09/2024- Encaminhado para acompanhamento da entrega
A97: 22.214.059-5 | B97: Licitação para aquisição de uniformes operacionais para a Operação Verão 2024/2025 a fim de atender a demanda da Polícia Científica do Paraná. | C97: Rodrigo Bianchini | D97: Grupo Auxiliar Administrativo | E97: Paranaguá e Matinhos | F97: 45435 | G97: R$ 105.584,40 | L97: CUSTEIO | M97: LICITAÇÃO | O97: TRAMITAÇÃO | P97: Alessandro Burko Lopes | Q97: Philippe Alicio de Carvalho | R97: SESP/SL | S97: 45581 | T97: 21/08/2024 - Com adequações enviado ao financeiro para ações que o caso requer. | U97: Provavelmente - Certame| PE 91181 | Publicado 06.11 | UNIFORMES OP. VERÃO - PCP | 9h30 | V97: Indefinido
A98: 22.474.402-1 | B98: Aquisição de um Scanner Tridimensional de Ambiente por meio de adesão à Ata de Registro de Preços PE n 92/2023 da Polícia Científica de Santa Catarina, para suprir a demanda da Polícia Científica do Paraná. | C98: Amanda | D98: Grupo Auxiliar Administrativo | E98: Campo Mourão | F98: 45490 | G98: R$309.000,00 | H98: 45681 | I98: 45686 | L98: INVESTIMENTO | M98: SRP Estadual | O98: TRAMITAÇÃO | P98: Carlos Alberto Bambini Junior | Q98: Leonardo Rodrigues da Silva | R98: PCP/CM/CHEFIA | S98: 45688 | T98: 17/07/2024- Encaminhado à Direção Administrativa para solicitação da carona à Polícia Científica de SC. 07/11/2024 - Encaminhado para SESP/COMPRAS para continuação da tramitação 13/12/2024 - Encaminhado para AT/SESP via SESP/APC para continuação da tramitação 31/01/2025 - Contrato e Empenho enviado ao Fornecedor para entrega do bem, protocolo enviado ao Gestor do contrato para aguardar equipamento. | U98: Provavelmente - processo instruído | V98: Indefinido
A99: 19.723.342-7 | B99: Aquisição de Estação Forense de alto desempenho para processamento de vestígios digitais, com Adesão a Ata de Registro de Preços - Convênio FIA/SEJUF - Projeto "Combate à Pandemia de Cyberpornografia - Fim da Impunidade!" | C99: Amanda | D99: Grupo Auxiliar Administrativo | E99: Seção de Computação Forense | F99: 44881 | G99: R$2.008.860,00 | L99: INVESTIMENTO | M99: SRP Estadual | O99: TRAMITAÇÃO | P99: Henrique Galperin | Q99: Cristiano de Mello Murbach | R99: PCP/DA - PCP/DA/GAA/CONTRATOS | S99: 45603 | T99: 29/07/2024 - Com informação ref. a vantajosidade, restituido SESP/DEST/SC | U99: ??? | V99: Indefinido
A100: 22.454.265-8 | B100: Aquisição de Estações Forenses de alto desempenho para processamento de vestígios digitais via Adesão à ATA de Registro de Preços - TED 001/2024 (LOTTOPAR) | C100: Amanda | D100: Grupo Auxiliar Administrativo | E100: Seção de Computação Forense | F100: 45485 | G100: R$ 382.640,00 | H100: 45554 | I100: 45569 | L100: INVESTIMENTO | M100: SRP Estadual | O100: TRAMITAÇÃO | P100: Henrique Galperin | Q100: Cristiano de Mello Murbach | R100: PCP/CWB/VISC/COMP | S100: 45574 | T100: 19/09/2024- Empenho assinado
A101: 22.415.334-1 | B101: aquisição de dois Espectrômetros de massa com plasma indutivamente acoplado (ICP-MS) | C101: Raphael | D101: GAA | E101: Química Forense | F101: 45477 | G101: R$ 5.922.423,12 | L101: INVESTIMENTO | M101: LICITAÇÃO | O101: TRAMITAÇÃO | P101: LUIS HENRIQUE SOARES | Q101: RONALD SILVA SZAFIRSKI | R101: PCP/CWB/TAR - PCP/CWB/TAR/TOX | S101: 45601 | T101: 06/09/2024 - Encaminhado para origem para adequações 20/09/2024 - Com adequações reenviado Setor de Licitações via APC | U101: talvez - Tem parecer da PGE da minuta do edital. Esta no taruma para adequções | V101: Indefinido
...

Sheet Compras 2023
A2: 264 | G2: R$ 64.256.132,32 | H2: 154 | I2: 153 | J2: 138 | M2: 25
A3: PROCESSO N° | B3: DESCRIÇÃO | C3: instrução | D3: UNIDADE PCP | E3: Unidade a ser atendida | F3: DATA DE CRIAÇÃO | G3: VALOR PREVISTO | H3: EMPENHO ASSINADO | I3: EMPENHO ENVIADO AO FORNECEDOR (DATA) | J3: MATERIAL ENTREGUE (DATA) | K3: VERBA | L3: MODALIDADE | M3: Convênio | N3: SITUAÇÃO | O3: GESTOR | P3: FISCAL | Q3: ONDE ESTÁ | R3: Desde Consulta | S3: Observações | T3: Info Transitória | U3: ANO DA INSTRUÇÃO
A4: 18.750.605-0 | B4: SRP - Aquisição através do Registro de Preço do PE 867/2020, de material de escritório para atender a unidade da Polícia Científica do Paraná | D4: CURITIBA | E4: TODAS UNIDADES - PCP | F4: 44636 | G4: R$ 2.632,65 | H4: SIM | I4: 44650 | J4: 44679 | K4: CUSTEIO | L4: REGISTRO DE PREÇO (ESTADUAL) | N4: FINALIZADO | O4: Não se aplica | P4: Não se aplica | Q4: PCP/DA/GAA/ALMOX | R4: 44761 | S4: Aguardando Entrega do Material02/12/2022 - Se encontra na PCP/DA/GAA/ALMOX para análise. Entregas realizadas: Andre Matias - 27/04/2022 JC da silva - falta entregar Solo G9 eireli - 10/05/2022 EVL eireli - 28/04/2022 | T4: #REF! | U4: #REF!
A5: 18.805.485-4 | B5: Licit. Rastreadores - Sol. abertura de procedimento licitatório, visando a contratação de empresa especializada em prestação de serviços de locação de rastreadores veiculares, a fim de atender a demanda da Polícia Científica do Paraná. | C5: Raphael | D5: CURITIBA | E5: TODAS UNIDADES - PCP | F5: 44650 | G5: R$ 107.568,00 | K5: CUSTEIO | L5: LICITAÇÃO | N5: ARQUIVADO | O5: Hideraldo Daniel Tavares e Amilton dos Santos | P5: Luiz Henrique da Silva Rotta, Henrique Czap Coelho, Lennon Biancato Ruhnke, Daniel Preti, Luis Henrique Ferreira de Moraes, Rafael Ricardo Fréz, Patrick Alysson de Souza e Silva, Marcos Paulo Bebici, Keila da Silva Back, Evandro Antônio Lara Seabra, Luciano Gardano Elias Bucharles, Maria Cecília Begnossi, Vanessa Regina Kluppel, Evandro Luiz Lustre, Edson da Silva Napoleão, Augusto Pasqualini Neto, Leonete Ghellere, Claudio Luiz Mangini e Edison Alves de Jesus | Q5: PCP/DA/GAA/COMPRAS | R5: 45068 | S5: Em análise para licitação desde o dia 29/07/2022No SL desde 13/09/2022 - 09/11 Setor de Compras - atualização de orçamentos - Orçamentos atualizados, aguardando assinaturas para devolução ao SL- 16/11/202202/12/2022 - Se encontra na SESP/SL para análise.19/12/2022 - Se encontra na PCP/DA/GAOFS para análise 10/01/2023 - Se encontra na SESP/SL para demais providências17/01/2023 - Se encontra na PCP/DA/SEC para demais providências01/02/2023 - Se encontra na PCP/DA/GAA/COMPRAS para providências 18/04/2023 - Processo de investimento, aguardando verba | T5: #REF! | U5: #REF!
A6: 18.849.645-8 | B6: Licitação - Aquisição de maletas para exames de perícia em local de crime, a fim de atender a demanda do órgão da Polícia Científica do Paraná, conforme instrumento de convênio firmado n.° 920483/2021 | C6: Tatiane | D6: CURITIBA | E6: TODAS UNIDADES - PCP | F6: 44662 | G6: R$ 998.226,88 | H6: SIM | I6: 45098 | J6: sim | K6: INVESTIMENTO | L6: LICITAÇÃO | M6: 920.483/2021 | N6: FINALIZADO | O6: Ciro José Cardoso Pimenta | P6: Jorge Aurélio Perito de Bem | Q6: PCP/DIR - PCP/DIR/DIROP | R6: 45274 | S6: Em andamenrtoNo SL desde 17/08/202202/12/2022 - Se encontra na SESP/GAS/SC para providências.19/12/2022 - Se encontra na SESP/NACC/EP para demais providências03/01/2023 - Se encontra na SESP/APC para demais providências17/01/2023 - Se encontra SESP/GOFS/CO providências 26/06/2023 - Encaminhado a origem para aguardar entrega 17/08/2023 - Se encontra na PCP/DIR/GAB para providencias
A7: 18.862.591-6 | B7: Licitação - Aquisição de Sistema Informatizado de Automação e Gestão LIMS, a fim de atender o Laboratório de DNA da Polícia Científica. Convênio Plataforma +Brasil número 919141/2021 | C7: Tatiane | D7: UETC Tarumã | E7: CURITIBA - GENÉTICA FORENSE | F7: 44664 | G7: R$ 594.733,56 | K7: INVESTIMENTO | L7: LICITAÇÃO | M7: 919.141/2021 | N7: ARQUIVADO | O7: Marianna Maia Taulois do Rosario | P7: Pedro Henrique Canezin | Q7: PCP/CWB/TAR/GENET | R7: 45373 | S7: Em análise para licitaçãoNo SL desde 31/08/2022 11/10/2022 - Encontra-se na CELEPAR para aprovação02/12/2022 - Se encontra na CELEP/GSI-A para providências.19/12/2022 - Se encontra na PCP/CWB/TAR/GENET para demais providências SOLICITADAS PELA AT 30/08/2023 - Se encontra na PCP/CWB/TAR/GENET desde a data 19/12/2022 | T7: #REF! | U7: 2022
A8: 18.862.601-7 | B8: Licitação Contratação de serviço de consultoria à acreditação na norma ABNT NBR ISO 17025 / Convênio Plataforma +Brasil número 919141/2021 | C8: Eduarda | D8: UETC Tarumã | E8: CURITIBA - GENÉTICA FORENSE | F8: 44664 | G8: R$ 169.900,00 | K8: CUSTEIO | L8: LICITAÇÃO | M8: 919.141/2021 | N8: ARQUIVADO | O8: Marianna Maia Taulois do Rosario | P8: Pedro Henrique Canezin | Q8: PCP/CWB/TAR/GENET | R8: 45377 | S8: Em análise para licitaçãoNo SL desde 13/09/2022 29/11/2022 - Retornou ao setor para atualização de orçamento a termo de referência (aguardando orçamentos atualizados)02/12/2022 - Se encontra na PCP/DA/GAA/COMPRAS para providências.17/01/2023 - Se encontra na SESP/GOFS/CO para demais providências 17/03/2023 - Devolvido a origem para adequação na Nova Lei 30/08/2023 - Se encontra no PCP/CWB/TAR/GENET desde a data 17/03/2023 para adequação a nova lei | T8: #REF! | U8: 2022
A9: 18.898.878-4 | B9: Licitação - Aquisição de detectores de metais para o órgão da Polícia Científica do Paraná, convênio firmado n. 920483/2021. | C9: Allan | D9: CURITIBA | E9: TODAS UNIDADES - PCP | F9: 44678 | G9: R$ 115.551,96 | H9: 45239 | I9: 45981 | J9: 45327 | K9: INVESTIMENTO | L9: LICITAÇÃO | M9: 920.483/2021 | N9: FINALIZADO | O9: Ciro José Cardoso Pimenta | P9: Jorge Aurélio Perito de Bem | Q9: PCP/DO/COORD | R9: 45463 | S9: Em análise para licitaçãoSL desde 13/09/2022 08/11/2022 - Retornou para atualização de orçamentos 08/11/2022 - Encaminhado a SESP/SL com as devidas correções02/12/2022 - Se encontra na SESP/SL para análise. 26/06/2023 - Se encontra na SESP/EP para fins de libreração de recuso 28/08/2023 - Encaminhado para SESP/GOFS/CO para providencias.05/02/2024- Material recebido | T9: #REF! | U9: 2022
A10: 19.175.031-4 | B10: SRP Produto de Limpeza II - Contratação através do SRP PE n 125/2021, de Produto de Limpeza II, visando atender a demanda do órgão da Polícia Científica do Paraná. | C10: Allan | D10: CURITIBA | E10: TODAS UNIDADES - PCP | F10: 44747 | G10: R$ 33.288,26 | H10: SIM | I10: 44769 | J10: 44824 | K10: CUSTEIO | L10: REGISTRO DE PREÇO (ESTADUAL) | N10: FINALIZADO | O10: Não se aplica | P10: Não se aplica | Q10: PCP/DA/GAA/ALMOX | R10: 44881 | S10: Aguardando finalização dos pagamentos05/12/2022 - Seencontra na PCP/DA/GAA/ALMOX para demais providências. Kelly A.D.L - 02/08/2022 e 16/08/2022 (entregou todo o material) Isanete - 03/08/2022 e 20/09/2022 (falta entregar) Cig eireli - 04/08/2022 e 12/08/2022 (entregou todo o material) Solo G9 - 15/09/2022 e 25/10/2022 (entregou todo o material) | T10: #REF! | U10: #REF!
A11: 19.122.659-3 | B11: Licitação - Aquisição de balanças semi-analíticas para atender a demanda das unidades da Polícia Científica do Paraná | C11: Raphael | D11: CURITIBA | E11: TODAS UNIDADES - PCP | F11: 44735 | G11: R$ 85.041,50 | H11: SIM | I11: 45034 | J11: 45054 | K11: INVESTIMENTO | L11: LICITAÇÃO | N11: FINALIZADO | O11: Francisco da Silva Martins | P11: Rafael Araújo da Silva | Q11: SESP/DG/NFS | R11: 45499 | S11: 24/10/2022 - Atualização de orçamentos 18/11/2022 - Encaminhado a SESP/SL para demais providências05/12/2022 - Se encontra na SESP/SL para análise. 26/06/2023 - Se encontra no GOFS/FI para liquidação da NF | T11: #REF! | U11: 2022
A12: 19.115.163-1 | B12: Inexigibilidade - Contratação de empresa para prestação de serviços de manutenção corretiva em equipamento Microcomparador Balístico | C12: Allan | D12: CURITIBA | E12: CURITIBA - BALÍSTICA FORENSE | F12: 44734 | G12: R$ 34.870,00 | K12: CUSTEIO | L12: DISPENSA (INEXIGIBILIDADE) | N12: ARQUIVADO | O12: Jorge Aurélio Perito de Bem | P12: Francisco da Silva Martins | Q12: PCP/CWB/VISC/BALI | R12: 45374 | S12: 23/09/2022 - PCP/DO/DIV/SEC para providências05/12/2022 - Se encontra na SESP/APC para demais providências.01/02/2023 - Se encontra na PCP/CWB/TAR/CHEFIA para demais providências 16/03/2023 - PCP/DA/SEC para análise e providencias 01/06/2023 - Encaminhado a origem para adequação 20/06/2023 - Encaminhado ao PCP/GAA/GAOFS para atualização orçamentária 31/07/2023 - Devolvido à origem para adequações 30/08/2023 - Se encontra na PCP/CWB/VISC/BALI desde a data 31/07/2023 para adequações | T12: #REF! | U12: #REF!
A13: 19.217.723-5 | B13: SRP - Aquisição através do Sistema de Registro de Preço do Pregão Eletrônico n 516/2021, de artigos de higiene e EPI's para atender a demanda do órgão da Polícia Científica do Paraná. | C13: Allan | D13: CURITIBA | E13: TODAS UNIDADES - PCP | F13: 44755 | G13: R$ 41.089,84 | H13: SIM | I13: 44770 | J13: 44824 | K13: CUSTEIO | L13: REGISTRO DE PREÇO (ESTADUAL) | N13: FINALIZADO | O13: Não se aplica | P13: Não se aplica | Q13: PCP/DA/GAA/COMPRAS | R13: 45568 | S13: Aguardando demais notas de pagamento05/12/2022 - Se encontra na PCP/DA/GAA/ALMOX para demais providências. INGÁDESC - 08/08/2022 MGS - 08/08/2022 Protflex - 11/08/2022 SomaPR - 23/08/2022 Sagati - 26/08/2022 Extec - 19/09/2022 Jhonathan - 08/09/2022 Tov clean 20/09/2022 CIG eireli - 28/09/2022 Dermelyne LTDA 16/09/2022 | T13: #REF! | U13: #REF!
A14: 19.184.014-3 | B14: Licitação - Aquisição de câmaras frias mortuárias para atender a demanda das unidades da Polícia Científica de Campo Mourão, Francisco Beltrão, Paranaguá e Toledo | C14: Allan | D14: CURITIBA | E14: TODAS UNIDADES - PCP | F14: 44749 | G14: R$ 302.318,00 | H14: SIM | I14: 44865 | J14: 45036 | K14: INVESTIMENTO | L14: LICITAÇÃO | N14: FINALIZADO | O14: Leonel Letnar Junior | P14: Henrique Czap Coelho, Graciele Cristina Zawadzki Pereira, Vanessa Regina Kluppel Cunha, Leonete Ghellere | Q14: SESP/DG/NFS | R14: 45499 | S14: Em análise setor de licitações SESPSL 27/10/2022 07/11/2022 - Aguardando assinatura do contrato 08/11/2022 - Encaminhado à SESP contratos para demais providências 16/11/2022 - Encaminhado email a empresa e para responsáveis para acompanhamento da instalção da camâra fria, protocolo enviado para o gestor para acompanhamento da execução.05/12/2022 - Se encontra na PCP/DO/SEC para demais providências.
A15: 19.154.401-3 | B15: Licitação - Aquisição de tanques balísticos para atender a demanda das unidades da Polícia Científica do Paraná. | C15: Allan | D15: CURITIBA | E15: TODAS UNIDADES - PCP | F15: 44743 | G15: R$ 130.533,32 | H15: SIM | I15: 45118 | J15: sim | K15: INVESTIMENTO | L15: LICITAÇÃO | N15: FINALIZADO | O15: Jorge Aurélio Perito de Bem, Leonel Letnar Junior | P15: Lennon Biancato Ruhnke, Rafael Ricardo Fréz, Graciele Cristina Zawadzki Pereira, Edson da Silva Napoleão, Augusto Pasqualini Neto | Q15: SESP/DG/NFS | R15: 45499 | S15: Em andamento para realização da minutaSL 17/10/202205/12/2022 - Se encontra na SESP/SL para análise 26/07/2023 - Para coletar assinatura do contratado 30/08/2023 - Se encontra no PCP/CWB/VISC/BALI para acompanhamento da entrega | T15: #REF! | U15: #REF!
A16: 19.176.669-5 | B16: Licitação - Aquisição de duas unidades de Scanners A3, a fim de atender a demanda do órgão da Polícia Científica do Paraná. | C16: Raphael | D16: CURITIBA | E16: UETC Visconde | F16: 44748 | G16: R$ 68.083,26 | H16: SIM | I16: sim | J16: 45065 | K16: INVESTIMENTO | L16: LICITAÇÃO | N16: FINALIZADO | O16: Daniel Preti | P16: Rafel Vinicius Monetta de Carvalho | Q16: SESP/DG/NFS | R16: 45499 | S16: 17/10/2022 - Retornou para ajuste dos valores (divergência R$0,01)18/10/2022- Corrigidos TR e Mapa, enviado SESP/APC para continuidade 01/11/2022 - Retornou para o compras para atualização de orçamento 04/11/2022 - Encaminhado para SESP/AT via SESP/APC com o devido orçamento atualizado05/12/2022 - Se encontra na SESP/SL para análise.16/12/2022 - Se encontra na SESP/SL/EXPED para demais providências04/01/2023 - Se encontra na SESP/SL para análise18/01/2023 - Licitado. Aguardando liberação de recursos 14/04/2023 - enviado SESP/APC para providencias
A17: 19.260.821-0 | B17: (1) SRP Água Mineral (IML) - Aquisição através do Sistema de Registro de Preço do Pregão Eletrônico n.o 1857/2021, de água mineral (galão de 20L) para atender a demanda das unidades da Polícia Científica de Curitiba (Unidade Tarumã), Paranaguá e Ponta Grossa. | C17: Allan | D17: CURITIBA | E17: TODAS UNIDADES - PCP | F17: 44767 | G17: R$ 13.720,80 | H17: SIM | I17: 44783 | J17: Entrega sob demanda | K17: CUSTEIO | L17: REGISTRO DE PREÇO (ESTADUAL) | N17: FINALIZADO | O17: Não se aplica | P17: Não se aplica | Q17: PCP/DA/GAA/COMPRAS | R17: 44865 | S17: Aguardando as notas atestadas05/12/2022 - Se encontra na PCP/DA/GAA/COMPRAS para providências. Vilma distribuidora - 22/08/2022 DJ LTDA - falta entregar 02/09/2022 - Encaminhado ao GAA para aguardar as demais NFs | T17: #REF! | U17: #REF!
A18: 19.268.395-5 | B18: (2) SRP Água Mineral (IML) - Aquisição através do Sistema de Registro de Preço do Pregão Eletrônico n.o 1857/2021, de água mineral (galão de 20L) para atender a demanda das unidades da Polícia Científica de Londrina, Apucarana, Jacarezinho e Ivaiporã. | C18: Allan | D18: CURITIBA | E18: TODAS UNIDADES - PCP | F18: 44767 | G18: R$ 7.461,20 | H18: SIM | I18: 44782 | J18: Entrega sob demanda | K18: CUSTEIO | L18: REGISTRO DE PREÇO (ESTADUAL) | N18: FINALIZADO | O18: Não se aplica | P18: Não se aplica | Q18: PCP/DA/GAA/COMPRAS | R18: 44865 | S18: Aguardando NF'S para pagamento05/12/2022 - Se encontra na PCP/DA/GAA/COMPRAS para providências. KS LTDA - 24/08/2022, 25/08/2022 e 21/09/2022 (falta entregar em Apucarana e Jacarezinho) 02/09/2022 - Encaminhado ao GAA para aguardar as demais NFs | T18: #REF! | U18: #REF!
A19: 19.268.428-5 | B19: (3) SRP Água Mineral (IML) - Aquisição através do Sistema de Registro de Preço do Pregão Eletrônico n.o 1857/2021, de água mineral (galão de 20L) para atender a demanda das unidades da Polícia Científica de Maringá, Umuarama, Campo Mourão e Paranavaí. | C19: Allan | D19: CURITIBA | E19: TODAS UNIDADES - PCP | F19: 44767 | G19: R$ 17.182,80 | H19: SIM | I19: 44782 | J19: Entrega sob demanda | K19: CUSTEIO | L19: REGISTRO DE PREÇO (ESTADUAL) | N19: FINALIZADO | O19: Não se aplica | P19: Não se aplica | Q19: PCP/DA/GAA/COMPRAS | R19: 44865 | S19: Liquidado, aguardando pagamento05/12/2022 - Se encontra na PCP/DA/GAA/COMPRAS para providências. KS LTDA - 22/08/2022 e 25/08/2022 (falta entregar) 26/10/2022 - Encaminhado ao GAA para aguardar as demais NFs | T19: #REF! | U19: #REF!
A20: 18.110.505-4 | B20: Licitação - Aquisição um Sistema de Cromatografia Líquida Acoplado a Espectrômetro de Massas Sequencial (LC-MS/MS), visando atender as necessidades de ampliação do escopo de análises analíticas realizadas pelos Laboratórios de Química Forense e Toxicologia Forense da Polícia Científica do Paraná (Convênio "Em Frente Brasil") | C20: Adolfo | D20: CURITIBA | E20: CURITIBA - LABORATÓRIOS | F20: 44459 | G20: R$ 2.434.705,50 | K20: INVESTIMENTO | L20: LICITAÇÃO | N20: TRAMITANDO | O20: Viviane Paola Zibe e Piegel | P20: Isabella Ferreira Melo | Q20: PCP/CWB/TAR/TOX | R20: 45470 | S20: SESP/APC/BP desde o dia 28/06/2022 05/12/2022 - Se encontra aguardando documentação na SESP/APC/BP 20/04/2023 - Encaminhado para origem para adequação conforme nova Lei de Licitações 11/05/2023 - Encaminado a SESP/APC para continuação da tramitação 30/08/2023 - Se encontra no SESP/APC para continuação da tramitação 05/12/2023 - SESP/APC desde 11/05/2023 aguardando recurso27/06/2024- Encaminhado à origem para arquivamento, considerando que foi instruído um novo protocolo
A21: 19.371.367-0 | B21: SRP Administrativo (1) - Carona ao SRP PE n 1428/2021, visando a contratação de postos de administrativo I 40 horas semanais junto à empresa PRODUSERV SERVIÇOS LTDA., a fim de atender a demanda do órgão da Polícia Científica do Paraná. | D21: CURITIBA | E21: TODAS UNIDADES - PCP | F21: 44791 | G21: R$ 199.853,36 | K21: CUSTEIO | L21: REGISTRO DE PREÇO (ESTADUAL) | N21: ARQUIVADO | O21: Não se aplica | P21: Não se aplica | Q21: PCP/DA/GAA/COMPRAS | R21: 45054 | S21: considerando a negativa de adesão a ata, arquivado
A22: 19.372.680-1 | B22: SRP Assistente Administrativo (3) - Carona ao SRP PE n 1428/2021, visando a contratação de postos de assistente administrativo I 40 horas semanais junto à empresa PLANSERVICE TERCEIRIZAÇÃO DE SERVIÇOS - EIRELI, a fim de atender a demanda do órgão da Polícia Científica do Paraná. | D22: CURITIBA | E22: TODAS UNIDADES - PCP | F22: 44791 | G22: R$ 59.826,08 | K22: CUSTEIO | L22: REGISTRO DE PREÇO (ESTADUAL) | N22: ARQUIVADO | O22: Não se aplica | P22: Não se aplica | Q22: PCP/DA/GAA/COMPRAS | R22: 45061 | S22: considerando a negativa de adesão a ata, arquivado | T22: #REF! | U22: #REF!
A23: 19.241.476-8 | B23: Dispensa - Aquisição de equipamentos de áudio para sonorização do auditório da Polícia Científica (Unidade Tarumã). Sistema de som | C23: Allan | D23: CURITIBA | E23: SEDE - TARUMÃ | F23: 44760 | G23: R$ 7.209,10 | K23: INVESTIMENTO | L23: DISPENSA (COMPRA DIRETA) | N23: ARQUIVADO | O23: Gabriel de Andrade Manoel | P23: Emílio Merino de Paz Júnior | Q23: PCP/NIC/OUV | R23: 45070 | S23: Aguardando análise pela Direção Geral da PCP 04/10/2022 - No orçamentário para informações e demais providências05/12/2022 - Se encontra na SESP/GAS/SC para demais providências.16/12/2022 - Se encontra na SESP/SL para demais providências10/01/2023 - Se encontra na SESP/SL/EXPED para demais providências18/01/2023 - Se encontra na PCP/DA/DIV para demais providências | T23: #REF! | U23: #REF!
A24: 19.405.931-0 | B24: SRP Material de Expediente (grupo iv) - Aquisição através do Sistema de Registro de Preço do Pregão Eletrônico n.o 260/2022, de Material de Expediente (grupo IV), para atender a demanda do órgão da Polícia Científica do Paraná. | C24: Allan | D24: CURITIBA | E24: TODAS UNIDADES - PCP | F24: 44799 | G24: R$ 1.628,25 | H24: SIM | I24: 44816 | K24: CUSTEIO | L24: REGISTRO DE PREÇO (ESTADUAL) | N24: FINALIZADO | O24: Não se aplica | P24: Não se aplica | Q24: PCP/DA/GAA/ALMOX | R24: 45125 | S24: Aguardando entrega do Material 11/10/2022 - Aguardando NF's para pagemento05/12/2022 - Se encontra PCP/DA/GAA/ALMOX para demias providências EVL eireli - 19/09/2022 e 20/09/2022 Distribuidora LTDA - 29/09/2022 Pem comercial - 17/10/2022 (falta entregar). | T24: #REF! | U24: #REF!
A25: 18.536.742-8 | B25: Abertura de Procedimento Licitatório para a Aquisição de Câmara Frigorífica Mortuária para equipar a unidade da Polícia Científica de Umuarama, Considerando o Convênio Federal N.O 920483/2021 | C25: Allan | D25: Umuarama | E25: UETC Umuarama | F25: 44804 | G25: R$ 162.000,00 | H25: SIM | I25: 45070 | K25: INVESTIMENTO | L25: LICITAÇÃO | M25: 920.483/2021 | N25: FINALIZADO | O25: Claudio Luiz Mangini | P25: Simone Silva de Queiroz | Q25: PCP/CM/CHEFIA | R25: 45540 | S25: 05/09/2022 - Encaminhado para SESP.10/10/2022 - Nesta data chegou no setor de licitações SL 17/10/202205/12/2022 - Se encontra na SESP/SL para análise.16/12/2022 - Se encontra na SESP/SL/EXPED para demais providências10/01/2023 - Se encontra na SESP/SL para análise18/01/2023 - Se encontra na SESP/NACC/EP para demais providências06/03/2022 - JA FOI LICITADO. AGUARDANDO EMISSÃO DE EMPENHO 24/05/2023 - Encaminhado a origem para aguardar a entrega do material
A26: 19.286.481-0 | B26: Aquisição de Ferramenta Forense de extração e processamento de dados provenientes da navegação na Internet, com Inexigibilidade de Licitação - Convênio FUNSUSP (AÇÃO 3 - META 1: meta específica 1) | C26: Allan | D26: CURITIBA | E26: CURITIBA - COMPUTAÇÃO FORENSE | F26: 44804 | G26: R$ 520.164,00 | H26: SIM | I26: 44848 | J26: 44963 | K26: INVESTIMENTO | L26: LICITAÇÃO | M26: FUNSUSP | N26: FINALIZADO | O26: Márcio Lopes Vilanova e Silva | P26: Fabio Luiz Correia da Rocha | Q26: SESP/DG/NFS | R26: 45499 | S26: 26/10/2022 - Encaminhado para elaboração da minuta07/11/2022 - Encaminhado contrato para a empresa realizar assinatura (aguardando retorno)10/11/2022 - Encaminhado ao SESP/SC para demais providências quanto a assinatura do DG e publicação do DIOE18/11/2022 - Encaminhado ao setor de computação Forense para aguardar a entrega do objeto 05/12/2022 - Se encontra na PCP/CWB/VISC/COMP para demais providências10/01/2023 - Se encontra na PCP/DA/GAA/COMPRAS para demais providências TECH BIZ - 06/02/2023 (2 ENTREGAS) Entregas realizadas.Falta somente nota de pagamento, verificado em 15/05/2023 | T26: #REF! | U26: #REF!
A27: 19.443.904-0 | B27: Aditivo de Acréscimo de até 25% sob o Contrato n 1047/2021 firmado entre o Departamento de Polícia Civil e a empresa FABBRICA D'ARMI BERETTA - SPA, a fim de atender a demanda do órgão da Polícia Científica do Paraná. 20 Pistolas para ACF | C27: Allan | D27: ACF | E27: CURITIBA - ACADEMIA DE CIÊNCIAS FORENSES - ACF | F27: 44809 | G27: R$ 46.979,94 | K27: INVESTIMENTO | L27: ADITIVO | N27: SOBRESTADO | O27: Não se aplica | P27: Não se aplica | Q27: PCP/DIR/GAB | R27: 44854 | S27: Aguardando aprovação DA/DIV 17/10/2022 - Para informação do IOF no contrato 20/10/2022 PCP/DG encaminhado para ciência05/12/2022 - Se encontra na PCP/DIR/GAB AGUARDANDO CONCLUSÃO DO PROCESSO LICITATÓRIO | T27: #REF! | U27: #REF!
A28: 19.401.599-2 | B28: Licit. Câmeras e Gravadores - Sol. abertura de procedimento licitatório, visando a aquisição de câmeras de vigilância e gravadores de vídeo, a fim de atender a demanda do órgão da Polícia Científica do Paraná. | C28: Raphael | D28: CURITIBA | E28: TODAS UNIDADES - PCP | F28: 44798 | G28: R$ 233.381,50 | K28: INVESTIMENTO | L28: LICITAÇÃO | N28: ARQUIVADO | O28: Mariane Moreira Poletto | P28: Raphael Laércio Zago | Q28: PCP/DA/GAA/COMPRAS | R28: 45168 | S28: Aguardando assinaturas 07/10/2022 - Encaminhado a SESP/GOFS para providências 27/10/2022 - Sobretestar o protocolo até segunda ordem05/12/2022 - Se envontra na PCP/DA/GAA/CHEFE para análise. 18/04/2023 - Sendo instruído 28/08/2023 - Encaminhado da PCP/DIR/NI para PCP/DA/GAA/COMPRAS para arquivamento
A29: 19.234.881-1 | B29: Aquisição de testes imunocromatográficos para Sangue Oculto e PSA | C29: Tatiane | D29: CURITIBA | E29: SEDE - TARUMÃ | F29: 44757 | G29: R$ 7.990,00 | K29: CUSTEIO | L29: DISPENSA (COMPRA DIRETA) | N29: ARQUIVADO | O29: Marianna Maia Taulois do Rosario | P29: Josiane Brodzinski | Q29: PCP/CWB/TAR/GENET | R29: 45002 | S29: Encaminhado para o financeiro,Para informação orçamentária, pré empenho e empenho 09/11/2022 - Retornou para atualização 10/11/2022 - Foi pedido a atualização as propostas, aguardando retorno. 18/11/2022 - Encaminhado a SESP/APC para análise e demais providências e encaminhar a SESP/SL05/12/2022 - Se encontra na PCP/CWB/TAR/GENET para demais providências.06/03/2023 - JA PASSOU PELO FINANCEIRO, NÃO TEM DESPACHO E ESTÁ NO TAR/GENET | T29: #REF! | U29: #REF!
A30: 19.403.625-6 | B30: PROCESSO DE COMPRA DE ITENS PARA COLETA DE RESÍDUOS DE DISPARO DE ARMAS DE FOGO (STUBS, FITAS DE CARBONO E EMBALAGENS) | C30: Eduarda | D30: CURITIBA | E30: TODAS UNIDADES - PCP | F30: 44792 | G30: R$ 14.730,00 | H30: SIM | I30: 45015 | J30: SIM | K30: CUSTEIO | L30: DISPENSA (COMPRA DIRETA) | N30: FINALIZADO | O30: Emilio Merino de Paz Junior | P30: Beatriz Rossi Canuto de Menezes Rodrigues | Q30: SESP/DG/NFS | R30: 45499 | S30: Encaminhado para o financeiro,Para informação orçamentária, pré empenho e empenho 05/12/2022 - Se encontra sobrestar pela SESP/APC/BP.02/02/2023 - Se encontra na SESP/GAS/SC para análise07/02/2023 - Se encontra na PCP/DA/GAA/COMPRAS para demais providências 30/03/2023 - Encaminhado a origem para aguardar a entrega do material | T30: #REF! | U30: #REF!
A31: 19.453.022-6 | B31: Plataforma integrada de sequenciamento automatizado, paralelo e de alto rendimento | C31: Eduarda | D31: UETC Tarumã | E31: CURITIBA - GENÉTICA FORENSE | F31: 44810 | G31: R$ 839.123,59 | H31: 45112 | I31: 45118 | J31: SIM | K31: INVESTIMENTO | L31: LICITAÇÃO | N31: FINALIZADO | O31: Mariana Maia Taulois do Rosario | P31: Jaqueline Andressa Machado Trentin Luz | Q31: SESP/DG/NFS | R31: 45499 | S31: 14/10/2022 - SL para análise05/12/2022 - Se encontra na SESP/SL para análise.16/12/2022 - Se encontra na SESP/SL/EXPED para demais providências10/01/2023 - Se encontra na SESP/SL para demais providências18/01/2023 - Se encontra na PCP/DA/GAOFS para demais providências02/02/2023 - Se encontra na PCP/CWB/TAR/GENET para demais providências03/07/2023 - Contrato assinado encaminhado à sesp11/07/2023 - Contrato e empenho assinados 30/08/2023 - Se encontra na PCP/DA/GAA/PATR para patrimoniamento
A32: 19.454.464-2 | B32: Aquisição de equipamentos diversos - Projeto Fim da Dúvida | C32: Raphael | D32: UETC Tarumã | E32: CURITIBA - GENÉTICA FORENSE | F32: 44810 | G32: R$ 118.091,50 | K32: INVESTIMENTO | L32: LICITAÇÃO | N32: Arquivado | O32: Mariana Maia Taulois do Rosario | P32: Jaqueline Andressa Machado Trentin Luz | Q32: PCP/CWB/TAR/GENET | R32: 45184 | S32: 10/10/2022 - Autorizado e Publicado 05/12/2022 - Se encontra na PCP/CWB/TAR/GENET para demais providências.05/05/2023 - Encaminhado para SEDEF informando que não é mais necessário tramitar devido aos equipamentos ja terem sido adquiridos com recursos proprios. 30/08/2023 - Encaminhado da SESP/APC para a PCP/DA/GAA/COMPRAS no dia 28/08/2023 para providencias | T32: #REF! | U32: #REF!
A33: 17.194.401-5 | B33: Aquisição de Perfurador automatizado de cartões tipo FTA - Projeto DNA - Fim da Dúvida | C33: Taborda | D33: CURITIBA | E33: TODAS UNIDADES - PCP | F33: 2021 | G33: R$ 400.000,00 | H33: SIM | I33: 44818 | J33: 44909 | K33: CUSTEIO | L33: LICITAÇÃO | N33: ARQUIVADO | O33: Mariana Ulyssea de Quadros | P33: Marcelo Malaghini | Q33: PCP/CWB/TAR/GENET | R33: 45096 | S33: 22/09/2022 - Contrato assinado. Enviado nesta data para a SESP26/09/2022 - Retornou com o Contrato assinado para informar a empresa.27/09/2022 - Enviado para a empresa o contrato assinado e a Nota de Empenho. Em cópia Marianna Maia e Malaghini (Gestor e Fiscal) Protocolo encaminhado para que aguardem a entrega do equipamento.05/12/2022 - Se encontra na PCP/DIR/GAB para demais providências.16/12/2022 - Se encontra na PCP/DA/GAA/PATR para demais providências18/01/2023 - Se encontra na PCP/CWB/TAR/GENETpara análise02/02/2023 - Se encontra na SEDEF/NFS para demais providências08/02/2023 - Se encontra na SEDEF/CPCA para demais providências QIAGEN - Entregas em 10/10/2022 e 14/12/2022 | T33: #REF! | U33: #REF!
A34: 18.713.605-9 | B34: processo de licitação para aquisição de reagentes químicos, visando atender as necessidades dos Laboratórios de Química Forense e Toxicologia Forense | C34: Adolfo | D34: CURITIBA | E34: CURITIBA - LABORATÓRIOS | F34: 44628 | G34: R$ 171.821,00 | H34: SIM | I34: 45016 | J34: 45082 | K34: CUSTEIO | L34: LICITAÇÃO | N34: FINALIZADO | O34: Viviane Paola Zibe e Piegel | P34: Isabella Ferreira Melo | Q34: PCP/CWB/TAR/QUIM | R34: 45191 | S34: Para intrução processual - 16/11/2022 - Aguardando assinaturas para encaminhamento ao financeiro 24/10/2022 Processo na fase de coleta de orçamentos.31/10/2022 - Aguardando orçamentos... O que foi enviado não atendeu01/12/2022 - Protocolo se encontra na SESP - SESP/SL.06/12/2022 - Se encontra na SESP/SL para análise."05/12/2022 - Se encontra na SESP/SL para análise. São 3 empresas, duas já realizaram as entregas. | T34: #REF! | U34: #REF!
A35: 19.340.617-3 | B35: COMISSÃO DO CONCURSO PÚBLICO PARA O CARGO DE AGENTE DE AUXILIAR DA PERÍCIA OFICIAL DO PARANÁ DA PCP DELIBERAÇÕES E DOCUMENTOS PARA ANÁLISE E ACOLHIMENTO DA INDICAÇÃO DE CONTRATAÇÃO DE BANCA EXAMINADORA PARA O CERTAME. | C35: Eduarda | D35: CURITIBA | E35: TODAS UNIDADES - PCP | F35: 44834 | G35: R$ 576.000,00 | H35: SIM | I35: 44861 | J35: 45041 | K35: INVESTIMENTO | L35: DISPENSA (COMPRA DIRETA) | N35: FINALIZADO | O35: Ciro José Cardoso Pimenta | P35: Gabriel de Andrade Manoel | Q35: SESP/DG/NFS | R35: 45513 | S35: 05/10/2022 - Encaminhado para Assessoria da Policia Cientifica para demais providências 27/10/2022- Para recolher assinatura da empresa06/12/2022 - Se encontra na PCP/DIR/DIROP para análise.
A36: 19.573.613-8 | B36: Licit. Cromatógrafo Gasoso (02) - Sol. abertura de procedimento licitatório, visando a aquisição de dois Sistemas de Cromatografia Gasosa Acoplado a Espectrometria de Massas, a fim de atender a demanda do Laboratório de Química Forense da Polícia Científica do Paraná. (UM INVESTIMENTO E UM CONVÊNIO (EM FRENTE BRASIL 894219/2019) | C36: Eduarda | D36: CURITIBA | E36: Curitiba - Laboratórios | F36: 44840 | G36: R$ 2.612.121,16 | H36: SIM | I36: 45100 | J36: sim/2 | K36: INVESTIMENTO | L36: LICITAÇÃO | M36: 894.219/2019 | N36: FINALIZADO | O36: Isabella Ferreira Melo | P36: Viviane Paola Zibe e Piegel | Q36: SESP/DG/NFS/CON | R36: 45489 | S36: 06/10/2022 - Protocolo aberto em razão do 19.036.122-5 ter sido cancelado devido a ter apenas um sistema de cromatografia.07/10/2022 - Encaminhado para tramitassão. 19/10/2022 - (alteração justificativa 85) Encaminhado a SESP/APC para demais providências 26/10/2022 - Encaminhado a assessoria da policia cientifica para análise e providências06/12/2022 - Se encontra na SESP/SL para análise.18/01/2023 - Se encontra na SESP/GOFS/FI para demais providências02/02/2023 - Se encontra na SESP/NACC/EP para demais providências 19/06/2023 - Encaminhado ao SESP/SC para continuação da tramitação 23/06/2023 - Empenho enviado
A37: 19.571.815-6 | B37: Aquisição de Tablet Forense (multiespectral) através do Convênio Federal 894219/2019 "Em Frente Brasil" | C37: Raphael | D37: CURITIBA | E37: SEDE - TARUMÃ | F37: 44844 | G37: R$ 315.000,00 | H37: SIM | I37: 45093 | J37: 45148 | K37: INVESTIMENTO | L37: DISPENSA (INEXIGIBILIDADE) | M37: 894.219/2019 | N37: ARQUIVADO | O37: Ciro José Cardoso Pimenta | P37: Jorge Aurélio Perito de Bem | Q37: SESP/ARQUIVO | R37: 45267 | S37: 10/10/2022 - Encaminhado PCP/DA/SEC para posterior encaminhamento ao DG 20/10/2022 - Anexado docs corrigidos e enviado p/ SESP/APC p/ continuidade 28/10/2022 Para análise01/12/2022 - Encaminhado para SESP - SESP/AT para providências.06/12/2022 - Se encontra na SESP/AT para demais providências.16/12/2022 - Se encontra na SESP/NACC/EP para demais providências09/01/2023 - Se encontra na SESP/GOFS/CO para demais providências 16/06/2023 - Encaminhado a origem para aguardar a entrega do material 30/08/2023 - Material entregue 10/08/2023, enviado GOFS/SESP para pagamento em 23/08/2023
A38: 19.152.596-5 | B38: PE-1679/2022 Licit. Processador de Tecidos Histológico, a fim de atender a demanda do Laboratório de Anatomopatologia Forense da Polícia Científica do Paraná. | C38: Eduarda | D38: CURITIBA | E38: SEDE - TARUMÃ | F38: 44848 | G38: R$ 69.651,55 | K38: INVESTIMENTO | L38: LICITAÇÃO | N38: TRAMITANDO | O38: Regina de Paula Xavier Gomes | P38: Anne Caroline Kambara Scholze | Q38: PCP/CWB/TAR/PATOL | R38: 45495 | S38: 14/10/2022 - Encaminhado para adequação de orçamentos17/10/2022 - Retornou para o compras nesta data 01/11/2022 - Taborda ficou de verificar com o Luciano APC08/11/2022 - Aguardando retorno da Regina com as negativas16/11/2022 - Encaminhado a SESP/SL via SESP/APC para continuidade da tramitação. 29/11/2022 - Protocolo retornou da AT solicitando mudar orçamentos. Foi realizada uma justificativa e devolvido o protocolo.01/12/2022 - Protocolo se encontra na SESP - SESP/SL para análise.18/01/2023 - Se encontra na PCP/DA/SEC para demais providências08/02/2023 - Se encontra na PCP/DA/GAA/CHEFE para análise 19/07/2023 - Encaminhado para PCP/DA/DIV para continuação da tramitação 30/08/2023- encontra-se no PCP/DA/GAA/COMPRAS para novas adequações. 04/09/2023 - Encaminhado a origem para as devidas adequações 05/12/2023- Desde 21/09 sobrestado na origem 12/01/2024 - Protocolo devolvido ao compras com adequações insuficientes, em acordo entre chefias em 08/02/2024 protocolo restituído a origem - PCP/CWB/TAR/GENET para instrução processual | T38: #REF! | U38: #REF!
A39: 19.589.832-4 | B39: SRP Administrativo (Lote 4 (DDD43) - Transferência de saldo da SESP ao DPC PE n 1428/2021, visando a contratação de postos de administrativo I 40 horas semanais junto à empresa PLANSERVICE TERCEIRIZAÇÃO DE SERVIÇOS EIRELI, a fim de atender a demanda do órgão da Polícia Científica do Paraná. | C39: Raphael | D39: CURITIBA | E39: Apucarana, Ivaiporã, Jacarezinho e Londrina | F39: 44845 | G39: R$ 226.180,80 | H39: SIM | I39: serviço | J39: SIM | K39: CUSTEIO | L39: REGISTRO DE PREÇO (ESTADUAL) | N39: ARQUIVADO | Q39: PCP/DA/GAA/CONTRATOS | R39: 45056 | S39: 17/10/2022 - Aguardando Assinaturas18/10/2022 - Assinaturas realizadas. Será encaminhado nesta data18/10/2022 - Enviado PCP/DA/SEC para aprovação e continuidade01/12/2022 - Protocolo se encontra na SESP - SESP/AT para providências. 14/12/2022 - Encaminhado à SESP/APC para demais providências16/12/2022 - Se encontra na SEAP/GS para demais providências10/01/2023 - Se encontra na SESP/GS para demais providências18/01/2023 - Se encontra na SESP/GOFS/FI para demais providências08/02/2023 - Se encontra na SESP/GAS/SC para demais providências | T39: #REF! | U39: #REF!
A40: 19.467.644-1 | B40: Registro de Preços para contratação futura e eventual de Equipamentos de processamento e armazenamento de vestígios digitais para equipar a Seção de Computação Forense da Polícia Científica do Paraná | C40: Eduarda | D40: CURITIBA | E40: SEÇÃO DE COMPUTAÇÃO FORENSE | F40: 44839 | G40: R$ 7.404.009,57 | K40: INVESTIMENTO | L40: LICITAÇÃO | N40: TRAMITANDO | O40: Márcio Lopes Vilanova e Silva | P40: Fabio Luiz Correia da Rocha | Q40: SEAP/DECON/SU | R40: 45468 | S40: 11/10/2022 - Encaminhado para atualização de proposta31/10/2022 - Propostas atualizadas - Será encaminhado 03/11/2022 - Encaminhado para DA/DIV para análise e manifestação 22/11/2022 - Retornou para ajustes no TR 22/11/2022 - Encaminhado a Seção de Computação para providências01/12/2022 - Protocolose encontra na PCP/CWB/VISC/COMP06/12/2022 - Se encontra na PCP/CWB/VISC/COMP para demais providências. 19/04/2023 - Será adequado conforme a nova Lei 30/06/2023 - Protocolo adequado a nova lei, enviado à PCP/DA/SEC sugerindo encaminhamento à CELEPAR 30/08/2023 - Enviado SESP/ATIC para providências. 31/10/2023 - Encamihado a SESP/APC para continuação da tramitação. 13/11/2023 - Encaminhado a origem para adequações 05/12/2023 - desde 17/11 SEAP/DECON/DP08/04/2024- Encaminhado à Divisão de Licitação para análise e manifestação14/06/2024- Processo licitatório adjudicado e homologado25/06/2024- Aguardando arquivamento
A41: 19.545.203-2 | B41: PROCESSO PARA COMPRA DE INSUMOS DO LABORATORIO DE PATOLOGIA FORENSE | C41: Eduarda | D41: CURITIBA | E41: LABORATÓRIO DE ANATOMOPATOLOGIA | F41: 44861 | G41: R$ 13.799,00 | H41: SIM | I41: sim | J41: 44945 | K41: CUSTEIO | L41: DISPENSA (COMPRA DIRETA) | N41: ARQUIVADO | O41: Regina de Paula Xavier Gomes | P41: Anne Caroline Kambara Scholze | Q41: PCP/DA/GAOFS | R41: 45005 | S41: 31/10/2022 - Aguardando atualização de orçamentos e o fechamento da proposta com a empresa (resposta da empresa)03/11/2022 - Aguardando o fechamento com a empresa ganhadora 04/11/2022 - Encaminhado ao PCP/DA/DIV para análise e manifestação01/12/2022 - Protocolo se encontra na SESP - SESP/SL06/12/2022 - Se encontra na SESP/SL para análise.16/12/2022 - Se encontra na PCP/DA/GAA/ALMOX para demais providências08/02/2023 - Se encontra na PCP/DA/GAOFS para demais providências | T41: #REF! | U41: #REF!
A42: 19.671.267-4 | B42: SRP material de escritório - aquisição através do sistema de registro de preço do pregão eletrônico no. 268/2022, de material de escritório, para atender a demanda do órgão da Polícia Científica do Paraná. | C42: Danielson | D42: CURITIBA | E42: TODAS UNIDADES - PCP | F42: 44866 | G42: R$ 524,72 | H42: SIM | I42: 44883 | J42: 45055 | K42: CUSTEIO | L42: REGISTRO DE PREÇO (ESTADUAL) | N42: ARQUIVADO | O42: Não se aplica | P42: Não se aplica | Q42: PCP/DA/GAOFS | R42: 45071 | S42: 01/11/2022 - Encaminhado para DA/DIV para análise e providências 30/11/2022 - Encaminhado ao Almoxarifado para aguardar a entrega do material01/12/2022 - Protocolo se encontra na PCP/DA - PCP/DA/GAA/ALMOX.06/12/2022 - Se encontra na PCP/DA/GAA/ALMOX para demais providências.02/02/2023 - Se encontra na PCP/DA/GAOFS para demais providências08/02/2023 - Se encontra na PCP/DA/GAA/ALMOX para demais providências EVL eireli - 19/01/2023 Leão de Judá Comercial LTDA -Entregue em 09/05/2023, com essa última entrega, todo o material foi entregue, finalizando assim o processo. | T42: #REF! | U42: #REF!
A43: 19.693.238-0 | B43: NOVO Realização de termo aditivo ao contrato 0477/2022 - GMS 2013/2022, firmado entre o ESTADO DO PARANÁ, por intermédio da SECRETARIA DE ESTADO DA SEGURANÇA PÚBLICA, e a empresa VALID SOLUÇÕES S.A, referente à CONFECÇÃO DE CARTEIRAS DE IDENTIDADE FUNCIONAIS EM FORMATO FÍSICO (CARTÃO) E DE PERSONALIZAÇÃO | C43: Taborda | D43: CURITIBA | E43: TODAS UNIDADES - PCP | F43: 44872 | G43: R$ 24.913,04 | K43: CUSTEIO | L43: ADITIVO | N43: ARQUIVADO | Q43: PCP/DA/GAA/COMPRAS | R43: 44973 | S43: 07/11/2022 - Instruído novo processo por solicitação da Gerência e da Assessoria da PCP01/12/2022 - Protocolo se encontra na DPC/IIPR - DPC/II/DIR.06/12/2022 - Se encontra na DPC/II/DIR para demais providências.16/12/2022 - Se encontra na DPC/DG para análise18/01/2023 - Se encontra na SESP/DG para análise02/02/2023 - Se encontra na SESP/GAS/SC para análise08/02/2023 - Se encontra na SESP/ATJ para demais providências 05/12/2023 - Arquivado desde 16/02/2023
A44: 19.700.034-1 | B44: Apostilamento ao Contrato n 1135/2022 - LANCI INDUSTRIA E COMÉRCIO DE MÓVEIS PLÁSTICOS EIRELI (Espaço Verde), visando a retificação do descritivo do objeto. | C44: Eduarda | D44: CURITIBA | E44: CURITIBA | F44: 44873 | G44: R$ 0,00 | K44: N/A | L44: N/A | N44: ARQUIVADO | O44: Não se aplica | P44: Não se aplica | Q44: SESP/GOFS/FI | R44: 44967 | S44: 09/11/2022 - Encaminhado a DA/DIV para análise e providências 21/11/2022 - Encaminhado a chefia do tarumã para apensar o processo no protolo cabeça.01/12/2022 - Protocolo se encontra na PCP/CWB/TAR - PCP/CWB/TAR/CHEFIA.06/12/2022 - Se encontra na PCP/CWB/TAR/CHEFIA para demais providências.16/12/2022 - Se encontra apostado09/01/2023 - Se encontra na SESP/GOFS/FI para demais providências18/01/2023 - Se encontra na PCP/DA/GAA/PATR para análise02/02/2023 - Se encontra apensado no protocolo 18.267.900-3 e no setor da SESP/GOFS/FI para demais providências 05/12/2023 - APENSADO AO PROTOCOLO 18.267.900-3 (AMBOS ARQUIVADOS)
A45: 19.092.656-7 | B45: SRP - aquisição de placas balísticas nível III com capa - ATA de Registro de Preço PE-870/2021 - Protocolo 175297693 | C45: Eduarda | D45: CURITIBA | E45: TODAS UNIDADES - PCP | F45: 44883 | G45: R$ 120.000,00 | K45: INVESTIMENTO | L45: REGISTRO DE PREÇO (ESTADUAL) | N45: SOBRESTADO | O45: Jorge Aurélio Perito de Bem | P45: Leonel Letnar Junior | Q45: PCP/DA/GAA/COMPRAS | R45: 44917 | S45: 30/11/2022 - Encaminhado ao Grupo Auxiliar Orçamentário para informação de Pré empenho e empenho01/12/2022 - Protocolo se encontra na PCP/DA - PCP/DA/GAA/CHEFE, aguardando disponibilidade orçamentáriade investimento.06/12/2022 - Se encontra sobrestar pela PCP/DA/GAA/CHEFE.16/12/2022 - Se encontra na PCP/DA/GAA/CHEFE sobrestar até segunda ordem11/01/2023 - Se encontra na PCP/DA/GAA/COMPRAS para demais providências 18/04/2023 - Aguardando ser encaminhado, mas está pronto 30/08/2023 - Sobrestado desde 25/01/2023
A46: 19.658.195-2 | B46: Abertura de procedimento Licitatório visando a aquisição de uniformes ( jalecos e aventais) | C46: Raphael | D46: CURITIBA | E46: TODAS UNIDADES - PCP | F46: 44887 | G46: R$ 141.558,00 | H46: 45508 | I46: 21/08/202328/08/2023 | J46: 17/10/2023 22/11/2023 - aventais | K46: CUSTEIO | L46: LICITAÇÃO | N46: FINALIZADO | O46: Josué Tadeu Borba | P46: Bruno Trevisan Zacharias | Q46: SESP/DG/NFS | R46: 45499 | S46: 08/11/2022 - Encaminhado para DA/DIV para análise e providências01/12/2022 - Protocolo se encontra para análise e providências na DA/DIV.06/12/2022 - Se encontra na PCP/DA/GAA/COMPRAS para providencias18/01/2023 - Se encontra na PCP/DA/GAOFS para análise02/02/2023 - Se encontra na SESP/SL para demais providências 30/08/2023 - Contrato e nota de empenho enviado ao fornecedor em 21/08/2023 e 28/08/2023, aguardando entrega 24/10/2023 - Material entregue Almoxarifado na data 17/10/2023 22/11/2023 - Recebido no dia 22/11/2023 no almoxarifado os aventais | T46: #REF! | U46: #REF!
A47: 19.363.539-3 | B47: SRP de contratação de controlador de acesso - aquisição através do sistema de registro de preço do pregão eletrônico no. 912/2021, de controlador de acesso, para atender a demanda do órgão da Polícia Científica do Paraná. | C47: Rodrigo Bianchini | D47: CURITIBA | E47: SEDE - TARUMÃ E CENTRAL | F47: 44790 | G47: R$ 367.542,72 | H47: SIM | I47: serviço | J47: Sim | K47: CUSTEIO | L47: REGISTRO DE PREÇO (ESTADUAL) | N47: ARQUIVADO | O47: Luis Henrique Ferreira de Moraes | P47: Jorge Aurélio Perito de Bem E Patrícia Doubas Cancelier | Q47: PCP/DA/GAA/CONTRATOS | R47: 45019 | S47: 01/12/2022 - Aguardando conclusão de cadastro em PCP/DA/GAA/COMPRAS.06/12/2022 - Se encontra na PCP/DA/GAA/COMPRAS para demais providências.16/12/2022 - Se encontra na SESP/DG para demais providências18/01/2023 - Se encontra na PCP/DA/GAA/COMPRAS para demais providências (atualização de orçamento) 28/02/2023 - Encamminhado a SESP/GAS/SC para demais providências | T47: #REF! | U47: #REF!
A48: 19.727.546-4 | B48: SRP de contratação de controlador de acesso - aquisição através do sistema de registro de preço do pregão eletrônico no. 912/2021, de controlador de acesso, para atender a demanda do órgão da Polícia Científica do Paraná. | C48: Rodrigo Bianchini | D48: CURITIBA | E48: UNIDADE PARANAGUÁ | F48: 44882 | G48: R$ 83.830,56 | H48: SIM | I48: serviço | J48: Sim | K48: CUSTEIO | L48: REGISTRO DE PREÇO (ESTADUAL) | N48: ARQUIVADO | O48: Vanessa Regina Kluppel Cunha | P48: Thiago Congrossi Moreira dos Santos | Q48: PCP/DA/GAA/CONTRATOS | R48: 45021 | S48: 01/12/2022 - Aguardando conclusão de cadastro em PCP/DA/GAA/COMPRAS.06/12/2022 - Se encontra na PCP/DA/DIV para demais providências.16/12/2022 - Se encontra na SESP/DG para demais providências09/01/2023 - Se encontra na SESP/GOFS/FI para demais providências18/01/2023 - Se encontra na PCP/DA/GAA/COMPRAS para demais providências (atualização de orçamento) 28/02/2023 - Encamminhado a SESP/GAS/SC para demais providências | T48: #REF! | U48: #REF!
A49: 19.761.614-8 | B49: SRP Material de Limpeza - aquisição através do sistema de registro de preço do pregão eletrônico no. 594/2021, de material de limpeza, para atender a demanda do órgão da Polícia Científica do Paraná. | C49: Eduarda/Raphael | D49: CURITIBA | E49: TODAS UNIDADES - PCP | F49: 44890 | G49: R$ 2.539,00 | H49: SIM | I49: 44902 | J49: 44985 | K49: CUSTEIO | L49: REGISTRO DE PREÇO (ESTADUAL) | N49: ARQUIVADO | O49: Não se aplica | P49: Não se aplica | Q49: PCP/DA/GAOFS | R49: 44998 | S49: 01/12/2022 - Aguardando conclusão de cadastro em PCP/DA/GAA/COMPRAS. 02/12/2022 - Encaminhado a Chefia da divisão administrativa da para análise e manifestação.06/12/2022 - Se encontra na PCP/DIR/GAB para demais providências. 12/12/2022 - Encaminhado ao almoxarifado para aguardar a entrega do material 09/01/2023 - Se encontra na PCP/DA/GAOFS aguardando pagamento18/01/2023 - Se encontra na PCP/DA/GAOFS para demais providências08/01/2023 - Se encontra na PCP/DA/GAA/ALMOX para demais providências Bonzao comercio de prod de limpeza eireli - 15/12/2022 Isanete - 28/02/2023. | T49: #REF! | U49: #REF!
